Workbook

Sheet VERI_TABANI
A1: SABİT SİSTEM PARAMETRELERİ (ARKA PLAN VERİ TABANI - DOKTORA MODELİ v24)
A3: GES Üretim Faktörü (kWh/kW-yıl) | B3: 1675 | C3: kWh/kW-yıl
A4: RES Üretim Faktörü (kWh/kW-yıl) | B4: 2628 | C4: kWh/kW-yıl
A5: GES Kurulum Birim Maliyeti (€/kW) | B5: 592.87 | C5: €/kW
A6: RES Kurulum Birim Maliyeti (€/kW) | B6: 1365.57 | C6: €/kW
A7: Tüketim Mahsuplaşma Fiyatı (≤%100) (€/kWh) | B7: 0.0934 | C7: €/kWh
A8: Şebekeye Satış Fiyatı (>%100) (€/kWh) | B8: 0.0594 | C8: €/kWh
A9: Doğalgaz Fiyatı (€/Sm3) | B9: 0.2746 | C9: €/Sm3
A10: Yeşil H2 Tesis Kurulum Birim Maliyeti (€/kg H2/yıl) | B10: 7.42 | C10: €/kg H2/yıl
A11: Gri H2 Tesis Kurulum Birim Maliyeti (€/kg H2/yıl) | B11: 3.33 | C11: €/kg H2/yıl
A12: H2 Injection Retrofit Maliyeti (€/kg H2/yıl) | B12: 0.343 | C12: €/kg H2/yıl
A13: Türkiye Şebeke Emisyon Faktörü (tCO2/kWh) | B13: 0.0006242 | C13: tCO2/kWh
A14: GES LCA Footprint (tCO2/kWh) | B14: 6e-05 | C14: tCO2/kWh
... A18: Doğalgaz Emisyon Faktörü (tCO2/Sm3) | B18: 0.00202 | C18: tCO2/Sm3
A20: PERİYOT BAZLI DÖNÜŞÜM VERİ KÜMELERİ (2025 – 2053 TAHMİN PROJEKSİYONLARI)
A22: Periyot | B22: Yıl Sayısı | C22: Orijinal Üretim (Ton) | D22: Elektrik Tüketimi (kWh) | E22: Doğalgaz Tüketimi (Sm3) | F22: Hidrojen Tüketimi (kg) | G22: SKDM Karbon Fiyatı (€/tCO2)
A23: 2025 – 2030 | B23: 6 | C23: 4304837.4 | D23: 1.3625871e+09 | E23: 5.2108659e+08 | F23: 10868199 | G23: 106.5
A24: 2031 – 2035 | B24: 5 | C24: 4136473 | D24: 1.3111603e+09 | E24: 5.0004277e+08 | F24: 10429292 | G24: 151.1
A25: 2036 – 2040 | B25: 5 | C25: 4635662.5 | D25: 1.4708613e+09 | E25: 5.5986454e+08 | F25: 11676983 | G25: 205.4
A26: 2041 – 2045 | B26: 5 | C26: 5134852 | D26: 1.6305622e+09 | E26: 6.1968631e+08 | F26: 12924673 | G26: 276.6
A27: 2046 – 2050 | B27: 5 | C27: 5634041.6 | D27: 1.7902632e+09 | E27: 6.7950808e+08 | F27: 14172364 | G27: 369.4
A28: 2051 – 2053 | B28: 3 | C28: 3620035.9 | D28: 1.1508144e+09 | E28: 4.364193e+08 | F28: 9102310 | G28: 390.6
A29: 2025 – 2053 TOPLAM | B29: =SUM(B23:B28) | C29: =SUM(C23:C28) | D29: =SUM(D23:D28) | E29: =SUM(E23:E28) | F29: =SUM(F23:F28) | G29: =AVERAGE(G23:G28)

Sheet DASHBOARD
A1: CAM ENERJİ FABRİKASI - DOKTORA TEZİ KARAR DESTEK VE KONTROL DASHBOARD'U (v24)
A2: SKDM Sürecinde Hibrit Enerji ve Hidrojen Entegrasyonu Bağımsız & Bütünleşik Analiz Mimarisi (v24)
A4: 1. KULLANICI SENARYO SEÇİMLERİ VE HEDEFLER
A5: Hedef Yenilenebilir Elektrik Oranı (%) | B5: 1.12 | C5: Fabrikanın toplam elektrik tüketimine göre hedeflenen yenilenebilir enerji oranı (Örn. %112)
A6: GES Katkı Oranı (% Tüketime Göre) | B6: 0.6 | C6: Toplam tüketimin Güneş Santralinden (GES) karşılanacak yüzdesi
A7: RES Katkı Oranı (% Tüketime Göre) | B7: 0.52 | C7: Toplam tüketimin Rüzgar Santralinden (RES) karşılanacak yüzdesi
A8: Hidrojen Kullanım Durumu / Tipi | B8: 1 | C8: 1 = Yeşil Hidrojen (%20 H2), -1 = Gri Hidrojen (%20 H2), 0 = Hidrojen Yok (%0 H2)
A9: Girilmiş GES + RES Toplamı (%) | B9: =B6+B7 | C9: =IF(ABS((B6+B7)-B5)>0.0001, "⚠️ UYARI: GES + RES Payları Toplamı (" & TEXT(B6+B7, "0.0%") & ") Hedef Orana (" & TEXT(B5, "0.0%") & ") Eşit Değildir!", "✅ ORAN DENGESİ UYUMLU: GES + RES Payı Toplamı Hedef Oran ile Eşittir.")
A10: Master Mod Seçim Şalteri (1=Mod 1, 2=Mod 2, 3=Mod 3) | B10: 1 | C10: 1 = Mod 1 (Enerji Oranı Odaklı), 2 = Mod 2 (Bütçe Odaklı), 3 = Mod 3 (Karbon Hedef Odaklı)
A11: Maksimum Yatırım Bütçesi Kısıtı (€) | B11: 200000000 | C11: Mod 2 için üst yatırım bütçesi limiti (Örn. 200 M€)
A12: Minimum Karbon Engelleme Hedefi (tCO₂) | B12: 5000000 | C12: Mod 3 için alt emisyon azaltım hedefi (Örn. 5 M tCO2)
A14: 2. PERİYOT BAZLI BAĞIMSIZ DAL (GES, RES, H2) VE BÜTÜNLEŞİK SİNERJİ ANALİZİ (v24)
A15: PERİYOT VE TÜKETİM VERİLERİ | D15: 1. DAL: GÜNEŞ ENERJİSİ SANTRALİ (GES) BAĞIMSIZ ANALİZ PANOSU | O15: 2. DAL: RÜZGAR ENERJİSİ SANTRALİ (RES) BAĞIMSIZ ANALİZ PANOSU | Z15: 3. DAL: HİDROJEN ENTEGRASYONU BAĞIMSIZ ANALİZ PANOSU | AK15: 4. DAL: BÜTÜNLEŞİK HİBRİT SİNERJİ PANOSU
A16: Periyot | B16: Toplam Üretim (Ton) | C16: Elektrik Tüketimi (kWh) | D16: GES Üretimi (kWh) | E16: Toplam GES Gücü (kW) | F16: İlave GES Gücü (kW) | G16: İlave GES Yatırımı (€) | H16: GES Mahsuplaşma Tasarrufu (€) | I16: GES Net SKDM Karbon Tasarrufu (€) | J16: GES Toplam Fayda (€) | K16: GES Tekil LCA Oranı (%) | L16: GES Mahsuplaşma Geri Ödeme (Yıl) | M16: GES Karbon Kazancı Geri Ödeme (Yıl) | N16: GES Kollektif Geri Ödeme (Yıl) | O16: RES Üretimi (kWh) | P16: Toplam RES Gücü (kW) | Q16: İlave RES Gücü (kW) | R16: İlave RES Yatırımı (€) | S16: RES Mahsuplaşma Tasarrufu (€) | T16: RES Net SKDM Karbon Tasarrufu (€) | U16: RES Toplam Fayda (€) | V16: RES Tekil LCA Oranı (%) | W16: RES Mahsuplaşma Geri Ödeme (Yıl) | X16: RES Karbon Kazancı Geri Ödeme (Yıl) | Y16: RES Kollektif Geri Ödeme (Yıl) | Z16: Kullanılmayan DG (Sm3) | AA16: H2 Tüketimi (kg) | AB16: H2 Yıllık Kapasitesi (kg/yıl) | AC16: İlave H2 Tesis/Retrofit Yatırımı (€) | AD16: H2 DG Maliyet Kazancı (€) | AE16: H2 Net SKDM Karbon Kazancı (€) | AF16: H2 Toplam Fayda (€) | AG16: H2 Tekil LCA Oranı (%) | AH16: H2 Mahsuplaşma Geri Ödeme (Yıl) | AI16: H2 Karbon Kazancı Geri Ödeme (Yıl) | AJ16: H2 Kollektif Geri Ödeme (Yıl) | AK16: GES Yatırımı (€) | AL16: RES Yatırımı (€) | AM16: H2 Tesis Yatırımı (€) | AN16: Toplam Kümülatif Yatırım (€) | AO16: GES Karbon Kazancı (tCO2) | AP16: RES Karbon Kazancı (tCO2) | AQ16: H2 Karbon Kazancı (tCO2) | AR16: Net Karbon Kazancı (tCO2) | AS16: Net Karbon Kazancı (€) | AT16: Birleşik LCA Oranı (%) | AU16: GES Toplam Faydası (€) | AV16: RES Toplam Faydası (€) | AW16: H2 Toplam Faydası (€) | AX16: Periyot Toplam Net Faydası (€) | AY16: Kollektif Mahsuplaşma Geri Ödeme (Yıl) | AZ16: Kollektif Karbon Kazancı Geri Ödeme (Yıl) | BA16: Kollektif Basit Geri Ödeme Süresi (Yıl)
A17: =VERI_TABANI!A23 | B17: =VERI_TABANI!C23 | C17: =VERI_TABANI!D23 | D17: =C17*DASHBOARD!$B$6 | E17: =(D17/VERI_TABANI!B23)/VERI_TABANI!$B$3 | F17: =E17 | G17: =F17*VERI_TABANI!$B$5 | H17: =MIN(C17, D17)*VERI_TABANI!$B$7 + MAX(0, D17-C17)*VERI_TABANI!$B$8 | I17: =D17*(VERI_TABANI!$B$13-VERI_TABANI!$B$14)*VERI_TABANI!G23 | J17: =H17+I17 | K17: =IFERROR((D17*VERI_TABANI!$B$14)/(D17*VERI_TABANI!$B$13), 0) | L17: =IFERROR(G17/(H17/VERI_TABANI!B23), 0) | M17: =IFERROR(G17/(I17/VERI_TABANI!B23), 0) | N17: =IFERROR(G17/(J17/VERI_TABANI!B23), 0) | O17: =C17*DASHBOARD!$B$7 | P17: =(O17/VERI_TABANI!B23)/VERI_TABANI!$B$4 | Q17: =P17 | R17: =Q17*VERI_TABANI!$B$6 | S17: =MIN(MAX(0, C17-D17), O17)*VERI_TABANI!$B$7 + MAX(0, O17-MAX(0, C17-D17))*VERI_TABANI!$B$8 | T17: =O17*(VERI_TABANI!$B$13-VERI_TABANI!$B$15)*VERI_TABANI!G23 | U17: =S17+T17 | V17: =IFERROR((O17*VERI_TABANI!$B$15)/(O17*VERI_TABANI!$B$13), 0) | W17: =IFERROR(R17/(S17/VERI_TABANI!B23), 0) | X17: =IFERROR(R17/(T17/VERI_TABANI!B23), 0) | Y17: =IFERROR(R17/(U17/VERI_TABANI!B23), 0) | Z17: =IF(ABS(DASHBOARD!$B$8)=1, VERI_TABANI!E23*(1-0.928), 0) | AA17: =IF(ABS(DASHBOARD!$B$8)=1, VERI_TABANI!F23, 0) | AB17: =AA17/VERI_TABANI!B23 | AC17: =IF(DASHBOARD!$B$8=1, AB17*(VERI_TABANI!$B$10+VERI_TABANI!$B$12), IF(DASHBOARD!$B$8=-1, AB17*(VERI_TABANI!$B$11+VERI_TABANI!$B$12), 0)) | AD17: =Z17*VERI_TABANI!$B$9 | AE17: =Z17*0.00206091519919798*VERI_TABANI!G23 | AF17: =AD17+AE17 | AG17: =IFERROR((IF($B$8=1, AA17*VERI_TABANI!B16, IF($B$8=-1, AA17*VERI_TABANI!B17, 0))) / (Z17*VERI_TABANI!B18), 0) | AH17: =IFERROR(AC17/(AD17/VERI_TABANI!B23), 0) | AI17: =IFERROR(AC17/(AE17/VERI_TABANI!B23), 0) | AJ17: =IFERROR(AC17/(AF17/VERI_TABANI!B23), 0) | AK17: =G17 | AL17: =R17 | AM17: =AC17 | AN17: =AK17+AL17+AM17 | AO17: =D17*(VERI_TABANI!$B$13-VERI_TABANI!$B$14) | AP17: =O17*(VERI_TABANI!$B$13-VERI_TABANI!$B$15) | AQ17: =IF($B$8=1, AA17*(0.00202-VERI_TABANI!B16), IF($B$8=-1, AA17*(0.00202-VERI_TABANI!B17), 0)) | AR17: =AO17+AP17+AQ17 | AS17: =I17+T17+AE17 | AT17: =IFERROR((D17*VERI_TABANI!$B$14 + O17*VERI_TABANI!$B$15 + IF($B$8=1, AA17*VERI_TABANI!B16, IF($B$8=-1, AA17*VERI_TABANI!B17, 0))) / ((D17+O17)*VERI_TABANI!$B$13 + Z17*VERI_TABANI!B18), 0) | AU17: =J17 | AV17: =U17 | AW17: =AF17 | AX17: =AU17+AV17+AW17 | AY17: =IFERROR(AN17/((H17+S17+AD17)/VERI_TABANI!B23), 0) | AZ17: =IFERROR(AN17/((I17+T17+AE17)/VERI_TABANI!B23), 0) | BA17: =IFERROR(AN17/(AX17/VERI_TABANI!B23), 0)
A18: =VERI_TABANI!A24 | B18: =VERI_TABANI!C24 | C18: =VERI_TABANI!D24 | D18: =C18*DASHBOARD!$B$6 | E18: =(D18/VERI_TABANI!B24)/VERI_TABANI!$B$3 | F18: =MAX(0, E18-E17) | G18: =F18*VERI_TABANI!$B$5 | H18: =MIN(C18, D18)*VERI_TABANI!$B$7 + MAX(0, D18-C18)*VERI_TABANI!$B$8 | I18: =D18*(VERI_TABANI!$B$13-VERI_TABANI!$B$14)*VERI_TABANI!G24 | J18: =H18+I18 | K18: =IFERROR((D18*VERI_TABANI!$B$14)/(D18*VERI_TABANI!$B$13), 0) | L18: =IFERROR(G18/(H18/VERI_TABANI!B24), 0) | M18: =IFERROR(G18/(I18/VERI_TABANI!B24), 0) | N18: =IFERROR(G18/(J18/VERI_TABANI!B24), 0) | O18: =C18*DASHBOARD!$B$7 | P18: =(O18/VERI_TABANI!B24)/VERI_TABANI!$B$4 | Q18: =MAX(0, P18-P17) | R18: =Q18*VERI_TABANI!$B$6 | S18: =MIN(MAX(0, C18-D18), O18)*VERI_TABANI!$B$7 + MAX(0, O18-MAX(0, C18-D18))*VERI_TABANI!$B$8 | T18: =O18*(VERI_TABANI!$B$13-VERI_TABANI!$B$15)*VERI_TABANI!G24 | U18: =S18+T18 | V18: =IFERROR((O18*VERI_TABANI!$B$15)/(O18*VERI_TABANI!$B$13), 0) | W18: =IFERROR(R18/(S18/VERI_TABANI!B24), 0) | X18: =IFERROR(R18/(T18/VERI_TABANI!B24), 0) | Y18: =IFERROR(R18/(U18/VERI_TABANI!B24), 0) | Z18: =IF(ABS(DASHBOARD!$B$8)=1, VERI_TABANI!E24*(1-0.928), 0) | AA18: =IF(ABS(DASHBOARD!$B$8)=1, VERI_TABANI!F24, 0) | AB18: =AA18/VERI_TABANI!B24 | AC18: =IF(DASHBOARD!$B$8=1, MAX(0, AB18-AB17)*(VERI_TABANI!$B$10+VERI_TABANI!$B$12), IF(DASHBOARD!$B$8=-1, MAX(0, AB18-AB17)*(VERI_TABANI!$B$11+VERI_TABANI!$B$12), 0)) | AD18: =Z18*VERI_TABANI!$B$9 | AE18: =Z18*0.00206091519919798*VERI_TABANI!G24 | AF18: =AD18+AE18 | AG18: =IFERROR((IF($B$8=1, AA18*VERI_TABANI!B16, IF($B$8=-1, AA18*VERI_TABANI!B17, 0))) / (Z18*VERI_TABANI!B18), 0) | AH18: =IFERROR(AC18/(AD18/VERI_TABANI!B24), 0) | AI18: =IFERROR(AC18/(AE18/VERI_TABANI!B24), 0) | AJ18: =IFERROR(AC18/(AF18/VERI_TABANI!B24), 0) | AK18: =G18 | AL18: =R18 | AM18: =AC18 | AN18: =AK18+AL18+AM18 | AO18: =D18*(VERI_TABANI!$B$13-VERI_TABANI!$B$14) | AP18: =O18*(VERI_TABANI!$B$13-VERI_TABANI!$B$15) | AQ18: =IF($B$8=1, AA18*(0.00202-VERI_TABANI!B16), IF($B$8=-1, AA18*(0.00202-VERI_TABANI!B17), 0)) | AR18: =AO18+AP18+AQ18 | AS18: =I18+T18+AE18 | AT18: =IFERROR((D18*VERI_TABANI!$B$14 + O18*VERI_TABANI!$B$15 + IF($B$8=1, AA18*VERI_TABANI!B16, IF($B$8=-1, AA18*VERI_TABANI!B17, 0))) / ((D18+O18)*VERI_TABANI!$B$13 + Z18*VERI_TABANI!B18), 0) | AU18: =J18 | AV18: =U18 | AW18: =AF18 | AX18: =AU18+AV18+AW18 | AY18: =IFERROR(AN18/((H18+S18+AD18)/VERI_TABANI!B23), 0) | AZ18: =IFERROR(AN18/((I18+T18+AE18)/VERI_TABANI!B23), 0) | BA18: =IFERROR(AN18/(AX18/VERI_TABANI!B24), 0)
A19: =VERI_TABANI!A25 | B19: =VERI_TABANI!C25 | C19: =VERI_TABANI!D25 | D19: =C19*DASHBOARD!$B$6 | E19: =(D19/VERI_TABANI!B25)/VERI_TABANI!$B$3 | F19: =MAX(0, E19-E18) | G19: =F19*VERI_TABANI!$B$5 | H19: =MIN(C19, D19)*VERI_TABANI!$B$7 + MAX(0, D19-C19)*VERI_TABANI!$B$8 | I19: =D19*(VERI_TABANI!$B$13-VERI_TABANI!$B$14)*VERI_TABANI!G25 | J19: =H19+I19 | K19: =IFERROR((D19*VERI_TABANI!$B$14)/(D19*VERI_TABANI!$B$13), 0) | L19: =IFERROR(G19/(H19/VERI_TABANI!B25), 0) | M19: =IFERROR(G19/(I19/VERI_TABANI!B25), 0) | N19: =IFERROR(G19/(J19/VERI_TABANI!B25), 0) | O19: =C19*DASHBOARD!$B$7 | P19: =(O19/VERI_TABANI!B25)/VERI_TABANI!$B$4 | Q19: =MAX(0, P19-P18) | R19: =Q19*VERI_TABANI!$B$6 | S19: =MIN(MAX(0, C19-D19), O19)*VERI_TABANI!$B$7 + MAX(0, O19-MAX(0, C19-D19))*VERI_TABANI!$B$8 | T19: =O19*(VERI_TABANI!$B$13-VERI_TABANI!$B$15)*VERI_TABANI!G25 | U19: =S19+T19 | V19: =IFERROR((O19*VERI_TABANI!$B$15)/(O19*VERI_TABANI!$B$13), 0) | W19: =IFERROR(R19/(S19/VERI_TABANI!B25), 0) | X19: =IFERROR(R19/(T19/VERI_TABANI!B25), 0) | Y19: =IFERROR(R19/(U19/VERI_TABANI!B25), 0) | Z19: =IF(ABS(DASHBOARD!$B$8)=1, VERI_TABANI!E25*(1-0.928), 0) | AA19: =IF(ABS(DASHBOARD!$B$8)=1, VERI_TABANI!F25, 0) | AB19: =AA19/VERI_TABANI!B25 | AC19: =IF(DASHBOARD!$B$8=1, MAX(0, AB19-AB18)*(VERI_TABANI!$B$10+VERI_TABANI!$B$12), IF(DASHBOARD!$B$8=-1, MAX(0, AB19-AB18)*(VERI_TABANI!$B$11+VERI_TABANI!$B$12), 0)) | AD19: =Z19*VERI_TABANI!$B$9 | AE19: =Z19*0.00206091519919798*VERI_TABANI!G25 | AF19: =AD19+AE19 | AG19: =IFERROR((IF($B$8=1, AA19*VERI_TABANI!B16, IF($B$8=-1, AA19*VERI_TABANI!B17, 0))) / (Z19*VERI_TABANI!B18), 0) | AH19: =IFERROR(AC19/(AD19/VERI_TABANI!B25), 0) | AI19: =IFERROR(AC19/(AE19/VERI_TABANI!B25), 0) | AJ19: =IFERROR(AC19/(AF19/VERI_TABANI!B25), 0) | AK19: =G19 | AL19: =R19 | AM19: =AC19 | AN19: =AK19+AL19+AM19 | AO19: =D19*(VERI_TABANI!$B$13-VERI_TABANI!$B$14) | AP19: =O19*(VERI_TABANI!$B$13-VERI_TABANI!$B$15) | AQ19: =IF($B$8=1, AA19*(0.00202-VERI_TABANI!B16), IF($B$8=-1, AA19*(0.00202-VERI_TABANI!B17), 0)) | AR19: =AO19+AP19+AQ19 | AS19: =I19+T19+AE19 | AT19: =IFERROR((D19*VERI_TABANI!$B$14 + O19*VERI_TABANI!$B$15 + IF($B$8=1, AA19*VERI_TABANI!B16, IF($B$8=-1, AA19*VERI_TABANI!B17, 0))) / ((D19+O19)*VERI_TABANI!$B$13 + Z19*VERI_TABANI!B18), 0) | AU19: =J19 | AV19: =U19 | AW19: =AF19 | AX19: =AU19+AV19+AW19 | AY19: =IFERROR(AN19/((H19+S19+AD19)/VERI_TABANI!B23), 0) | AZ19: =IFERROR(AN19/((I19+T19+AE19)/VERI_TABANI!B23), 0) | BA19: =IFERROR(AN19/(AX19/VERI_TABANI!B25), 0)
A20: =VERI_TABANI!A26 | B20: =VERI_TABANI!C26 | C20: =VERI_TABANI!D26 | D20: =C20*DASHBOARD!$B$6 | E20: =(D20/VERI_TABANI!B26)/VERI_TABANI!$B$3 | F20: =MAX(0, E20-E19) | G20: =F20*VERI_TABANI!$B$5 | H20: =MIN(C20, D20)*VERI_TABANI!$B$7 + MAX(0, D20-C20)*VERI_TABANI!$B$8 | I20: =D20*(VERI_TABANI!$B$13-VERI_TABANI!$B$14)*VERI_TABANI!G26 | J20: =H20+I20 | K20: =IFERROR((D20*VERI_TABANI!$B$14)/(D20*VERI_TABANI!$B$13), 0) | L20: =IFERROR(G20/(H20/VERI_TABANI!B26), 0) | M20: =IFERROR(G20/(I20/VERI_TABANI!B26), 0) | N20: =IFERROR(G20/(J20/VERI_TABANI!B26), 0) | O20: =C20*DASHBOARD!$B$7 | P20: =(O20/VERI_TABANI!B26)/VERI_TABANI!$B$4 | Q20: =MAX(0, P20-P19) | R20: =Q20*VERI_TABANI!$B$6 | S20: =MIN(MAX(0, C20-D20), O20)*VERI_TABANI!$B$7 + MAX(0, O20-MAX(0, C20-D20))*VERI_TABANI!$B$8 | T20: =O20*(VERI_TABANI!$B$13-VERI_TABANI!$B$15)*VERI_TABANI!G26 | U20: =S20+T20 | V20: =IFERROR((O20*VERI_TABANI!$B$15)/(O20*VERI_TABANI!$B$13), 0) | W20: =IFERROR(R20/(S20/VERI_TABANI!B26), 0) | X20: =IFERROR(R20/(T20/VERI_TABANI!B26), 0) | Y20: =IFERROR(R20/(U20/VERI_TABANI!B26), 0) | Z20: =IF(ABS(DASHBOARD!$B$8)=1, VERI_TABANI!E26*(1-0.928), 0) | AA20: =IF(ABS(DASHBOARD!$B$8)=1, VERI_TABANI!F26, 0) | AB20: =AA20/VERI_TABANI!B26 | AC20: =IF(DASHBOARD!$B$8=1, MAX(0, AB20-AB19)*(VERI_TABANI!$B$10+VERI_TABANI!$B$12), IF(DASHBOARD!$B$8=-1, MAX(0, AB20-AB19)*(VERI_TABANI!$B$11+VERI_TABANI!$B$12), 0)) | AD20: =Z20*VERI_TABANI!$B$9 | AE20: =Z20*0.00206091519919798*VERI_TABANI!G26 | AF20: =AD20+AE20 | AG20: =IFERROR((IF($B$8=1, AA20*VERI_TABANI!B16, IF($B$8=-1, AA20*VERI_TABANI!B17, 0))) / (Z20*VERI_TABANI!B18), 0) | AH20: =IFERROR(AC20/(AD20/VERI_TABANI!B26), 0) | AI20: =IFERROR(AC20/(AE20/VERI_TABANI!B26), 0) | AJ20: =IFERROR(AC20/(AF20/VERI_TABANI!B26), 0) | AK20: =G20 | AL20: =R20 | AM20: =AC20 | AN20: =AK20+AL20+AM20 | AO20: =D20*(VERI_TABANI!$B$13-VERI_TABANI!$B$14) | AP20: =O20*(VERI_TABANI!$B$13-VERI_TABANI!$B$15) | AQ20: =IF($B$8=1, AA20*(0.00202-VERI_TABANI!B16), IF($B$8=-1, AA20*(0.00202-VERI_TABANI!B17), 0)) | AR20: =AO20+AP20+AQ20 | AS20: =I20+T20+AE20 | AT20: =IFERROR((D20*VERI_TABANI!$B$14 + O20*VERI_TABANI!$B$15 + IF($B$8=1, AA20*VERI_TABANI!B16, IF($B$8=-1, AA20*VERI_TABANI!B17, 0))) / ((D20+O20)*VERI_TABANI!$B$13 + Z20*VERI_TABANI!B18), 0) | AU20: =J20 | AV20: =U20 | AW20: =AF20 | AX20: =AU20+AV20+AW20 | AY20: =IFERROR(AN20/((H20+S20+AD20)/VERI_TABANI!B23), 0) | AZ20: =IFERROR(AN20/((I20+T20+AE20)/VERI_TABANI!B23), 0) | BA20: =IFERROR(AN20/(AX20/VERI_TABANI!B26), 0)
A21: =VERI_TABANI!A27 | B21: =VERI_TABANI!C27 | C21: =VERI_TABANI!D27 | D21: =C21*DASHBOARD!$B$6 | E21: =(D21/VERI_TABANI!B27)/VERI_TABANI!$B$3 | F21: =MAX(0, E21-E20) | G21: =F21*VERI_TABANI!$B$5 | H21: =MIN(C21, D21)*VERI_TABANI!$B$7 + MAX(0, D21-C21)*VERI_TABANI!$B$8 | I21: =D21*(VERI_TABANI!$B$13-VERI_TABANI!$B$14)*VERI_TABANI!G27 | J21: =H21+I21 | K21: =IFERROR((D21*VERI_TABANI!$B$14)/(D21*VERI_TABANI!$B$13), 0) | L21: =IFERROR(G21/(H21/VERI_TABANI!B27), 0) | M21: =IFERROR(G21/(I21/VERI_TABANI!B27), 0) | N21: =IFERROR(G21/(J21/VERI_TABANI!B27), 0) | O21: =C21*DASHBOARD!$B$7 | P21: =(O21/VERI_TABANI!B27)/VERI_TABANI!$B$4 | Q21: =MAX(0, P21-P20) | R21: =Q21*VERI_TABANI!$B$6 | S21: =MIN(MAX(0, C21-D21), O21)*VERI_TABANI!$B$7 + MAX(0, O21-MAX(0, C21-D21))*VERI_TABANI!$B$8 | T21: =O21*(VERI_TABANI!$B$13-VERI_TABANI!$B$15)*VERI_TABANI!G27 | U21: =S21+T21 | V21: =IFERROR((O21*VERI_TABANI!$B$15)/(O21*VERI_TABANI!$B$13), 0) | W21: =IFERROR(R21/(S21/VERI_TABANI!B27), 0) | X21: =IFERROR(R21/(T21/VERI_TABANI!B27), 0) | Y21: =IFERROR(R21/(U21/VERI_TABANI!B27), 0) | Z21: =IF(ABS(DASHBOARD!$B$8)=1, VERI_TABANI!E27*(1-0.928), 0) | AA21: =IF(ABS(DASHBOARD!$B$8)=1, VERI_TABANI!F27, 0) | AB21: =AA21/VERI_TABANI!B27 | AC21: =IF(DASHBOARD!$B$8=1, MAX(0, AB21-AB20)*(VERI_TABANI!$B$10+VERI_TABANI!$B$12), IF(DASHBOARD!$B$8=-1, MAX(0, AB21-AB20)*(VERI_TABANI!$B$11+VERI_TABANI!$B$12), 0)) | AD21: =Z21*VERI_TABANI!$B$9 | AE21: =Z21*0.00206091519919798*VERI_TABANI!G27 | AF21: =AD21+AE21 | AG21: =IFERROR((IF($B$8=1, AA21*VERI_TABANI!B16, IF($B$8=-1, AA21*VERI_TABANI!B17, 0))) / (Z21*VERI_TABANI!B18), 0) | AH21: =IFERROR(AC21/(AD21/VERI_TABANI!B27), 0) | AI21: =IFERROR(AC21/(AE21/VERI_TABANI!B27), 0) | AJ21: =IFERROR(AC21/(AF21/VERI_TABANI!B27), 0) | AK21: =G21 | AL21: =R21 | AM21: =AC21 | AN21: =AK21+AL21+AM21 | AO21: =D21*(VERI_TABANI!$B$13-VERI_TABANI!$B$14) | AP21: =O21*(VERI_TABANI!$B$13-VERI_TABANI!$B$15) | AQ21: =IF($B$8=1, AA21*(0.00202-VERI_TABANI!B16), IF($B$8=-1, AA21*(0.00202-VERI_TABANI!B17), 0)) | AR21: =AO21+AP21+AQ21 | AS21: =I21+T21+AE21 | AT21: =IFERROR((D21*VERI_TABANI!$B$14 + O21*VERI_TABANI!$B$15 + IF($B$8=1, AA21*VERI_TABANI!B16, IF($B$8=-1, AA21*VERI_TABANI!B17, 0))) / ((D21+O21)*VERI_TABANI!$B$13 + Z21*VERI_TABANI!B18), 0) | AU21: =J21 | AV21: =U21 | AW21: =AF21 | AX21: =AU21+AV21+AW21 | AY21: =IFERROR(AN21/((H21+S21+AD21)/VERI_TABANI!B23), 0) | AZ21: =IFERROR(AN21/((I21+T21+AE21)/VERI_TABANI!B23), 0) | BA21: =IFERROR(AN21/(AX21/VERI_TABANI!B27), 0)
A22: =VERI_TABANI!A28 | B22: =VERI_TABANI!C28 | C22: =VERI_TABANI!D28 | D22: =C22*DASHBOARD!$B$6 | E22: =(D22/VERI_TABANI!B28)/VERI_TABANI!$B$3 | F22: =MAX(0, E22-E21) | G22: =F22*VERI_TABANI!$B$5 | H22: =MIN(C22, D22)*VERI_TABANI!$B$7 + MAX(0, D22-C22)*VERI_TABANI!$B$8 | I22: =D22*(VERI_TABANI!$B$13-VERI_TABANI!$B$14)*VERI_TABANI!G28 | J22: =H22+I22 | K22: =IFERROR((D22*VERI_TABANI!$B$14)/(D22*VERI_TABANI!$B$13), 0) | L22: =IFERROR(G22/(H22/VERI_TABANI!B28), 0) | M22: =IFERROR(G22/(I22/VERI_TABANI!B28), 0) | N22: =IFERROR(G22/(J22/VERI_TABANI!B28), 0) | O22: =C22*DASHBOARD!$B$7 | P22: =(O22/VERI_TABANI!B28)/VERI_TABANI!$B$4 | Q22: =MAX(0, P22-P21) | R22: =Q22*VERI_TABANI!$B$6 | S22: =MIN(MAX(0, C22-D22), O22)*VERI_TABANI!$B$7 + MAX(0, O22-MAX(0, C22-D22))*VERI_TABANI!$B$8 | T22: =O22*(VERI_TABANI!$B$13-VERI_TABANI!$B$15)*VERI_TABANI!G28 | U22: =S22+T22 | V22: =IFERROR((O22*VERI_TABANI!$B$15)/(O22*VERI_TABANI!$B$13), 0) | W22: =IFERROR(R22/(S22/VERI_TABANI!B28), 0) | X22: =IFERROR(R22/(T22/VERI_TABANI!B28), 0) | Y22: =IFERROR(R22/(U22/VERI_TABANI!B28), 0) | Z22: =IF(ABS(DASHBOARD!$B$8)=1, VERI_TABANI!E28*(1-0.928), 0) | AA22: =IF(ABS(DASHBOARD!$B$8)=1, VERI_TABANI!F28, 0) | AB22: =AA22/VERI_TABANI!B28 | AC22: =IF(DASHBOARD!$B$8=1, MAX(0, AB22-AB21)*(VERI_TABANI!$B$10+VERI_TABANI!$B$12), IF(DASHBOARD!$B$8=-1, MAX(0, AB22-AB21)*(VERI_TABANI!$B$11+VERI_TABANI!$B$12), 0)) | AD22: =Z22*VERI_TABANI!$B$9 | AE22: =Z22*0.00206091519919798*VERI_TABANI!G28 | AF22: =AD22+AE22 | AG22: =IFERROR((IF($B$8=1, AA22*VERI_TABANI!B16, IF($B$8=-1, AA22*VERI_TABANI!B17, 0))) / (Z22*VERI_TABANI!B18), 0) | AH22: =IFERROR(AC22/(AD22/VERI_TABANI!B28), 0) | AI22: =IFERROR(AC22/(AE22/VERI_TABANI!B28), 0) | AJ22: =IFERROR(AC22/(AF22/VERI_TABANI!B28), 0) | AK22: =G22 | AL22: =R22 | AM22: =AC22 | AN22: =AK22+AL22+AM22 | AO22: =D22*(VERI_TABANI!$B$13-VERI_TABANI!$B$14) | AP22: =O22*(VERI_TABANI!$B$13-VERI_TABANI!$B$15) | AQ22: =IF($B$8=1, AA22*(0.00202-VERI_TABANI!B16), IF($B$8=-1, AA22*(0.00202-VERI_TABANI!B17), 0)) | AR22: =AO22+AP22+AQ22 | AS22: =I22+T22+AE22 | AT22: =IFERROR((D22*VERI_TABANI!$B$14 + O22*VERI_TABANI!$B$15 + IF($B$8=1, AA22*VERI_TABANI!B16, IF($B$8=-1, AA22*VERI_TABANI!B17, 0))) / ((D22+O22)*VERI_TABANI!$B$13 + Z22*VERI_TABANI!B18), 0) | AU22: =J22 | AV22: =U22 | AW22: =AF22 | AX22: =AU22+AV22+AW22 | AY22: =IFERROR(AN22/((H22+S22+AD22)/VERI_TABANI!B23), 0) | AZ22: =IFERROR(AN22/((I22+T22+AE22)/VERI_TABANI!B23), 0) | BA22: =IFERROR(AN22/(AX22/VERI_TABANI!B28), 0)
A23: GENEL TOPLAM | B23: =SUM(B17:B22) | C23: =SUM(C17:C22) | D23: =SUM(D17:D22) | E23: =MAX(E17:E22) | F23: =SUM(F17:F22) | G23: =SUM(G17:G22) | H23: =SUM(H17:H22) | I23: =SUM(I17:I22) | J23: =SUM(J17:J22) | K23: =IFERROR((D23*VERI_TABANI!$B$14)/(D23*VERI_TABANI!$B$13), 0) | L23: =IFERROR(G23/(H23/29), 0) | M23: =IFERROR(G23/(I23/29), 0) | N23: =IFERROR(G23/(J23/29), 0) | O23: =SUM(O17:O22) | P23: =MAX(P17:P22) | Q23: =SUM(Q17:Q22) | R23: =SUM(R17:R22) | S23: =SUM(S17:S22) | T23: =SUM(T17:T22) | U23: =SUM(U17:U22) | V23: =IFERROR((O23*VERI_TABANI!$B$15)/(O23*VERI_TABANI!$B$13), 0) | W23: =IFERROR(R23/(S23/29), 0) | X23: =IFERROR(R23/(T23/29), 0) | Y23: =IFERROR(R23/(U23/29), 0) | Z23: =SUM(Z17:Z22) | AA23: =SUM(AA17:AA22) | AB23: =MAX(AB17:AB22) | AC23: =SUM(AC17:AC22) | AD23: =SUM(AD17:AD22) | AE23: =SUM(AE17:AE22) | AF23: =SUM(AF17:AF22) | AG23: =IFERROR((IF($B$8=1, AA23*VERI_TABANI!B16, IF($B$8=-1, AA23*VERI_TABANI!B17, 0))) / (Z23*VERI_TABANI!B18), 0) | AH23: =IFERROR(AC23/(AD23/29), 0) | AI23: =IFERROR(AC23/(AE23/29), 0) | AJ23: =IFERROR(AC23/(AF23/29), 0) | AK23: =SUM(AK17:AK22) | AL23: =SUM(AL17:AL22) | AM23: =SUM(AM17:AM22) | AN23: =SUM(AN17:AN22) | AO23: =SUM(AO17:AO22) | AP23: =SUM(AP17:AP22) | AQ23: =SUM(AQ17:AQ22) | AR23: =SUM(AR17:AR22) | AS23: =SUM(AS17:AS22) | AT23: =IFERROR((D23*VERI_TABANI!$B$14 + O23*VERI_TABANI!$B$15 + IF($B$8=1, AA23*VERI_TABANI!B16, IF($B$8=-1, AA23*VERI_TABANI!B17, 0))) / ((D23+O23)*VERI_TABANI!$B$13 + Z23*VERI_TABANI!B18), 0) | AU23: =SUM(AU17:AU22) | AV23: =SUM(AV17:AV22) | AW23: =SUM(AW17:AW22) | AX23: =SUM(AX17:AX22) | AY23: =IFERROR(AN23/((H23+S23+AD23)/29), 0) | AZ23: =IFERROR(AN23/((I23+T23+AE23)/29), 0) | BA23: =IFERROR(AN23/(AX23/29), 0)

Sheet SUREKLI_SENARYO_MATRISI
A1: 441 KOMBİNASYONLU TAM DUYARLILIK SİMÜLASYON MATRİSİ (GES %0-%200, RES %0-%200, H2 %0-%20)
A4: Senaryo No | B4: GES Oranı (%) | C4: RES Oranı (%) | D4: H2 Durumu | E4: EPDK Rejimi | F4: Kümülatif Yatırım (€) | G4: 29 Yıllık Net Fayda (€) | H4: Engellenen Net Karbon (tCO2) | I4: Birleşik LCA Oranı (%) | J4: Basit Amortisman Süresi (Yıl) | K4: Karbon/CAPEX (tCO2/€) | L4: LCA Footprint | M4: Net Metering Distance | N4: ROI Ratio | O4: Scope 1+2 Shield Helper | P4: Knee Point Distance | Q4: Wind-Solar Sinerji Match | R4: Payback Sort Helper | S4: Filtered Net Fayda | T4: Filtered Payback | U4: Filtered ROI | V4: Filtered Carbon | W4: Filtered CO2/CAPEX | X4: Filtered EPDK Match | Y4: Filtered LCA % | Z4: Filtered Scope 1+2 | AA4: Filtered Knee Point | AB4: Filtered Synergy
A5: 1 | B5: 0 | C5: 0 | D5: Yok (%0) | E5: =IF((B5+C5)<=1, "Tam Mahsuplaşma (≤%100)", "Kısmi Satış (>%100)") | F5: =((VERI_TABANI!$D$29*B5/VERI_TABANI!$B$29)/VERI_TABANI!$B$3)*VERI_TABANI!$B$5 + ((VERI_TABANI!$D$29*C5/VERI_TABANI!$B$29)/VERI_TABANI!$B$4)*VERI_TABANI!$B$6 + IF(ISNUMBER(SEARCH("Var", D5)), (VERI_TABANI!$F$29/VERI_TABANI!$B$29)*(VERI_TABANI!$B$10+VERI_TABANI!$B$12), 0) | G5: =(((MIN(VERI_TABANI!D23, VERI_TABANI!D23*B5)*VERI_TABANI!$B$7 + MAX(0, VERI_TABANI!D23*B5-VERI_TABANI!D23)*VERI_TABANI!$B$8) + (MIN(MAX(0, VERI_TABANI!D23-VERI_TABANI!D23*B5), VERI_TABANI!D23*C5)*VERI_TABANI!$B$7 + MAX(0, VERI_TABANI!D23*C5-MAX(0, VERI_TABANI!D23-VERI_TABANI!D23*B5))*VERI_TABANI!$B$8) + IF(ABS(IF(ISNUMBER(SEARCH("Var", D5)), 1, IF(ISNUMBER(SEARCH("Gri", D5)), -1, 0)))=1, VERI_TABANI!E23*(1-0.928)*VERI_TABANI!$B$9, 0) + (VERI_TABANI!D23*B5*(VERI_TABANI!$B$13-VERI_TABANI!$B$14)*VERI_TABANI!G23) + (VERI_TABANI!D23*C5*(VERI_TABANI!$B$13-VERI_TABANI!$B$15)*VERI_TABANI!G23) + IF(ABS(IF(ISNUMBER(SEARCH("Var", D5)), 1, IF(ISNUMBER(SEARCH("Gri", D5)), -1, 0)))=1, VERI_TABANI!E23*(1-0.928)*0.00206091519919798*VERI_TABANI!G23, 0)) + ((MIN(VERI_TABANI!D24, VERI_TABANI!D24*B5)*VERI_TABANI!$B$7 + MAX(0, VERI_TABANI!D24*B5-VERI_TABANI!D24)*VERI_TABANI!$B$8) + (MIN(MAX(0, VERI_TABANI!D24-VERI_TABANI!D24*B5), VERI_TABANI!D24*C5)*VERI_TABANI!$B$7 + MAX(0, VERI_TABANI!D24*C5-MAX(0, VERI_TABANI!D24-VERI_TABANI!D24*B5))*VERI_TABANI!$B$8) + IF(ABS(IF(ISNUMBER(SEARCH("Var", D5)), 1, IF(ISNUMBER(SEARCH("Gri", D5)), -1, 0)))=1, VERI_TABANI!E24*(1-0.928)*VERI_TABANI!$B$9, 0) + (VERI_TABANI!D24*B5*(VERI_TABANI!$B$13-VERI_TABANI!$B$14)*VERI_TABANI!G24) + (VERI_TABANI!D24*C5*(VERI_TABANI!$B$13-VERI_TABANI!$B$15)*VERI_TABANI!G24) + IF(ABS(IF(ISNUMBER(SEARCH("Var", D5)), 1, IF(ISNUMBER(SEARCH("Gri", D5)), -1, 0)))=1, VERI_TABANI!E24*(1-0.928)*0.00206091519919798*VERI_TABANI!G24, 0)) + ((MIN(VERI_TABANI!D25, VERI_TABANI!D25*B5)*VERI_TABANI!$B$7 + MAX(0, VERI_TABANI!D25*B5-VERI_TABANI!D25)*VERI_TABANI!$B$8) + (MIN(MAX(0, VERI_TABANI!D25-VERI_TABANI!D25*B5), VERI_TABANI!D25*C5)*VERI_TABANI!$B$7 + MAX(0, VERI_TABANI!D25*C5-MAX(0, VERI_TABANI!D25-VERI_TABANI!D25*B5))*VERI_TABANI!$B$8) + IF(ABS(IF(ISNUMBER(SEARCH("Var", D5)), 1, IF(ISNUMBER(SEARCH("Gri", D5)), -1, 0)))=1, VERI_TABANI!E25*(1-0.928)*VERI_TABANI!$B$9, 0) + (VERI_TABANI!D25*B5*(VERI_TABANI!$B$13-VERI_TABANI!$B$14)*VERI_TABANI!G25) + (VERI_TABANI!D25*C5*(VERI_TABANI!$B$13-VERI_TABANI!$B$15)*VERI_TABANI!G25) + IF(ABS(IF(ISNUMBER(SEARCH("Var", D5)), 1, IF(ISNUMBER(SEARCH("Gri", D5)), -1, 0)))=1, VERI_TABANI!E25*(1-0.928)*0.00206091519919798*VERI_TABANI!G25, 0)) + ((MIN(VERI_TABANI!D26, VERI_TABANI!D26*B5)*VERI_TABANI!$B$7 + MAX(0, VERI_TABANI!D26*B5-VERI_TABANI!D26)*VERI_TABANI!$B$8) + (MIN(MAX(0, VERI_TABANI!D26-VERI_TABANI!D26*B5), VERI_TABANI!D26*C5)*VERI_TABANI!$B$7 + MAX(0, VERI_TABANI!D26*C5-MAX(0, VERI_TABANI!D26-VERI_TABANI!D26*B5))*VERI_TABANI!$B$8) + IF(ABS(IF(ISNUMBER(SEARCH("Var", D5)), 1, IF(ISNUMBER(SEARCH("Gri", D5)), -1, 0)))=1, VERI_TABANI!E26*(1-0.928)*VERI_TABANI!$B$9, 0) + (VERI_TABANI!D26*B5*(VERI_TABANI!$B$13-VERI_TABANI!$B$14)*VERI_TABANI!G26) + (VERI_TABANI!D26*C5*(VERI_TABANI!$B$13-VERI_TABANI!$B$15)*VERI_TABANI!G26) + IF(ABS(IF(ISNUMBER(SEARCH("Var", D5)), 1, IF(ISNUMBER(SEARCH("Gri", D5)), -1, 0)))=1, VERI_TABANI!E26*(1-0.928)*0.00206091519919798*VERI_TABANI!G26, 0)) + ((MIN(VERI_TABANI!D27, VERI_TABANI!D27*B5)*VERI_TABANI!$B$7 + MAX(0, VERI_TABANI!D27*B5-VERI_TABANI!D27)*VERI_TABANI!$B$8) + (MIN(MAX(0, VERI_TABANI!D27-VERI_TABANI!D27*B5), VERI_TABANI!D27*C5)*VERI_TABANI!$B$7 + MAX(0, VERI_TABANI!D27*C5-MAX(0, VERI_TABANI!D27-VERI_TABANI!D27*B5))*VERI_TABANI!$B$8) + IF(ABS(IF(ISNUMBER(SEARCH("Var", D5)), 1, IF(ISNUMBER(SEARCH("Gri", D5)), -1, 0)))=1, VERI_TABANI!E27*(1-0.928)*VERI_TABANI!$B$9, 0) + (VERI_TABANI!D27*B5*(VERI_TABANI!$B$13-VERI_TABANI!$B$14)*VERI_TABANI!G27) + (VERI_TABANI!D27*C5*(VERI_TABANI!$B$13-VERI_TABANI!$B$15)*VERI_TABANI!G27) + IF(ABS(IF(ISNUMBER(SEARCH("Var", D5)), 1, IF(ISNUMBER(SEARCH("Gri", D5)), -1, 0)))=1, VERI_TABANI!E27*(1-0.928)*0.00206091519919798*VERI_TABANI!G27, 0)) + ((MIN(VERI_TABANI!D28, VERI_TABANI!D28*B5)*VERI_TABANI!$B$7 + MAX(0, VERI_TABANI!D28*B5-VERI_TABANI!D28)*VERI_TABANI!$B$8) + (MIN(MAX(0, VERI_TABANI!D28-VERI_TABANI!D28*B5), VERI_TABANI!D28*C5)*VERI_TABANI!$B$7 + MAX(0, VERI_TABANI!D28*C5-MAX(0, VERI_TABANI!D28-VERI_TABANI!D28*B5))*VERI_TABANI!$B$8) + IF(ABS(IF(ISNUMBER(SEARCH("Var", D5)), 1, IF(ISNUMBER(SEARCH("Gri", D5)), -1, 0)))=1, VERI_TABANI!E28*(1-0.928)*VERI_TABANI!$B$9, 0) + (VERI_TABANI!D28*B5*(VERI_TABANI!$B$13-VERI_TABANI!$B$14)*VERI_TABANI!G28) + (VERI_TABANI!D28*C5*(VERI_TABANI!$B$13-VERI_TABANI!$B$15)*VERI_TABANI!G28) + IF(ABS(IF(ISNUMBER(SEARCH("Var", D5)), 1, IF(ISNUMBER(SEARCH("Gri", D5)), -1, 0)))=1, VERI_TABANI!E28*(1-0.928)*0.00206091519919798*VERI_TABANI!G28, 0))) | H5: =(((VERI_TABANI!D23*B5*(VERI_TABANI!$B$13-VERI_TABANI!$B$14)) + (VERI_TABANI!D23*C5*(VERI_TABANI!$B$13-VERI_TABANI!$B$15)) + IF(ISNUMBER(SEARCH("Var", D5)), VERI_TABANI!F23*(0.00202-VERI_TABANI!$B$16), IF(ISNUMBER(SEARCH("Gri", D5)), VERI_TABANI!F23*(0.00202-VERI_TABANI!$B$17), 0))) + ((VERI_TABANI!D24*B5*(VERI_TABANI!$B$13-VERI_TABANI!$B$14)) + (VERI_TABANI!D24*C5*(VERI_TABANI!$B$13-VERI_TABANI!$B$15)) + IF(ISNUMBER(SEARCH("Var", D5)), VERI_TABANI!F24*(0.00202-VERI_TABANI!$B$16), IF(ISNUMBER(SEARCH("Gri", D5)), VERI_TABANI!F24*(0.00202-VERI_TABANI!$B$17), 0))) + ((VERI_TABANI!D25*B5*(VERI_TABANI!$B$13-VERI_TABANI!$B$14)) + (VERI_TABANI!D25*C5*(VERI_TABANI!$B$13-VERI_TABANI!$B$15)) + IF(ISNUMBER(SEARCH("Var", D5)), VERI_TABANI!F25*(0.00202-VERI_TABANI!$B$16), IF(ISNUMBER(SEARCH("Gri", D5)), VERI_TABANI!F25*(0.00202-VERI_TABANI!$B$17), 0))) + ((VERI_TABANI!D26*B5*(VERI_TABANI!$B$13-VERI_TABANI!$B$14)) + (VERI_TABANI!D26*C5*(VERI_TABANI!$B$13-VERI_TABANI!$B$15)) + IF(ISNUMBER(SEARCH("Var", D5)), VERI_TABANI!F26*(0.00202-VERI_TABANI!$B$16), IF(ISNUMBER(SEARCH("Gri", D5)), VERI_TABANI!F26*(0.00202-VERI_TABANI!$B$17), 0))) + ((VERI_TABANI!D27*B5*(VERI_TABANI!$B$13-VERI_TABANI!$B$14)) + (VERI_TABANI!D27*C5*(VERI_TABANI!$B$13-VERI_TABANI!$B$15)) + IF(ISNUMBER(SEARCH("Var", D5)), VERI_TABANI!F27*(0.00202-VERI_TABANI!$B$16), IF(ISNUMBER(SEARCH("Gri", D5)), VERI_TABANI!F27*(0.00202-VERI_TABANI!$B$17), 0))) + ((VERI_TABANI!D28*B5*(VERI_TABANI!$B$13-VERI_TABANI!$B$14)) + (VERI_TABANI!D28*C5*(VERI_TABANI!$B$13-VERI_TABANI!$B$15)) + IF(ISNUMBER(SEARCH("Var", D5)), VERI_TABANI!F28*(0.00202-VERI_TABANI!$B$16), IF(ISNUMBER(SEARCH("Gri", D5)), VERI_TABANI!F28*(0.00202-VERI_TABANI!$B$17), 0)))) | I5: =IFERROR(((VERI_TABANI!$D$29*B5*VERI_TABANI!$B$14 + VERI_TABANI!$D$29*C5*VERI_TABANI!$B$15 + IF(ISNUMBER(SEARCH("Var", D5)), VERI_TABANI!$F$29*VERI_TABANI!$B$16, 0))) / (((VERI_TABANI!$D$29*B5 + VERI_TABANI!$D$29*C5)*VERI_TABANI!$B$13 + IF(ISNUMBER(SEARCH("Var", D5)), VERI_TABANI!$E$29*(1-0.928)*VERI_TABANI!$B$18, 0))), 0) | J5: =IFERROR(F5/(G5/29), 0) | K5: =IF(F5>0, H5/F5, 0) | L5: =IF(F5>0, I5, 1000000000) | M5: =ABS((B5+C5)-1) | N5: =IF(F5>0, (G5/29)/F5, 0) | O5: =IF(AND((B5+C5)>=1, ISNUMBER(SEARCH("Var", D5))), F5, 1000000000) | P5: =IF(F5>0, SQRT((F5/MAX(F$5:F$886))^2 + (1 - H5/MAX(H$5:H$886))^2 + (J5/MAX(J$5:J$886))^2), 1000000000) | Q5: =IF(AND(ABS(B5-0.5)<0.01, ABS(C5-0.5)<0.01, ISNUMBER(SEARCH("Var", D5))), 1, 0) | R5: =IF(F5>0, J5, 1000000000) | S5: =IF(AND(F5<=DASHBOARD!$B$11, H5>=DASHBOARD!$B$13), G5, -1000000000000) | T5: =IF(AND(F5<=DASHBOARD!$B$11, H5>=DASHBOARD!$B$13), R5, 1000000000000) | U5: =IF(AND(F5<=DASHBOARD!$B$11, H5>=DASHBOARD!$B$13), N5, -1000000000000) | V5: =IF(AND(F5<=DASHBOARD!$B$11, H5>=DASHBOARD!$B$13), H5, -1000000000000) | W5: =IF(AND(F5<=DASHBOARD!$B$11, H5>=DASHBOARD!$B$13), K5, -1000000000000) | X5: =IF(AND(F5<=DASHBOARD!$B$11, H5>=DASHBOARD!$B$13), M5, 1000000000000) | Y5: =IF(AND(F5<=DASHBOARD!$B$10, H5>=DASHBOARD!$B$11), L5, 1000000000000) | Z5: =IF(AND(F5<=DASHBOARD!$B$10, H5>=DASHBOARD!$B$11), O5, 1000000000000) | AA5: =IF(AND(F5<=DASHBOARD!$B$10, H5>=DASHBOARD!$B$11), P5, 1000000000000) | AB5: =IF(AND(F5<=DASHBOARD!$B$10, H5>=DASHBOARD!$B$11), Q5, -1000000000000)
A6: 2 | B6: 0 | C6: 0 | D6: Var (%20) | E6: =IF((B6+C6)<=1, "Tam Mahsuplaşma (≤%100)", "Kısmi Satış (>%100)") | F6: =((VERI_TABANI!$D$29*B6/VERI_TABANI!$B$29)/VERI_TABANI!$B$3)*VERI_TABANI!$B$5 + ((VERI_TABANI!$D$29*C6/VERI_TABANI!$B$29)/VERI_TABANI!$B$4)*VERI_TABANI!$B$6 + IF(ISNUMBER(SEARCH("Var", D6)), (VERI_TABANI!$F$29/VERI_TABANI!$B$29)*(VERI_TABANI!$B$10+VERI_TABANI!$B$12), 0) | G6: =(((MIN(VERI_TABANI!D23, VERI_TABANI!D23*B6)*VERI_TABANI!$B$7 + MAX(0, VERI_TABANI!D23*B6-VERI_TABANI!D23)*VERI_TABANI!$B$8) + (MIN(MAX(0, VERI_TABANI!D23-VERI_TABANI!D23*B6), VERI_TABANI!D23*C6)*VERI_TABANI!$B$7 + MAX(0, VERI_TABANI!D23*C6-MAX(0, VERI_TABANI!D23-VERI_TABANI!D23*B6))*VERI_TABANI!$B$8) + IF(ABS(IF(ISNUMBER(SEARCH("Var", D6)), 1, IF(ISNUMBER(SEARCH("Gri", D6)), -1, 0)))=1, VERI_TABANI!E23*(1-0.928)*VERI_TABANI!$B$9, 0) + (VERI_TABANI!D23*B6*(VERI_TABANI!$B$13-VERI_TABANI!$B$14)*VERI_TABANI!G23) + (VERI_TABANI!D23*C6*(VERI_TABANI!$B$13-VERI_TABANI!$B$15)*VERI_TABANI!G23) + IF(ABS(IF(ISNUMBER(SEARCH("Var", D6)), 1, IF(ISNUMBER(SEARCH("Gri", D6)), -1, 0)))=1, VERI_TABANI!E23*(1-0.928)*0.00206091519919798*VERI_TABANI!G23, 0)) + ((MIN(VERI_TABANI!D24, VERI_TABANI!D24*B6)*VERI_TABANI!$B$7 + MAX(0, VERI_TABANI!D24*B6-VERI_TABANI!D24)*VERI_TABANI!$B$8) + (MIN(MAX(0, VERI_TABANI!D24-VERI_TABANI!D24*B6), VERI_TABANI!D24*C6)*VERI_TABANI!$B$7 + MAX(0, VERI_TABANI!D24*C6-MAX(0, VERI_TABANI!D24-VERI_TABANI!D24*B6))*VERI_TABANI!$B$8) + IF(ABS(IF(ISNUMBER(SEARCH("Var", D6)), 1, IF(ISNUMBER(SEARCH("Gri", D6)), -1, 0)))=1, VERI_TABANI!E24*(1-0.928)*VERI_TABANI!$B$9, 0) + (VERI_TABANI!D24*B6*(VERI_TABANI!$B$13-VERI_TABANI!$B$14)*VERI_TABANI!G24) + (VERI_TABANI!D24*C6*(VERI_TABANI!$B$13-VERI_TABANI!$B$15)*VERI_TABANI!G24) + IF(ABS(IF(ISNUMBER(SEARCH("Var", D6)), 1, IF(ISNUMBER(SEARCH("Gri", D6)), -1, 0)))=1, VERI_TABANI!E24*(1-0.928)*0.00206091519919798*VERI_TABANI!G24, 0)) + ((MIN(VERI_TABANI!D25, VERI_TABANI!D25*B6)*VERI_TABANI!$B$7 + MAX(0, VERI_TABANI!D25*B6-VERI_TABANI!D25)*VERI_TABANI!$B$8) + (MIN(MAX(0, VERI_TABANI!D25-VERI_TABANI!D25*B6), VERI_TABANI!D25*C6)*VERI_TABANI!$B$7 + MAX(0, VERI_TABANI!D25*C6-MAX(0, VERI_TABANI!D25-VERI_TABANI!D25*B6))*VERI_TABANI!$B$8) + IF(ABS(IF(ISNUMBER(SEARCH("Var", D6)), 1, IF(ISNUMBER(SEARCH("Gri", D6)), -1, 0)))=1, VERI_TABANI!E25*(1-0.928)*VERI_TABANI!$B$9, 0) + (VERI_TABANI!D25*B6*(VERI_TABANI!$B$13-VERI_TABANI!$B$14)*VERI_TABANI!G25) + (VERI_TABANI!D25*C6*(VERI_TABANI!$B$13-VERI_TABANI!$B$15)*VERI_TABANI!G25) + IF(ABS(IF(ISNUMBER(SEARCH("Var", D6)), 1, IF(ISNUMBER(SEARCH("Gri", D6)), -1, 0)))=1, VERI_TABANI!E25*(1-0.928)*0.00206091519919798*VERI_TABANI!G25, 0)) + ((MIN(VERI_TABANI!D26, VERI_TABANI!D26*B6)*VERI_TABANI!$B$7 + MAX(0, VERI_TABANI!D26*B6-VERI_TABANI!D26)*VERI_TABANI!$B$8) + (MIN(MAX(0, VERI_TABANI!D26-VERI_TABANI!D26*B6), VERI_TABANI!D26*C6)*VERI_TABANI!$B$7 + MAX(0, VERI_TABANI!D26*C6-MAX(0, VERI_TABANI!D26-VERI_TABANI!D26*B6))*VERI_TABANI!$B$8) + IF(ABS(IF(ISNUMBER(SEARCH("Var", D6)), 1, IF(ISNUMBER(SEARCH("Gri", D6)), -1, 0)))=1, VERI_TABANI!E26*(1-0.928)*VERI_TABANI!$B$9, 0) + (VERI_TABANI!D26*B6*(VERI_TABANI!$B$13-VERI_TABANI!$B$14)*VERI_TABANI!G26) + (VERI_TABANI!D26*C6*(VERI_TABANI!$B$13-VERI_TABANI!$B$15)*VERI_TABANI!G26) + IF(ABS(IF(ISNUMBER(SEARCH("Var", D6)), 1, IF(ISNUMBER(SEARCH("Gri", D6)), -1, 0)))=1, VERI_TABANI!E26*(1-0.928)*0.00206091519919798*VERI_TABANI!G26, 0)) + ((MIN(VERI_TABANI!D27, VERI_TABANI!D27*B6)*VERI_TABANI!$B$7 + MAX(0, VERI_TABANI!D27*B6-VERI_TABANI!D27)*VERI_TABANI!$B$8) + (MIN(MAX(0, VERI_TABANI!D27-VERI_TABANI!D27*B6), VERI_TABANI!D27*C6)*VERI_TABANI!$B$7 + MAX(0, VERI_TABANI!D27*C6-MAX(0, VERI_TABANI!D27-VERI_TABANI!D27*B6))*VERI_TABANI!$B$8) + IF(ABS(IF(ISNUMBER(SEARCH("Var", D6)), 1, IF(ISNUMBER(SEARCH("Gri", D6)), -1, 0)))=1, VERI_TABANI!E27*(1-0.928)*VERI_TABANI!$B$9, 0) + (VERI_TABANI!D27*B6*(VERI_TABANI!$B$13-VERI_TABANI!$B$14)*VERI_TABANI!G27) + (VERI_TABANI!D27*C6*(VERI_TABANI!$B$13-VERI_TABANI!$B$15)*VERI_TABANI!G27) + IF(ABS(IF(ISNUMBER(SEARCH("Var", D6)), 1, IF(ISNUMBER(SEARCH("Gri", D6)), -1, 0)))=1, VERI_TABANI!E27*(1-0.928)*0.00206091519919798*VERI_TABANI!G27, 0)) + ((MIN(VERI_TABANI!D28, VERI_TABANI!D28*B6)*VERI_TABANI!$B$7 + MAX(0, VERI_TABANI!D28*B6-VERI_TABANI!D28)*VERI_TABANI!$B$8) + (MIN(MAX(0, VERI_TABANI!D28-VERI_TABANI!D28*B6), VERI_TABANI!D28*C6)*VERI_TABANI!$B$7 + MAX(0, VERI_TABANI!D28*C6-MAX(0, VERI_TABANI!D28-VERI_TABANI!D28*B6))*VERI_TABANI!$B$8) + IF(ABS(IF(ISNUMBER(SEARCH("Var", D6)), 1, IF(ISNUMBER(SEARCH("Gri", D6)), -1, 0)))=1, VERI_TABANI!E28*(1-0.928)*VERI_TABANI!$B$9, 0) + (VERI_TABANI!D28*B6*(VERI_TABANI!$B$13-VERI_TABANI!$B$14)*VERI_TABANI!G28) + (VERI_TABANI!D28*C6*(VERI_TABANI!$B$13-VERI_TABANI!$B$15)*VERI_TABANI!G28) + IF(ABS(IF(ISNUMBER(SEARCH("Var", D6)), 1, IF(ISNUMBER(SEARCH("Gri", D6)), -1, 0)))=1, VERI_TABANI!E28*(1-0.928)*0.00206091519919798*VERI_TABANI!G28, 0))) | H6: =(((VERI_TABANI!D23*B6*(VERI_TABANI!$B$13-VERI_TABANI!$B$14)) + (VERI_TABANI!D23*C6*(VERI_TABANI!$B$13-VERI_TABANI!$B$15)) + IF(ISNUMBER(SEARCH("Var", D6)), VERI_TABANI!F23*(0.00202-VERI_TABANI!$B$16), IF(ISNUMBER(SEARCH("Gri", D6)), VERI_TABANI!F23*(0.00202-VERI_TABANI!$B$17), 0))) + ((VERI_TABANI!D24*B6*(VERI_TABANI!$B$13-VERI_TABANI!$B$14)) + (VERI_TABANI!D24*C6*(VERI_TABANI!$B$13-VERI_TABANI!$B$15)) + IF(ISNUMBER(SEARCH("Var", D6)), VERI_TABANI!F24*(0.00202-VERI_TABANI!$B$16), IF(ISNUMBER(SEARCH("Gri", D6)), VERI_TABANI!F24*(0.00202-VERI_TABANI!$B$17), 0))) + ((VERI_TABANI!D25*B6*(VERI_TABANI!$B$13-VERI_TABANI!$B$14)) + (VERI_TABANI!D25*C6*(VERI_TABANI!$B$13-VERI_TABANI!$B$15)) + IF(ISNUMBER(SEARCH("Var", D6)), VERI_TABANI!F25*(0.00202-VERI_TABANI!$B$16), IF(ISNUMBER(SEARCH("Gri", D6)), VERI_TABANI!F25*(0.00202-VERI_TABANI!$B$17), 0))) + ((VERI_TABANI!D26*B6*(VERI_TABANI!$B$13-VERI_TABANI!$B$14)) + (VERI_TABANI!D26*C6*(VERI_TABANI!$B$13-VERI_TABANI!$B$15)) + IF(ISNUMBER(SEARCH("Var", D6)), VERI_TABANI!F26*(0.00202-VERI_TABANI!$B$16), IF(ISNUMBER(SEARCH("Gri", D6)), VERI_TABANI!F26*(0.00202-VERI_TABANI!$B$17), 0))) + ((VERI_TABANI!D27*B6*(VERI_TABANI!$B$13-VERI_TABANI!$B$14)) + (VERI_TABANI!D27*C6*(VERI_TABANI!$B$13-VERI_TABANI!$B$15)) + IF(ISNUMBER(SEARCH("Var", D6)), VERI_TABANI!F27*(0.00202-VERI_TABANI!$B$16), IF(ISNUMBER(SEARCH("Gri", D6)), VERI_TABANI!F27*(0.00202-VERI_TABANI!$B$17), 0))) + ((VERI_TABANI!D28*B6*(VERI_TABANI!$B$13-VERI_TABANI!$B$14)) + (VERI_TABANI!D28*C6*(VERI_TABANI!$B$13-VERI_TABANI!$B$15)) + IF(ISNUMBER(SEARCH("Var", D6)), VERI_TABANI!F28*(0.00202-VERI_TABANI!$B$16), IF(ISNUMBER(SEARCH("Gri", D6)), VERI_TABANI!F28*(0.00202-VERI_TABANI!$B$17), 0)))) | I6: =IFERROR(((VERI_TABANI!$D$29*B6*VERI_TABANI!$B$14 + VERI_TABANI!$D$29*C6*VERI_TABANI!$B$15 + IF(ISNUMBER(SEARCH("Var", D6)), VERI_TABANI!$F$29*VERI_TABANI!$B$16, 0))) / (((VERI_TABANI!$D$29*B6 + VERI_TABANI!$D$29*C6)*VERI_TABANI!$B$13 + IF(ISNUMBER(SEARCH("Var", D6)), VERI_TABANI!$E$29*(1-0.928)*VERI_TABANI!$B$18, 0))), 0) | J6: =IFERROR(F6/(G6/29), 0) | K6: =IF(F6>0, H6/F6, 0) | L6: =IF(F6>0, I6, 1000000000) | M6: =ABS((B6+C6)-1) | N6: =IF(F6>0, (G6/29)/F6, 0) | O6: =IF(AND((B6+C6)>=1, ISNUMBER(SEARCH("Var", D6))), F6, 1000000000) | P6: =IF(F6>0, SQRT((F6/MAX(F$5:F$886))^2 + (1 - H6/MAX(H$5:H$886))^2 + (J6/MAX(J$5:J$886))^2), 1000000000) | Q6: =IF(AND(ABS(B6-0.5)<0.01, ABS(C6-0.5)<0.01, ISNUMBER(SEARCH("Var", D6))), 1, 0) | R6: =IF(F6>0, J6, 1000000000) | S6: =IF(AND(F6<=DASHBOARD!$B$11, H6>=DASHBOARD!$B$13), G6, -1000000000000) | T6: =IF(AND(F6<=DASHBOARD!$B$11, H6>=DASHBOARD!$B$13), R6, 1000000000000) | U6: =IF(AND(F6<=DASHBOARD!$B$11, H6>=DASHBOARD!$B$13), N6, -1000000000000) | V6: =IF(AND(F6<=DASHBOARD!$B$11, H6>=DASHBOARD!$B$13), H6, -1000000000000) | W6: =IF(AND(F6<=DASHBOARD!$B$11, H6>=DASHBOARD!$B$13), K6, -1000000000000) | X6: =IF(AND(F6<=DASHBOARD!$B$11, H6>=DASHBOARD!$B$13), M6, 1000000000000) | Y6: =IF(AND(F6<=DASHBOARD!$B$10, H6>=DASHBOARD!$B$11), L6, 1000000000000) | Z6: =IF(AND(F6<=DASHBOARD!$B$10, H6>=DASHBOARD!$B$11), O6, 1000000000000) | AA6: =IF(AND(F6<=DASHBOARD!$B$10, H6>=DASHBOARD!$B$11), P6, 1000000000000) | AB6: =IF(AND(F6<=DASHBOARD!$B$10, H6>=DASHBOARD!$B$11), Q6, -1000000000000)
A7: 3 | B7: 0 | C7: 0.1 | D7: Yok (%0) | E7: =IF((B7+C7)<=1, "Tam Mahsuplaşma (≤%100)", "Kısmi Satış (>%100)") | F7: =((VERI_TABANI!$D$29*B7/VERI_TABANI!$B$29)/VERI_TABANI!$B$3)*VERI_TABANI!$B$5 + ((VERI_TABANI!$D$29*C7/VERI_TABANI!$B$29)/VERI_TABANI!$B$4)*VERI_TABANI!$B$6 + IF(ISNUMBER(SEARCH("Var", D7)), (VERI_TABANI!$F$29/VERI_TABANI!$B$29)*(VERI_TABANI!$B$10+VERI_TABANI!$B$12), 0) | G7: =(((MIN(VERI_TABANI!D23, VERI_TABANI!D23*B7)*VERI_TABANI!$B$7 + MAX(0, VERI_TABANI!D23*B7-VERI_TABANI!D23)*VERI_TABANI!$B$8) + (MIN(MAX(0, VERI_TABANI!D23-VERI_TABANI!D23*B7), VERI_TABANI!D23*C7)*VERI_TABANI!$B$7 + MAX(0, VERI_TABANI!D23*C7-MAX(0, VERI_TABANI!D23-VERI_TABANI!D23*B7))*VERI_TABANI!$B$8) + IF(ABS(IF(ISNUMBER(SEARCH("Var", D7)), 1, IF(ISNUMBER(SEARCH("Gri", D7)), -1, 0)))=1, VERI_TABANI!E23*(1-0.928)*VERI_TABANI!$B$9, 0) + (VERI_TABANI!D23*B7*(VERI_TABANI!$B$13-VERI_TABANI!$B$14)*VERI_TABANI!G23) + (VERI_TABANI!D23*C7*(VERI_TABANI!$B$13-VERI_TABANI!$B$15)*VERI_TABANI!G23) + IF(ABS(IF(ISNUMBER(SEARCH("Var", D7)), 1, IF(ISNUMBER(SEARCH("Gri", D7)), -1, 0)))=1, VERI_TABANI!E23*(1-0.928)*0.00206091519919798*VERI_TABANI!G23, 0)) + ((MIN(VERI_TABANI!D24, VERI_TABANI!D24*B7)*VERI_TABANI!$B$7 + MAX(0, VERI_TABANI!D24*B7-VERI_TABANI!D24)*VERI_TABANI!$B$8) + (MIN(MAX(0, VERI_TABANI!D24-VERI_TABANI!D24*B7), VERI_TABANI!D24*C7)*VERI_TABANI!$B$7 + MAX(0, VERI_TABANI!D24*C7-MAX(0, VERI_TABANI!D24-VERI_TABANI!D24*B7))*VERI_TABANI!$B$8) + IF(ABS(IF(ISNUMBER(SEARCH("Var", D7)), 1, IF(ISNUMBER(SEARCH("Gri", D7)), -1, 0)))=1, VERI_TABANI!E24*(1-0.928)*VERI_TABANI!$B$9, 0) + (VERI_TABANI!D24*B7*(VERI_TABANI!$B$13-VERI_TABANI!$B$14)*VERI_TABANI!G24) + (VERI_TABANI!D24*C7*(VERI_TABANI!$B$13-VERI_TABANI!$B$15)*VERI_TABANI!G24) + IF(ABS(IF(ISNUMBER(SEARCH("Var", D7)), 1, IF(ISNUMBER(SEARCH("Gri", D7)), -1, 0)))=1, VERI_TABANI!E24*(1-0.928)*0.00206091519919798*VERI_TABANI!G24, 0)) + ((MIN(VERI_TABANI!D25, VERI_TABANI!D25*B7)*VERI_TABANI!$B$7 + MAX(0, VERI_TABANI!D25*B7-VERI_TABANI!D25)*VERI_TABANI!$B$8) + (MIN(MAX(0, VERI_TABANI!D25-VERI_TABANI!D25*B7), VERI_TABANI!D25*C7)*VERI_TABANI!$B$7 + MAX(0, VERI_TABANI!D25*C7-MAX(0, VERI_TABANI!D25-VERI_TABANI!D25*B7))*VERI_TABANI!$B$8) + IF(ABS(IF(ISNUMBER(SEARCH("Var", D7)), 1, IF(ISNUMBER(SEARCH("Gri", D7)), -1, 0)))=1, VERI_TABANI!E25*(1-0.928)*VERI_TABANI!$B$9, 0) + (VERI_TABANI!D25*B7*(VERI_TABANI!$B$13-VERI_TABANI!$B$14)*VERI_TABANI!G25) + (VERI_TABANI!D25*C7*(VERI_TABANI!$B$13-VERI_TABANI!$B$15)*VERI_TABANI!G25) + IF(ABS(IF(ISNUMBER(SEARCH("Var", D7)), 1, IF(ISNUMBER(SEARCH("Gri", D7)), -1, 0)))=1, VERI_TABANI!E25*(1-0.928)*0.00206091519919798*VERI_TABANI!G25, 0)) + ((MIN(VERI_TABANI!D26, VERI_TABANI!D26*B7)*VERI_TABANI!$B$7 + MAX(0, VERI_TABANI!D26*B7-VERI_TABANI!D26)*VERI_TABANI!$B$8) + (MIN(MAX(0, VERI_TABANI!D26-VERI_TABANI!D26*B7), VERI_TABANI!D26*C7)*VERI_TABANI!$B$7 + MAX(0, VERI_TABANI!D26*C7-MAX(0, VERI_TABANI!D26-VERI_TABANI!D26*B7))*VERI_TABANI!$B$8) + IF(ABS(IF(ISNUMBER(SEARCH("Var", D7)), 1, IF(ISNUMBER(SEARCH("Gri", D7)), -1, 0)))=1, VERI_TABANI!E26*(1-0.928)*VERI_TABANI!$B$9, 0) + (VERI_TABANI!D26*B7*(VERI_TABANI!$B$13-VERI_TABANI!$B$14)*VERI_TABANI!G26) + (VERI_TABANI!D26*C7*(VERI_TABANI!$B$13-VERI_TABANI!$B$15)*VERI_TABANI!G26) + IF(ABS(IF(ISNUMBER(SEARCH("Var", D7)), 1, IF(ISNUMBER(SEARCH("Gri", D7)), -1, 0)))=1, VERI_TABANI!E26*(1-0.928)*0.00206091519919798*VERI_TABANI!G26, 0)) + ((MIN(VERI_TABANI!D27, VERI_TABANI!D27*B7)*VERI_TABANI!$B$7 + MAX(0, VERI_TABANI!D27*B7-VERI_TABANI!D27)*VERI_TABANI!$B$8) + (MIN(MAX(0, VERI_TABANI!D27-VERI_TABANI!D27*B7), VERI_TABANI!D27*C7)*VERI_TABANI!$B$7 + MAX(0, VERI_TABANI!D27*C7-MAX(0, VERI_TABANI!D27-VERI_TABANI!D27*B7))*VERI_TABANI!$B$8) + IF(ABS(IF(ISNUMBER(SEARCH("Var", D7)), 1, IF(ISNUMBER(SEARCH("Gri", D7)), -1, 0)))=1, VERI_TABANI!E27*(1-0.928)*VERI_TABANI!$B$9, 0) + (VERI_TABANI!D27*B7*(VERI_TABANI!$B$13-VERI_TABANI!$B$14)*VERI_TABANI!G27) + (VERI_TABANI!D27*C7*(VERI_TABANI!$B$13-VERI_TABANI!$B$15)*VERI_TABANI!G27) + IF(ABS(IF(ISNUMBER(SEARCH("Var", D7)), 1, IF(ISNUMBER(SEARCH("Gri", D7)), -1, 0)))=1, VERI_TABANI!E27*(1-0.928)*0.00206091519919798*VERI_TABANI!G27, 0)) + ((MIN(VERI_TABANI!D28, VERI_TABANI!D28*B7)*VERI_TABANI!$B$7 + MAX(0, VERI_TABANI!D28*B7-VERI_TABANI!D28)*VERI_TABANI!$B$8) + (MIN(MAX(0, VERI_TABANI!D28-VERI_TABANI!D28*B7), VERI_TABANI!D28*C7)*VERI_TABANI!$B$7 + MAX(0, VERI_TABANI!D28*C7-MAX(0, VERI_TABANI!D28-VERI_TABANI!D28*B7))*VERI_TABANI!$B$8) + IF(ABS(IF(ISNUMBER(SEARCH("Var", D7)), 1, IF(ISNUMBER(SEARCH("Gri", D7)), -1, 0)))=1, VERI_TABANI!E28*(1-0.928)*VERI_TABANI!$B$9, 0) + (VERI_TABANI!D28*B7*(VERI_TABANI!$B$13-VERI_TABANI!$B$14)*VERI_TABANI!G28) + (VERI_TABANI!D28*C7*(VERI_TABANI!$B$13-VERI_TABANI!$B$15)*VERI_TABANI!G28) + IF(ABS(IF(ISNUMBER(SEARCH("Var", D7)), 1, IF(ISNUMBER(SEARCH("Gri", D7)), -1, 0)))=1, VERI_TABANI!E28*(1-0.928)*0.00206091519919798*VERI_TABANI!G28, 0))) | H7: =(((VERI_TABANI!D23*B7*(VERI_TABANI!$B$13-VERI_TABANI!$B$14)) + (VERI_TABANI!D23*C7*(VERI_TABANI!$B$13-VERI_TABANI!$B$15)) + IF(ISNUMBER(SEARCH("Var", D7)), VERI_TABANI!F23*(0.00202-VERI_TABANI!$B$16), IF(ISNUMBER(SEARCH("Gri", D7)), VERI_TABANI!F23*(0.00202-VERI_TABANI!$B$17), 0))) + ((VERI_TABANI!D24*B7*(VERI_TABANI!$B$13-VERI_TABANI!$B$14)) + (VERI_TABANI!D24*C7*(VERI_TABANI!$B$13-VERI_TABANI!$B$15)) + IF(ISNUMBER(SEARCH("Var", D7)), VERI_TABANI!F24*(0.00202-VERI_TABANI!$B$16), IF(ISNUMBER(SEARCH("Gri", D7)), VERI_TABANI!F24*(0.00202-VERI_TABANI!$B$17), 0))) + ((VERI_TABANI!D25*B7*(VERI_TABANI!$B$13-VERI_TABANI!$B$14)) + (VERI_TABANI!D25*C7*(VERI_TABANI!$B$13-VERI_TABANI!$B$15)) + IF(ISNUMBER(SEARCH("Var", D7)), VERI_TABANI!F25*(0.00202-VERI_TABANI!$B$16), IF(ISNUMBER(SEARCH("Gri", D7)), VERI_TABANI!F25*(0.00202-VERI_TABANI!$B$17), 0))) + ((VERI_TABANI!D26*B7*(VERI_TABANI!$B$13-VERI_TABANI!$B$14)) + (VERI_TABANI!D26*C7*(VERI_TABANI!$B$13-VERI_TABANI!$B$15)) + IF(ISNUMBER(SEARCH("Var", D7)), VERI_TABANI!F26*(0.00202-VERI_TABANI!$B$16), IF(ISNUMBER(SEARCH("Gri", D7)), VERI_TABANI!F26*(0.00202-VERI_TABANI!$B$17), 0))) + ((VERI_TABANI!D27*B7*(VERI_TABANI!$B$13-VERI_TABANI!$B$14)) + (VERI_TABANI!D27*C7*(VERI_TABANI!$B$13-VERI_TABANI!$B$15)) + IF(ISNUMBER(SEARCH("Var", D7)), VERI_TABANI!F27*(0.00202-VERI_TABANI!$B$16), IF(ISNUMBER(SEARCH("Gri", D7)), VERI_TABANI!F27*(0.00202-VERI_TABANI!$B$17), 0))) + ((VERI_TABANI!D28*B7*(VERI_TABANI!$B$13-VERI_TABANI!$B$14)) + (VERI_TABANI!D28*C7*(VERI_TABANI!$B$13-VERI_TABANI!$B$15)) + IF(ISNUMBER(SEARCH("Var", D7)), VERI_TABANI!F28*(0.00202-VERI_TABANI!$B$16), IF(ISNUMBER(SEARCH("Gri", D7)), VERI_TABANI!F28*(0.00202-VERI_TABANI!$B$17), 0)))) | I7: =IFERROR(((VERI_TABANI!$D$29*B7*VERI_TABANI!$B$14 + VERI_TABANI!$D$29*C7*VERI_TABANI!$B$15 + IF(ISNUMBER(SEARCH("Var", D7)), VERI_TABANI!$F$29*VERI_TABANI!$B$16, 0))) / (((VERI_TABANI!$D$29*B7 + VERI_TABANI!$D$29*C7)*VERI_TABANI!$B$13 + IF(ISNUMBER(SEARCH("Var", D7)), VERI_TABANI!$E$29*(1-0.928)*VERI_TABANI!$B$18, 0))), 0) | J7: =IFERROR(F7/(G7/29), 0) | K7: =IF(F7>0, H7/F7, 0) | L7: =IF(F7>0, I7, 1000000000) | M7: =ABS((B7+C7)-1) | N7: =IF(F7>0, (G7/29)/F7, 0) | O7: =IF(AND((B7+C7)>=1, ISNUMBER(SEARCH("Var", D7))), F7, 1000000000) | P7: =IF(F7>0, SQRT((F7/MAX(F$5:F$886))^2 + (1 - H7/MAX(H$5:H$886))^2 + (J7/MAX(J$5:J$886))^2), 1000000000) | Q7: =IF(AND(ABS(B7-0.5)<0.01, ABS(C7-0.5)<0.01, ISNUMBER(SEARCH("Var", D7))), 1, 0) | R7: =IF(F7>0, J7, 1000000000) | S7: =IF(AND(F7<=DASHBOARD!$B$11, H7>=DASHBOARD!$B$13), G7, -1000000000000) | T7: =IF(AND(F7<=DASHBOARD!$B$11, H7>=DASHBOARD!$B$13), R7, 1000000000000) | U7: =IF(AND(F7<=DASHBOARD!$B$11, H7>=DASHBOARD!$B$13), N7, -1000000000000) | V7: =IF(AND(F7<=DASHBOARD!$B$11, H7>=DASHBOARD!$B$13), H7, -1000000000000) | W7: =IF(AND(F7<=DASHBOARD!$B$11, H7>=DASHBOARD!$B$13), K7, -1000000000000) | X7: =IF(AND(F7<=DASHBOARD!$B$11, H7>=DASHBOARD!$B$13), M7, 1000000000000) | Y7: =IF(AND(F7<=DASHBOARD!$B$10, H7>=DASHBOARD!$B$11), L7, 1000000000000) | Z7: =IF(AND(F7<=DASHBOARD!$B$10, H7>=DASHBOARD!$B$11), O7, 1000000000000) | AA7: =IF(AND(F7<=DASHBOARD!$B$10, H7>=DASHBOARD!$B$11), P7, 1000000000000) | AB7: =IF(AND(F7<=DASHBOARD!$B$10, H7>=DASHBOARD!$B$11), Q7, -1000000000000)
A8: 4 | B8: 0 | C8: 0.1 | D8: Var (%20) | E8: =IF((B8+C8)<=1, "Tam Mahsuplaşma (≤%100)", "Kısmi Satış (>%100)") | F8: =((VERI_TABANI!$D$29*B8/VERI_TABANI!$B$29)/VERI_TABANI!$B$3)*VERI_TABANI!$B$5 + ((VERI_TABANI!$D$29*C8/VERI_TABANI!$B$29)/VERI_TABANI!$B$4)*VERI_TABANI!$B$6 + IF(ISNUMBER(SEARCH("Var", D8)), (VERI_TABANI!$F$29/VERI_TABANI!$B$29)*(VERI_TABANI!$B$10+VERI_TABANI!$B$12), 0) | G8: =(((MIN(VERI_TABANI!D23, VERI_TABANI!D23*B8)*VERI_TABANI!$B$7 + MAX(0, VERI_TABANI!D23*B8-VERI_TABANI!D23)*VERI_TABANI!$B$8) + (MIN(MAX(0, VERI_TABANI!D23-VERI_TABANI!D23*B8), VERI_TABANI!D23*C8)*VERI_TABANI!$B$7 + MAX(0, VERI_TABANI!D23*C8-MAX(0, VERI_TABANI!D23-VERI_TABANI!D23*B8))*VERI_TABANI!$B$8) + IF(ABS(IF(ISNUMBER(SEARCH("Var", D8)), 1, IF(ISNUMBER(SEARCH("Gri", D8)), -1, 0)))=1, VERI_TABANI!E23*(1-0.928)*VERI_TABANI!$B$9, 0) + (VERI_TABANI!D23*B8*(VERI_TABANI!$B$13-VERI_TABANI!$B$14)*VERI_TABANI!G23) + (VERI_TABANI!D23*C8*(VERI_TABANI!$B$13-VERI_TABANI!$B$15)*VERI_TABANI!G23) + IF(ABS(IF(ISNUMBER(SEARCH("Var", D8)), 1, IF(ISNUMBER(SEARCH("Gri", D8)), -1, 0)))=1, VERI_TABANI!E23*(1-0.928)*0.00206091519919798*VERI_TABANI!G23, 0)) + ((MIN(VERI_TABANI!D24, VERI_TABANI!D24*B8)*VERI_TABANI!$B$7 + MAX(0, VERI_TABANI!D24*B8-VERI_TABANI!D24)*VERI_TABANI!$B$8) + (MIN(MAX(0, VERI_TABANI!D24-VERI_TABANI!D24*B8), VERI_TABANI!D24*C8)*VERI_TABANI!$B$7 + MAX(0, VERI_TABANI!D24*C8-MAX(0, VERI_TABANI!D24-VERI_TABANI!D24*B8))*VERI_TABANI!$B$8) + IF(ABS(IF(ISNUMBER(SEARCH("Var", D8)), 1, IF(ISNUMBER(SEARCH("Gri", D8)), -1, 0)))=1, VERI_TABANI!E24*(1-0.928)*VERI_TABANI!$B$9, 0) + (VERI_TABANI!D24*B8*(VERI_TABANI!$B$13-VERI_TABANI!$B$14)*VERI_TABANI!G24) + (VERI_TABANI!D24*C8*(VERI_TABANI!$B$13-VERI_TABANI!$B$15)*VERI_TABANI!G24) + IF(ABS(IF(ISNUMBER(SEARCH("Var", D8)), 1, IF(ISNUMBER(SEARCH("Gri", D8)), -1, 0)))=1, VERI_TABANI!E24*(1-0.928)*0.00206091519919798*VERI_TABANI!G24, 0)) + ((MIN(VERI_TABANI!D25, VERI_TABANI!D25*B8)*VERI_TABANI!$B$7 + MAX(0, VERI_TABANI!D25*B8-VERI_TABANI!D25)*VERI_TABANI!$B$8) + (MIN(MAX(0, VERI_TABANI!D25-VERI_TABANI!D25*B8), VERI_TABANI!D25*C8)*VERI_TABANI!$B$7 + MAX(0, VERI_TABANI!D25*C8-MAX(0, VERI_TABANI!D25-VERI_TABANI!D25*B8))*VERI_TABANI!$B$8) + IF(ABS(IF(ISNUMBER(SEARCH("Var", D8)), 1, IF(ISNUMBER(SEARCH("Gri", D8)), -1, 0)))=1, VERI_TABANI!E25*(1-0.928)*VERI_TABANI!$B$9, 0) + (VERI_TABANI!D25*B8*(VERI_TABANI!$B$13-VERI_TABANI!$B$14)*VERI_TABANI!G25) + (VERI_TABANI!D25*C8*(VERI_TABANI!$B$13-VERI_TABANI!$B$15)*VERI_TABANI!G25) + IF(ABS(IF(ISNUMBER(SEARCH("Var", D8)), 1, IF(ISNUMBER(SEARCH("Gri", D8)), -1, 0)))=1, VERI_TABANI!E25*(1-0.928)*0.00206091519919798*VERI_TABANI!G25, 0)) + ((MIN(VERI_TABANI!D26, VERI_TABANI!D26*B8)*VERI_TABANI!$B$7 + MAX(0, VERI_TABANI!D26*B8-VERI_TABANI!D26)*VERI_TABANI!$B$8) + (MIN(MAX(0, VERI_TABANI!D26-VERI_TABANI!D26*B8), VERI_TABANI!D26*C8)*VERI_TABANI!$B$7 + MAX(0, VERI_TABANI!D26*C8-MAX(0, VERI_TABANI!D26-VERI_TABANI!D26*B8))*VERI_TABANI!$B$8) + IF(ABS(IF(ISNUMBER(SEARCH("Var", D8)), 1, IF(ISNUMBER(SEARCH("Gri", D8)), -1, 0)))=1, VERI_TABANI!E26*(1-0.928)*VERI_TABANI!$B$9, 0) + (VERI_TABANI!D26*B8*(VERI_TABANI!$B$13-VERI_TABANI!$B$14)*VERI_TABANI!G26) + (VERI_TABANI!D26*C8*(VERI_TABANI!$B$13-VERI_TABANI!$B$15)*VERI_TABANI!G26) + IF(ABS(IF(ISNUMBER(SEARCH("Var", D8)), 1, IF(ISNUMBER(SEARCH("Gri", D8)), -1, 0)))=1, VERI_TABANI!E26*(1-0.928)*0.00206091519919798*VERI_TABANI!G26, 0)) + ((MIN(VERI_TABANI!D27, VERI_TABANI!D27*B8)*VERI_TABANI!$B$7 + MAX(0, VERI_TABANI!D27*B8-VERI_TABANI!D27)*VERI_TABANI!$B$8) + (MIN(MAX(0, VERI_TABANI!D27-VERI_TABANI!D27*B8), VERI_TABANI!D27*C8)*VERI_TABANI!$B$7 + MAX(0, VERI_TABANI!D27*C8-MAX(0, VERI_TABANI!D27-VERI_TABANI!D27*B8))*VERI_TABANI!$B$8) + IF(ABS(IF(ISNUMBER(SEARCH("Var", D8)), 1, IF(ISNUMBER(SEARCH("Gri", D8)), -1, 0)))=1, VERI_TABANI!E27*(1-0.928)*VERI_TABANI!$B$9, 0) + (VERI_TABANI!D27*B8*(VERI_TABANI!$B$13-VERI_TABANI!$B$14)*VERI_TABANI!G27) + (VERI_TABANI!D27*C8*(VERI_TABANI!$B$13-VERI_TABANI!$B$15)*VERI_TABANI!G27) + IF(ABS(IF(ISNUMBER(SEARCH("Var", D8)), 1, IF(ISNUMBER(SEARCH("Gri", D8)), -1, 0)))=1, VERI_TABANI!E27*(1-0.928)*0.00206091519919798*VERI_TABANI!G27, 0)) + ((MIN(VERI_TABANI!D28, VERI_TABANI!D28*B8)*VERI_TABANI!$B$7 + MAX(0, VERI_TABANI!D28*B8-VERI_TABANI!D28)*VERI_TABANI!$B$8) + (MIN(MAX(0, VERI_TABANI!D28-VERI_TABANI!D28*B8), VERI_TABANI!D28*C8)*VERI_TABANI!$B$7 + MAX(0, VERI_TABANI!D28*C8-MAX(0, VERI_TABANI!D28-VERI_TABANI!D28*B8))*VERI_TABANI!$B$8) + IF(ABS(IF(ISNUMBER(SEARCH("Var", D8)), 1, IF(ISNUMBER(SEARCH("Gri", D8)), -1, 0)))=1, VERI_TABANI!E28*(1-0.928)*VERI_TABANI!$B$9, 0) + (VERI_TABANI!D28*B8*(VERI_TABANI!$B$13-VERI_TABANI!$B$14)*VERI_TABANI!G28) + (VERI_TABANI!D28*C8*(VERI_TABANI!$B$13-VERI_TABANI!$B$15)*VERI_TABANI!G28) + IF(ABS(IF(ISNUMBER(SEARCH("Var", D8)), 1, IF(ISNUMBER(SEARCH("Gri", D8)), -1, 0)))=1, VERI_TABANI!E28*(1-0.928)*0.00206091519919798*VERI_TABANI!G28, 0))) | H8: =(((VERI_TABANI!D23*B8*(VERI_TABANI!$B$13-VERI_TABANI!$B$14)) + (VERI_TABANI!D23*C8*(VERI_TABANI!$B$13-VERI_TABANI!$B$15)) + IF(ISNUMBER(SEARCH("Var", D8)), VERI_TABANI!F23*(0.00202-VERI_TABANI!$B$16), IF(ISNUMBER(SEARCH("Gri", D8)), VERI_TABANI!F23*(0.00202-VERI_TABANI!$B$17), 0))) + ((VERI_TABANI!D24*B8*(VERI_TABANI!$B$13-VERI_TABANI!$B$14)) + (VERI_TABANI!D24*C8*(VERI_TABANI!$B$13-VERI_TABANI!$B$15)) + IF(ISNUMBER(SEARCH("Var", D8)), VERI_TABANI!F24*(0.00202-VERI_TABANI!$B$16), IF(ISNUMBER(SEARCH("Gri", D8)), VERI_TABANI!F24*(0.00202-VERI_TABANI!$B$17), 0))) + ((VERI_TABANI!D25*B8*(VERI_TABANI!$B$13-VERI_TABANI!$B$14)) + (VERI_TABANI!D25*C8*(VERI_TABANI!$B$13-VERI_TABANI!$B$15)) + IF(ISNUMBER(SEARCH("Var", D8)), VERI_TABANI!F25*(0.00202-VERI_TABANI!$B$16), IF(ISNUMBER(SEARCH("Gri", D8)), VERI_TABANI!F25*(0.00202-VERI_TABANI!$B$17), 0))) + ((VERI_TABANI!D26*B8*(VERI_TABANI!$B$13-VERI_TABANI!$B$14)) + (VERI_TABANI!D26*C8*(VERI_TABANI!$B$13-VERI_TABANI!$B$15)) + IF(ISNUMBER(SEARCH("Var", D8)), VERI_TABANI!F26*(0.00202-VERI_TABANI!$B$16), IF(ISNUMBER(SEARCH("Gri", D8)), VERI_TABANI!F26*(0.00202-VERI_TABANI!$B$17), 0))) + ((VERI_TABANI!D27*B8*(VERI_TABANI!$B$13-VERI_TABANI!$B$14)) + (VERI_TABANI!D27*C8*(VERI_TABANI!$B$13-VERI_TABANI!$B$15)) + IF(ISNUMBER(SEARCH("Var", D8)), VERI_TABANI!F27*(0.00202-VERI_TABANI!$B$16), IF(ISNUMBER(SEARCH("Gri", D8)), VERI_TABANI!F27*(0.00202-VERI_TABANI!$B$17), 0))) + ((VERI_TABANI!D28*B8*(VERI_TABANI!$B$13-VERI_TABANI!$B$14)) + (VERI_TABANI!D28*C8*(VERI_TABANI!$B$13-VERI_TABANI!$B$15)) + IF(ISNUMBER(SEARCH("Var", D8)), VERI_TABANI!F28*(0.00202-VERI_TABANI!$B$16), IF(ISNUMBER(SEARCH("Gri", D8)), VERI_TABANI!F28*(0.00202-VERI_TABANI!$B$17), 0)))) | I8: =IFERROR(((VERI_TABANI!$D$29*B8*VERI_TABANI!$B$14 + VERI_TABANI!$D$29*C8*VERI_TABANI!$B$15 + IF(ISNUMBER(SEARCH("Var", D8)), VERI_TABANI!$F$29*VERI_TABANI!$B$16, 0))) / (((VERI_TABANI!$D$29*B8 + VERI_TABANI!$D$29*C8)*VERI_TABANI!$B$13 + IF(ISNUMBER(SEARCH("Var", D8)), VERI_TABANI!$E$29*(1-0.928)*VERI_TABANI!$B$18, 0))), 0) | J8: =IFERROR(F8/(G8/29), 0) | K8: =IF(F8>0, H8/F8, 0) | L8: =IF(F8>0, I8, 1000000000) | M8: =ABS((B8+C8)-1) | N8: =IF(F8>0, (G8/29)/F8, 0) | O8: =IF(AND((B8+C8)>=1, ISNUMBER(SEARCH("Var", D8))), F8, 1000000000) | P8: =IF(F8>0, SQRT((F8/MAX(F$5:F$886))^2 + (1 - H8/MAX(H$5:H$886))^2 + (J8/MAX(J$5:J$886))^2), 1000000000) | Q8: =IF(AND(ABS(B8-0.5)<0.01, ABS(C8-0.5)<0.01, ISNUMBER(SEARCH("Var", D8))), 1, 0) | R8: =IF(F8>0, J8, 1000000000) | S8: =IF(AND(F8<=DASHBOARD!$B$11, H8>=DASHBOARD!$B$13), G8, -1000000000000) | T8: =IF(AND(F8<=DASHBOARD!$B$11, H8>=DASHBOARD!$B$13), R8, 1000000000000) | U8: =IF(AND(F8<=DASHBOARD!$B$11, H8>=DASHBOARD!$B$13), N8, -1000000000000) | V8: =IF(AND(F8<=DASHBOARD!$B$11, H8>=DASHBOARD!$B$13), H8, -1000000000000) | W8: =IF(AND(F8<=DASHBOARD!$B$11, H8>=DASHBOARD!$B$13), K8, -1000000000000) | X8: =IF(AND(F8<=DASHBOARD!$B$11, H8>=DASHBOARD!$B$13), M8, 1000000000000) | Y8: =IF(AND(F8<=DASHBOARD!$B$10, H8>=DASHBOARD!$B$11), L8, 1000000000000) | Z8: =IF(AND(F8<=DASHBOARD!$B$10, H8>=DASHBOARD!$B$11), O8, 1000000000000) | AA8: =IF(AND(F8<=DASHBOARD!$B$10, H8>=DASHBOARD!$B$11), P8, 1000000000000) | AB8: =IF(AND(F8<=DASHBOARD!$B$10, H8>=DASHBOARD!$B$11), Q8, -1000000000000)
A9: 5 | B9: 0 | C9: 0.2 | D9: Yok (%0) | E9: =IF((B9+C9)<=1, "Tam Mahsuplaşma (≤%100)", "Kısmi Satış (>%100)") | F9: =((VERI_TABANI!$D$29*B9/VERI_TABANI!$B$29)/VERI_TABANI!$B$3)*VERI_TABANI!$B$5 + ((VERI_TABANI!$D$29*C9/VERI_TABANI!$B$29)/VERI_TABANI!$B$4)*VERI_TABANI!$B$6 + IF(ISNUMBER(SEARCH("Var", D9)), (VERI_TABANI!$F$29/VERI_TABANI!$B$29)*(VERI_TABANI!$B$10+VERI_TABANI!$B$12), 0) | G9: =(((MIN(VERI_TABANI!D23, VERI_TABANI!D23*B9)*VERI_TABANI!$B$7 + MAX(0, VERI_TABANI!D23*B9-VERI_TABANI!D23)*VERI_TABANI!$B$8) + (MIN(MAX(0, VERI_TABANI!D23-VERI_TABANI!D23*B9), VERI_TABANI!D23*C9)*VERI_TABANI!$B$7 + MAX(0, VERI_TABANI!D23*C9-MAX(0, VERI_TABANI!D23-VERI_TABANI!D23*B9))*VERI_TABANI!$B$8) + IF(ABS(IF(ISNUMBER(SEARCH("Var", D9)), 1, IF(ISNUMBER(SEARCH("Gri", D9)), -1, 0)))=1, VERI_TABANI!E23*(1-0.928)*VERI_TABANI!$B$9, 0) + (VERI_TABANI!D23*B9*(VERI_TABANI!$B$13-VERI_TABANI!$B$14)*VERI_TABANI!G23) + (VERI_TABANI!D23*C9*(VERI_TABANI!$B$13-VERI_TABANI!$B$15)*VERI_TABANI!G23) + IF(ABS(IF(ISNUMBER(SEARCH("Var", D9)), 1, IF(ISNUMBER(SEARCH("Gri", D9)), -1, 0)))=1, VERI_TABANI!E23*(1-0.928)*0.00206091519919798*VERI_TABANI!G23, 0)) + ((MIN(VERI_TABANI!D24, VERI_TABANI!D24*B9)*VERI_TABANI!$B$7 + MAX(0, VERI_TABANI!D24*B9-VERI_TABANI!D24)*VERI_TABANI!$B$8) + (MIN(MAX(0, VERI_TABANI!D24-VERI_TABANI!D24*B9), VERI_TABANI!D24*C9)*VERI_TABANI!$B$7 + MAX(0, VERI_TABANI!D24*C9-MAX(0, VERI_TABANI!D24-VERI_TABANI!D24*B9))*VERI_TABANI!$B$8) + IF(ABS(IF(ISNUMBER(SEARCH("Var", D9)), 1, IF(ISNUMBER(SEARCH("Gri", D9)), -1, 0)))=1, VERI_TABANI!E24*(1-0.928)*VERI_TABANI!$B$9, 0) + (VERI_TABANI!D24*B9*(VERI_TABANI!$B$13-VERI_TABANI!$B$14)*VERI_TABANI!G24) + (VERI_TABANI!D24*C9*(VERI_TABANI!$B$13-VERI_TABANI!$B$15)*VERI_TABANI!G24) + IF(ABS(IF(ISNUMBER(SEARCH("Var", D9)), 1, IF(ISNUMBER(SEARCH("Gri", D9)), -1, 0)))=1, VERI_TABANI!E24*(1-0.928)*0.00206091519919798*VERI_TABANI!G24, 0)) + ((MIN(VERI_TABANI!D25, VERI_TABANI!D25*B9)*VERI_TABANI!$B$7 + MAX(0, VERI_TABANI!D25*B9-VERI_TABANI!D25)*VERI_TABANI!$B$8) + (MIN(MAX(0, VERI_TABANI!D25-VERI_TABANI!D25*B9), VERI_TABANI!D25*C9)*VERI_TABANI!$B$7 + MAX(0, VERI_TABANI!D25*C9-MAX(0, VERI_TABANI!D25-VERI_TABANI!D25*B9))*VERI_TABANI!$B$8) + IF(ABS(IF(ISNUMBER(SEARCH("Var", D9)), 1, IF(ISNUMBER(SEARCH("Gri", D9)), -1, 0)))=1, VERI_TABANI!E25*(1-0.928)*VERI_TABANI!$B$9, 0) + (VERI_TABANI!D25*B9*(VERI_TABANI!$B$13-VERI_TABANI!$B$14)*VERI_TABANI!G25) + (VERI_TABANI!D25*C9*(VERI_TABANI!$B$13-VERI_TABANI!$B$15)*VERI_TABANI!G25) + IF(ABS(IF(ISNUMBER(SEARCH("Var", D9)), 1, IF(ISNUMBER(SEARCH("Gri", D9)), -1, 0)))=1, VERI_TABANI!E25*(1-0.928)*0.00206091519919798*VERI_TABANI!G25, 0)) + ((MIN(VERI_TABANI!D26, VERI_TABANI!D26*B9)*VERI_TABANI!$B$7 + MAX(0, VERI_TABANI!D26*B9-VERI_TABANI!D26)*VERI_TABANI!$B$8) + (MIN(MAX(0, VERI_TABANI!D26-VERI_TABANI!D26*B9), VERI_TABANI!D26*C9)*VERI_TABANI!$B$7 + MAX(0, VERI_TABANI!D26*C9-MAX(0, VERI_TABANI!D26-VERI_TABANI!D26*B9))*VERI_TABANI!$B$8) + IF(ABS(IF(ISNUMBER(SEARCH("Var", D9)), 1, IF(ISNUMBER(SEARCH("Gri", D9)), -1, 0)))=1, VERI_TABANI!E26*(1-0.928)*VERI_TABANI!$B$9, 0) + (VERI_TABANI!D26*B9*(VERI_TABANI!$B$13-VERI_TABANI!$B$14)*VERI_TABANI!G26) + (VERI_TABANI!D26*C9*(VERI_TABANI!$B$13-VERI_TABANI!$B$15)*VERI_TABANI!G26) + IF(ABS(IF(ISNUMBER(SEARCH("Var", D9)), 1, IF(ISNUMBER(SEARCH("Gri", D9)), -1, 0)))=1, VERI_TABANI!E26*(1-0.928)*0.00206091519919798*VERI_TABANI!G26, 0)) + ((MIN(VERI_TABANI!D27, VERI_TABANI!D27*B9)*VERI_TABANI!$B$7 + MAX(0, VERI_TABANI!D27*B9-VERI_TABANI!D27)*VERI_TABANI!$B$8) + (MIN(MAX(0, VERI_TABANI!D27-VERI_TABANI!D27*B9), VERI_TABANI!D27*C9)*VERI_TABANI!$B$7 + MAX(0, VERI_TABANI!D27*C9-MAX(0, VERI_TABANI!D27-VERI_TABANI!D27*B9))*VERI_TABANI!$B$8) + IF(ABS(IF(ISNUMBER(SEARCH("Var", D9)), 1, IF(ISNUMBER(SEARCH("Gri", D9)), -1, 0)))=1, VERI_TABANI!E27*(1-0.928)*VERI_TABANI!$B$9, 0) + (VERI_TABANI!D27*B9*(VERI_TABANI!$B$13-VERI_TABANI!$B$14)*VERI_TABANI!G27) + (VERI_TABANI!D27*C9*(VERI_TABANI!$B$13-VERI_TABANI!$B$15)*VERI_TABANI!G27) + IF(ABS(IF(ISNUMBER(SEARCH("Var", D9)), 1, IF(ISNUMBER(SEARCH("Gri", D9)), -1, 0)))=1, VERI_TABANI!E27*(1-0.928)*0.00206091519919798*VERI_TABANI!G27, 0)) + ((MIN(VERI_TABANI!D28, VERI_TABANI!D28*B9)*VERI_TABANI!$B$7 + MAX(0, VERI_TABANI!D28*B9-VERI_TABANI!D28)*VERI_TABANI!$B$8) + (MIN(MAX(0, VERI_TABANI!D28-VERI_TABANI!D28*B9), VERI_TABANI!D28*C9)*VERI_TABANI!$B$7 + MAX(0, VERI_TABANI!D28*C9-MAX(0, VERI_TABANI!D28-VERI_TABANI!D28*B9))*VERI_TABANI!$B$8) + IF(ABS(IF(ISNUMBER(SEARCH("Var", D9)), 1, IF(ISNUMBER(SEARCH("Gri", D9)), -1, 0)))=1, VERI_TABANI!E28*(1-0.928)*VERI_TABANI!$B$9, 0) + (VERI_TABANI!D28*B9*(VERI_TABANI!$B$13-VERI_TABANI!$B$14)*VERI_TABANI!G28) + (VERI_TABANI!D28*C9*(VERI_TABANI!$B$13-VERI_TABANI!$B$15)*VERI_TABANI!G28) + IF(ABS(IF(ISNUMBER(SEARCH("Var", D9)), 1, IF(ISNUMBER(SEARCH("Gri", D9)), -1, 0)))=1, VERI_TABANI!E28*(1-0.928)*0.00206091519919798*VERI_TABANI!G28, 0))) | H9: =(((VERI_TABANI!D23*B9*(VERI_TABANI!$B$13-VERI_TABANI!$B$14)) + (VERI_TABANI!D23*C9*(VERI_TABANI!$B$13-VERI_TABANI!$B$15)) + IF(ISNUMBER(SEARCH("Var", D9)), VERI_TABANI!F23*(0.00202-VERI_TABANI!$B$16), IF(ISNUMBER(SEARCH("Gri", D9)), VERI_TABANI!F23*(0.00202-VERI_TABANI!$B$17), 0))) + ((VERI_TABANI!D24*B9*(VERI_TABANI!$B$13-VERI_TABANI!$B$14)) + (VERI_TABANI!D24*C9*(VERI_TABANI!$B$13-VERI_TABANI!$B$15)) + IF(ISNUMBER(SEARCH("Var", D9)), VERI_TABANI!F24*(0.00202-VERI_TABANI!$B$16), IF(ISNUMBER(SEARCH("Gri", D9)), VERI_TABANI!F24*(0.00202-VERI_TABANI!$B$17), 0))) + ((VERI_TABANI!D25*B9*(VERI_TABANI!$B$13-VERI_TABANI!$B$14)) + (VERI_TABANI!D25*C9*(VERI_TABANI!$B$13-VERI_TABANI!$B$15)) + IF(ISNUMBER(SEARCH("Var", D9)), VERI_TABANI!F25*(0.00202-VERI_TABANI!$B$16), IF(ISNUMBER(SEARCH("Gri", D9)), VERI_TABANI!F25*(0.00202-VERI_TABANI!$B$17), 0))) + ((VERI_TABANI!D26*B9*(VERI_TABANI!$B$13-VERI_TABANI!$B$14)) + (VERI_TABANI!D26*C9*(VERI_TABANI!$B$13-VERI_TABANI!$B$15)) + IF(ISNUMBER(SEARCH("Var", D9)), VERI_TABANI!F26*(0.00202-VERI_TABANI!$B$16), IF(ISNUMBER(SEARCH("Gri", D9)), VERI_TABANI!F26*(0.00202-VERI_TABANI!$B$17), 0))) + ((VERI_TABANI!D27*B9*(VERI_TABANI!$B$13-VERI_TABANI!$B$14)) + (VERI_TABANI!D27*C9*(VERI_TABANI!$B$13-VERI_TABANI!$B$15)) + IF(ISNUMBER(SEARCH("Var", D9)), VERI_TABANI!F27*(0.00202-VERI_TABANI!$B$16), IF(ISNUMBER(SEARCH("Gri", D9)), VERI_TABANI!F27*(0.00202-VERI_TABANI!$B$17), 0))) + ((VERI_TABANI!D28*B9*(VERI_TABANI!$B$13-VERI_TABANI!$B$14)) + (VERI_TABANI!D28*C9*(VERI_TABANI!$B$13-VERI_TABANI!$B$15)) + IF(ISNUMBER(SEARCH("Var", D9)), VERI_TABANI!F28*(0.00202-VERI_TABANI!$B$16), IF(ISNUMBER(SEARCH("Gri", D9)), VERI_TABANI!F28*(0.00202-VERI_TABANI!$B$17), 0)))) | I9: =IFERROR(((VERI_TABANI!$D$29*B9*VERI_TABANI!$B$14 + VERI_TABANI!$D$29*C9*VERI_TABANI!$B$15 + IF(ISNUMBER(SEARCH("Var", D9)), VERI_TABANI!$F$29*VERI_TABANI!$B$16, 0))) / (((VERI_TABANI!$D$29*B9 + VERI_TABANI!$D$29*C9)*VERI_TABANI!$B$13 + IF(ISNUMBER(SEARCH("Var", D9)), VERI_TABANI!$E$29*(1-0.928)*VERI_TABANI!$B$18, 0))), 0) | J9: =IFERROR(F9/(G9/29), 0) | K9: =IF(F9>0, H9/F9, 0) | L9: =IF(F9>0, I9, 1000000000) | M9: =ABS((B9+C9)-1) | N9: =IF(F9>0, (G9/29)/F9, 0) | O9: =IF(AND((B9+C9)>=1, ISNUMBER(SEARCH("Var", D9))), F9, 1000000000) | P9: =IF(F9>0, SQRT((F9/MAX(F$5:F$886))^2 + (1 - H9/MAX(H$5:H$886))^2 + (J9/MAX(J$5:J$886))^2), 1000000000) | Q9: =IF(AND(ABS(B9-0.5)<0.01, ABS(C9-0.5)<0.01, ISNUMBER(SEARCH("Var", D9))), 1, 0) | R9: =IF(F9>0, J9, 1000000000) | S9: =IF(AND(F9<=DASHBOARD!$B$11, H9>=DASHBOARD!$B$13), G9, -1000000000000) | T9: =IF(AND(F9<=DASHBOARD!$B$11, H9>=DASHBOARD!$B$13), R9, 1000000000000) | U9: =IF(AND(F9<=DASHBOARD!$B$11, H9>=DASHBOARD!$B$13), N9, -1000000000000) | V9: =IF(AND(F9<=DASHBOARD!$B$11, H9>=DASHBOARD!$B$13), H9, -1000000000000) | W9: =IF(AND(F9<=DASHBOARD!$B$11, H9>=DASHBOARD!$B$13), K9, -1000000000000) | X9: =IF(AND(F9<=DASHBOARD!$B$11, H9>=DASHBOARD!$B$13), M9, 1000000000000) | Y9: =IF(AND(F9<=DASHBOARD!$B$10, H9>=DASHBOARD!$B$11), L9, 1000000000000) | Z9: =IF(AND(F9<=DASHBOARD!$B$10, H9>=DASHBOARD!$B$11), O9, 1000000000000) | AA9: =IF(AND(F9<=DASHBOARD!$B$10, H9>=DASHBOARD!$B$11), P9, 1000000000000) | AB9: =IF(AND(F9<=DASHBOARD!$B$10, H9>=DASHBOARD!$B$11), Q9, -1000000000000)
A10: 6 | B10: 0 | C10: 0.2 | D10: Var (%20) | E10: =IF((B10+C10)<=1, "Tam Mahsuplaşma (≤%100)", "Kısmi Satış (>%100)") | F10: =((VERI_TABANI!$D$29*B10/VERI_TABANI!$B$29)/VERI_TABANI!$B$3)*VERI_TABANI!$B$5 + ((VERI_TABANI!$D$29*C10/VERI_TABANI!$B$29)/VERI_TABANI!$B$4)*VERI_TABANI!$B$6 + IF(ISNUMBER(SEARCH("Var", D10)), (VERI_TABANI!$F$29/VERI_TABANI!$B$29)*(VERI_TABANI!$B$10+VERI_TABANI!$B$12), 0) | G10: =(((MIN(VERI_TABANI!D23, VERI_TABANI!D23*B10)*VERI_TABANI!$B$7 + MAX(0, VERI_TABANI!D23*B10-VERI_TABANI!D23)*VERI_TABANI!$B$8) + (MIN(MAX(0, VERI_TABANI!D23-VERI_TABANI!D23*B10), VERI_TABANI!D23*C10)*VERI_TABANI!$B$7 + MAX(0, VERI_TABANI!D23*C10-MAX(0, VERI_TABANI!D23-VERI_TABANI!D23*B10))*VERI_TABANI!$B$8) + IF(ABS(IF(ISNUMBER(SEARCH("Var", D10)), 1, IF(ISNUMBER(SEARCH("Gri", D10)), -1, 0)))=1, VERI_TABANI!E23*(1-0.928)*VERI_TABANI!$B$9, 0) + (VERI_TABANI!D23*B10*(VERI_TABANI!$B$13-VERI_TABANI!$B$14)*VERI_TABANI!G23) + (VERI_TABANI!D23*C10*(VERI_TABANI!$B$13-VERI_TABANI!$B$15)*VERI_TABANI!G23) + IF(ABS(IF(ISNUMBER(SEARCH("Var", D10)), 1, IF(ISNUMBER(SEARCH("Gri", D10)), -1, 0)))=1, VERI_TABANI!E23*(1-0.928)*0.00206091519919798*VERI_TABANI!G23, 0)) + ((MIN(VERI_TABANI!D24, VERI_TABANI!D24*B10)*VERI_TABANI!$B$7 + MAX(0, VERI_TABANI!D24*B10-VERI_TABANI!D24)*VERI_TABANI!$B$8) + (MIN(MAX(0, VERI_TABANI!D24-VERI_TABANI!D24*B10), VERI_TABANI!D24*C10)*VERI_TABANI!$B$7 + MAX(0, VERI_TABANI!D24*C10-MAX(0, VERI_TABANI!D24-VERI_TABANI!D24*B10))*VERI_TABANI!$B$8) + IF(ABS(IF(ISNUMBER(SEARCH("Var", D10)), 1, IF(ISNUMBER(SEARCH("Gri", D10)), -1, 0)))=1, VERI_TABANI!E24*(1-0.928)*VERI_TABANI!$B$9, 0) + (VERI_TABANI!D24*B10*(VERI_TABANI!$B$13-VERI_TABANI!$B$14)*VERI_TABANI!G24) + (VERI_TABANI!D24*C10*(VERI_TABANI!$B$13-VERI_TABANI!$B$15)*VERI_TABANI!G24) + IF(ABS(IF(ISNUMBER(SEARCH("Var", D10)), 1, IF(ISNUMBER(SEARCH("Gri", D10)), -1, 0)))=1, VERI_TABANI!E24*(1-0.928)*0.00206091519919798*VERI_TABANI!G24, 0)) + ((MIN(VERI_TABANI!D25, VERI_TABANI!D25*B10)*VERI_TABANI!$B$7 + MAX(0, VERI_TABANI!D25*B10-VERI_TABANI!D25)*VERI_TABANI!$B$8) + (MIN(MAX(0, VERI_TABANI!D25-VERI_TABANI!D25*B10), VERI_TABANI!D25*C10)*VERI_TABANI!$B$7 + MAX(0, VERI_TABANI!D25*C10-MAX(0, VERI_TABANI!D25-VERI_TABANI!D25*B10))*VERI_TABANI!$B$8) + IF(ABS(IF(ISNUMBER(SEARCH("Var", D10)), 1, IF(ISNUMBER(SEARCH("Gri", D10)), -1, 0)))=1, VERI_TABANI!E25*(1-0.928)*VERI_TABANI!$B$9, 0) + (VERI_TABANI!D25*B10*(VERI_TABANI!$B$13-VERI_TABANI!$B$14)*VERI_TABANI!G25) + (VERI_TABANI!D25*C10*(VERI_TABANI!$B$13-VERI_TABANI!$B$15)*VERI_TABANI!G25) + IF(ABS(IF(ISNUMBER(SEARCH("Var", D10)), 1, IF(ISNUMBER(SEARCH("Gri", D10)), -1, 0)))=1, VERI_TABANI!E25*(1-0.928)*0.00206091519919798*VERI_TABANI!G25, 0)) + ((MIN(VERI_TABANI!D26, VERI_TABANI!D26*B10)*VERI_TABANI!$B$7 + MAX(0, VERI_TABANI!D26*B10-VERI_TABANI!D26)*VERI_TABANI!$B$8) + (MIN(MAX(0, VERI_TABANI!D26-VERI_TABANI!D26*B10), VERI_TABANI!D26*C10)*VERI_TABANI!$B$7 + MAX(0, VERI_TABANI!D26*C10-MAX(0, VERI_TABANI!D26-VERI_TABANI!D26*B10))*VERI_TABANI!$B$8) + IF(ABS(IF(ISNUMBER(SEARCH("Var", D10)), 1, IF(ISNUMBER(SEARCH("Gri", D10)), -1, 0)))=1, VERI_TABANI!E26*(1-0.928)*VERI_TABANI!$B$9, 0) + (VERI_TABANI!D26*B10*(VERI_TABANI!$B$13-VERI_TABANI!$B$14)*VERI_TABANI!G26) + (VERI_TABANI!D26*C10*(VERI_TABANI!$B$13-VERI_TABANI!$B$15)*VERI_TABANI!G26) + IF(ABS(IF(ISNUMBER(SEARCH("Var", D10)), 1, IF(ISNUMBER(SEARCH("Gri", D10)), -1, 0)))=1, VERI_TABANI!E26*(1-0.928)*0.00206091519919798*VERI_TABANI!G26, 0)) + ((MIN(VERI_TABANI!D27, VERI_TABANI!D27*B10)*VERI_TABANI!$B$7 + MAX(0, VERI_TABANI!D27*B10-VERI_TABANI!D27)*VERI_TABANI!$B$8) + (MIN(MAX(0, VERI_TABANI!D27-VERI_TABANI!D27*B10), VERI_TABANI!D27*C10)*VERI_TABANI!$B$7 + MAX(0, VERI_TABANI!D27*C10-MAX(0, VERI_TABANI!D27-VERI_TABANI!D27*B10))*VERI_TABANI!$B$8) + IF(ABS(IF(ISNUMBER(SEARCH("Var", D10)), 1, IF(ISNUMBER(SEARCH("Gri", D10)), -1, 0)))=1, VERI_TABANI!E27*(1-0.928)*VERI_TABANI!$B$9, 0) + (VERI_TABANI!D27*B10*(VERI_TABANI!$B$13-VERI_TABANI!$B$14)*VERI_TABANI!G27) + (VERI_TABANI!D27*C10*(VERI_TABANI!$B$13-VERI_TABANI!$B$15)*VERI_TABANI!G27) + IF(ABS(IF(ISNUMBER(SEARCH("Var", D10)), 1, IF(ISNUMBER(SEARCH("Gri", D10)), -1, 0)))=1, VERI_TABANI!E27*(1-0.928)*0.00206091519919798*VERI_TABANI!G27, 0)) + ((MIN(VERI_TABANI!D28, VERI_TABANI!D28*B10)*VERI_TABANI!$B$7 + MAX(0, VERI_TABANI!D28*B10-VERI_TABANI!D28)*VERI_TABANI!$B$8) + (MIN(MAX(0, VERI_TABANI!D28-VERI_TABANI!D28*B10), VERI_TABANI!D28*C10)*VERI_TABANI!$B$7 + MAX(0, VERI_TABANI!D28*C10-MAX(0, VERI_TABANI!D28-VERI_TABANI!D28*B10))*VERI_TABANI!$B$8) + IF(ABS(IF(ISNUMBER(SEARCH("Var", D10)), 1, IF(ISNUMBER(SEARCH("Gri", D10)), -1, 0)))=1, VERI_TABANI!E28*(1-0.928)*VERI_TABANI!$B$9, 0) + (VERI_TABANI!D28*B10*(VERI_TABANI!$B$13-VERI_TABANI!$B$14)*VERI_TABANI!G28) + (VERI_TABANI!D28*C10*(VERI_TABANI!$B$13-VERI_TABANI!$B$15)*VERI_TABANI!G28) + IF(ABS(IF(ISNUMBER(SEARCH("Var", D10)), 1, IF(ISNUMBER(SEARCH("Gri", D10)), -1, 0)))=1, VERI_TABANI!E28*(1-0.928)*0.00206091519919798*VERI_TABANI!G28, 0))) | H10: =(((VERI_TABANI!D23*B10*(VERI_TABANI!$B$13-VERI_TABANI!$B$14)) + (VERI_TABANI!D23*C10*(VERI_TABANI!$B$13-VERI_TABANI!$B$15)) + IF(ISNUMBER(SEARCH("Var", D10)), VERI_TABANI!F23*(0.00202-VERI_TABANI!$B$16), IF(ISNUMBER(SEARCH("Gri", D10)), VERI_TABANI!F23*(0.00202-VERI_TABANI!$B$17), 0))) + ((VERI_TABANI!D24*B10*(VERI_TABANI!$B$13-VERI_TABANI!$B$14)) + (VERI_TABANI!D24*C10*(VERI_TABANI!$B$13-VERI_TABANI!$B$15)) + IF(ISNUMBER(SEARCH("Var", D10)), VERI_TABANI!F24*(0.00202-VERI_TABANI!$B$16), IF(ISNUMBER(SEARCH("Gri", D10)), VERI_TABANI!F24*(0.00202-VERI_TABANI!$B$17), 0))) + ((VERI_TABANI!D25*B10*(VERI_TABANI!$B$13-VERI_TABANI!$B$14)) + (VERI_TABANI!D25*C10*(VERI_TABANI!$B$13-VERI_TABANI!$B$15)) + IF(ISNUMBER(SEARCH("Var", D10)), VERI_TABANI!F25*(0.00202-VERI_TABANI!$B$16), IF(ISNUMBER(SEARCH("Gri", D10)), VERI_TABANI!F25*(0.00202-VERI_TABANI!$B$17), 0))) + ((VERI_TABANI!D26*B10*(VERI_TABANI!$B$13-VERI_TABANI!$B$14)) + (VERI_TABANI!D26*C10*(VERI_TABANI!$B$13-VERI_TABANI!$B$15)) + IF(ISNUMBER(SEARCH("Var", D10)), VERI_TABANI!F26*(0.00202-VERI_TABANI!$B$16), IF(ISNUMBER(SEARCH("Gri", D10)), VERI_TABANI!F26*(0.00202-VERI_TABANI!$B$17), 0))) + ((VERI_TABANI!D27*B10*(VERI_TABANI!$B$13-VERI_TABANI!$B$14)) + (VERI_TABANI!D27*C10*(VERI_TABANI!$B$13-VERI_TABANI!$B$15)) + IF(ISNUMBER(SEARCH("Var", D10)), VERI_TABANI!F27*(0.00202-VERI_TABANI!$B$16), IF(ISNUMBER(SEARCH("Gri", D10)), VERI_TABANI!F27*(0.00202-VERI_TABANI!$B$17), 0))) + ((VERI_TABANI!D28*B10*(VERI_TABANI!$B$13-VERI_TABANI!$B$14)) + (VERI_TABANI!D28*C10*(VERI_TABANI!$B$13-VERI_TABANI!$B$15)) + IF(ISNUMBER(SEARCH("Var", D10)), VERI_TABANI!F28*(0.00202-VERI_TABANI!$B$16), IF(ISNUMBER(SEARCH("Gri", D10)), VERI_TABANI!F28*(0.00202-VERI_TABANI!$B$17), 0)))) | I10: =IFERROR(((VERI_TABANI!$D$29*B10*VERI_TABANI!$B$14 + VERI_TABANI!$D$29*C10*VERI_TABANI!$B$15 + IF(ISNUMBER(SEARCH("Var", D10)), VERI_TABANI!$F$29*VERI_TABANI!$B$16, 0))) / (((VERI_TABANI!$D$29*B10 + VERI_TABANI!$D$29*C10)*VERI_TABANI!$B$13 + IF(ISNUMBER(SEARCH("Var", D10)), VERI_TABANI!$E$29*(1-0.928)*VERI_TABANI!$B$18, 0))), 0) | J10: =IFERROR(F10/(G10/29), 0) | K10: =IF(F10>0, H10/F10, 0) | L10: =IF(F10>0, I10, 1000000000) | M10: =ABS((B10+C10)-1) | N10: =IF(F10>0, (G10/29)/F10, 0) | O10: =IF(AND((B10+C10)>=1, ISNUMBER(SEARCH("Var", D10))), F10, 1000000000) | P10: =IF(F10>0, SQRT((F10/MAX(F$5:F$886))^2 + (1 - H10/MAX(H$5:H$886))^2 + (J10/MAX(J$5:J$886))^2), 1000000000) | Q10: =IF(AND(ABS(B10-0.5)<0.01, ABS(C10-0.5)<0.01, ISNUMBER(SEARCH("Var", D10))), 1, 0) | R10: =IF(F10>0, J10, 1000000000) | S10: =IF(AND(F10<=DASHBOARD!$B$11, H10>=DASHBOARD!$B$13), G10, -1000000000000) | T10: =IF(AND(F10<=DASHBOARD!$B$11, H10>=DASHBOARD!$B$13), R10, 1000000000000) | U10: =IF(AND(F10<=DASHBOARD!$B$11, H10>=DASHBOARD!$B$13), N10, -1000000000000) | V10: =IF(AND(F10<=DASHBOARD!$B$11, H10>=DASHBOARD!$B$13), H10, -1000000000000) | W10: =IF(AND(F10<=DASHBOARD!$B$11, H10>=DASHBOARD!$B$13), K10, -1000000000000) | X10: =IF(AND(F10<=DASHBOARD!$B$11, H10>=DASHBOARD!$B$13), M10, 1000000000000) | Y10: =IF(AND(F10<=DASHBOARD!$B$10, H10>=DASHBOARD!$B$11), L10, 1000000000000) | Z10: =IF(AND(F10<=DASHBOARD!$B$10, H10>=DASHBOARD!$B$11), O10, 1000000000000) | AA10: =IF(AND(F10<=DASHBOARD!$B$10, H10>=DASHBOARD!$B$11), P10, 1000000000000) | AB10: =IF(AND(F10<=DASHBOARD!$B$10, H10>=DASHBOARD!$B$11), Q10, -1000000000000)
A11: 7 | B11: 0 | C11: 0.3 | D11: Yok (%0) | E11: =IF((B11+C11)<=1, "Tam Mahsuplaşma (≤%100)", "Kısmi Satış (>%100)") | F11: =((VERI_TABANI!$D$29*B11/VERI_TABANI!$B$29)/VERI_TABANI!$B$3)*VERI_TABANI!$B$5 + ((VERI_TABANI!$D$29*C11/VERI_TABANI!$B$29)/VERI_TABANI!$B$4)*VERI_TABANI!$B$6 + IF(ISNUMBER(SEARCH("Var", D11)), (VERI_TABANI!$F$29/VERI_TABANI!$B$29)*(VERI_TABANI!$B$10+VERI_TABANI!$B$12), 0) | G11: =(((MIN(VERI_TABANI!D23, VERI_TABANI!D23*B11)*VERI_TABANI!$B$7 + MAX(0, VERI_TABANI!D23*B11-VERI_TABANI!D23)*VERI_TABANI!$B$8) + (MIN(MAX(0, VERI_TABANI!D23-VERI_TABANI!D23*B11), VERI_TABANI!D23*C11)*VERI_TABANI!$B$7 + MAX(0, VERI_TABANI!D23*C11-MAX(0, VERI_TABANI!D23-VERI_TABANI!D23*B11))*VERI_TABANI!$B$8) + IF(ABS(IF(ISNUMBER(SEARCH("Var", D11)), 1, IF(ISNUMBER(SEARCH("Gri", D11)), -1, 0)))=1, VERI_TABANI!E23*(1-0.928)*VERI_TABANI!$B$9, 0) + (VERI_TABANI!D23*B11*(VERI_TABANI!$B$13-VERI_TABANI!$B$14)*VERI_TABANI!G23) + (VERI_TABANI!D23*C11*(VERI_TABANI!$B$13-VERI_TABANI!$B$15)*VERI_TABANI!G23) + IF(ABS(IF(ISNUMBER(SEARCH("Var", D11)), 1, IF(ISNUMBER(SEARCH("Gri", D11)), -1, 0)))=1, VERI_TABANI!E23*(1-0.928)*0.00206091519919798*VERI_TABANI!G23, 0)) + ((MIN(VERI_TABANI!D24, VERI_TABANI!D24*B11)*VERI_TABANI!$B$7 + MAX(0, VERI_TABANI!D24*B11-VERI_TABANI!D24)*VERI_TABANI!$B$8) + (MIN(MAX(0, VERI_TABANI!D24-VERI_TABANI!D24*B11), VERI_TABANI!D24*C11)*VERI_TABANI!$B$7 + MAX(0, VERI_TABANI!D24*C11-MAX(0, VERI_TABANI!D24-VERI_TABANI!D24*B11))*VERI_TABANI!$B$8) + IF(ABS(IF(ISNUMBER(SEARCH("Var", D11)), 1, IF(ISNUMBER(SEARCH("Gri", D11)), -1, 0)))=1, VERI_TABANI!E24*(1-0.928)*VERI_TABANI!$B$9, 0) + (VERI_TABANI!D24*B11*(VERI_TABANI!$B$13-VERI_TABANI!$B$14)*VERI_TABANI!G24) + (VERI_TABANI!D24*C11*(VERI_TABANI!$B$13-VERI_TABANI!$B$15)*VERI_TABANI!G24) + IF(ABS(IF(ISNUMBER(SEARCH("Var", D11)), 1, IF(ISNUMBER(SEARCH("Gri", D11)), -1, 0)))=1, VERI_TABANI!E24*(1-0.928)*0.00206091519919798*VERI_TABANI!G24, 0)) + ((MIN(VERI_TABANI!D25, VERI_TABANI!D25*B11)*VERI_TABANI!$B$7 + MAX(0, VERI_TABANI!D25*B11-VERI_TABANI!D25)*VERI_TABANI!$B$8) + (MIN(MAX(0, VERI_TABANI!D25-VERI_TABANI!D25*B11), VERI_TABANI!D25*C11)*VERI_TABANI!$B$7 + MAX(0, VERI_TABANI!D25*C11-MAX(0, VERI_TABANI!D25-VERI_TABANI!D25*B11))*VERI_TABANI!$B$8) + IF(ABS(IF(ISNUMBER(SEARCH("Var", D11)), 1, IF(ISNUMBER(SEARCH("Gri", D11)), -1, 0)))=1, VERI_TABANI!E25*(1-0.928)*VERI_TABANI!$B$9, 0) + (VERI_TABANI!D25*B11*(VERI_TABANI!$B$13-VERI_TABANI!$B$14)*VERI_TABANI!G25) + (VERI_TABANI!D25*C11*(VERI_TABANI!$B$13-VERI_TABANI!$B$15)*VERI_TABANI!G25) + IF(ABS(IF(ISNUMBER(SEARCH("Var", D11)), 1, IF(ISNUMBER(SEARCH("Gri", D11)), -1, 0)))=1, VERI_TABANI!E25*(1-0.928)*0.00206091519919798*VERI_TABANI!G25, 0)) + ((MIN(VERI_TABANI!D26, VERI_TABANI!D26*B11)*VERI_TABANI!$B$7 + MAX(0, VERI_TABANI!D26*B11-VERI_TABANI!D26)*VERI_TABANI!$B$8) + (MIN(MAX(0, VERI_TABANI!D26-VERI_TABANI!D26*B11), VERI_TABANI!D26*C11)*VERI_TABANI!$B$7 + MAX(0, VERI_TABANI!D26*C11-MAX(0, VERI_TABANI!D26-VERI_TABANI!D26*B11))*VERI_TABANI!$B$8) + IF(ABS(IF(ISNUMBER(SEARCH("Var", D11)), 1, IF(ISNUMBER(SEARCH("Gri", D11)), -1, 0)))=1, VERI_TABANI!E26*(1-0.928)*VERI_TABANI!$B$9, 0) + (VERI_TABANI!D26*B11*(VERI_TABANI!$B$13-VERI_TABANI!$B$14)*VERI_TABANI!G26) + (VERI_TABANI!D26*C11*(VERI_TABANI!$B$13-VERI_TABANI!$B$15)*VERI_TABANI!G26) + IF(ABS(IF(ISNUMBER(SEARCH("Var", D11)), 1, IF(ISNUMBER(SEARCH("Gri", D11)), -1, 0)))=1, VERI_TABANI!E26*(1-0.928)*0.00206091519919798*VERI_TABANI!G26, 0)) + ((MIN(VERI_TABANI!D27, VERI_TABANI!D27*B11)*VERI_TABANI!$B$7 + MAX(0, VERI_TABANI!D27*B11-VERI_TABANI!D27)*VERI_TABANI!$B$8) + (MIN(MAX(0, VERI_TABANI!D27-VERI_TABANI!D27*B11), VERI_TABANI!D27*C11)*VERI_TABANI!$B$7 + MAX(0, VERI_TABANI!D27*C11-MAX(0, VERI_TABANI!D27-VERI_TABANI!D27*B11))*VERI_TABANI!$B$8) + IF(ABS(IF(ISNUMBER(SEARCH("Var", D11)), 1, IF(ISNUMBER(SEARCH("Gri", D11)), -1, 0)))=1, VERI_TABANI!E27*(1-0.928)*VERI_TABANI!$B$9, 0) + (VERI_TABANI!D27*B11*(VERI_TABANI!$B$13-VERI_TABANI!$B$14)*VERI_TABANI!G27) + (VERI_TABANI!D27*C11*(VERI_TABANI!$B$13-VERI_TABANI!$B$15)*VERI_TABANI!G27) + IF(ABS(IF(ISNUMBER(SEARCH("Var", D11)), 1, IF(ISNUMBER(SEARCH("Gri", D11)), -1, 0)))=1, VERI_TABANI!E27*(1-0.928)*0.00206091519919798*VERI_TABANI!G27, 0)) + ((MIN(VERI_TABANI!D28, VERI_TABANI!D28*B11)*VERI_TABANI!$B$7 + MAX(0, VERI_TABANI!D28*B11-VERI_TABANI!D28)*VERI_TABANI!$B$8) + (MIN(MAX(0, VERI_TABANI!D28-VERI_TABANI!D28*B11), VERI_TABANI!D28*C11)*VERI_TABANI!$B$7 + MAX(0, VERI_TABANI!D28*C11-MAX(0, VERI_TABANI!D28-VERI_TABANI!D28*B11))*VERI_TABANI!$B$8) + IF(ABS(IF(ISNUMBER(SEARCH("Var", D11)), 1, IF(ISNUMBER(SEARCH("Gri", D11)), -1, 0)))=1, VERI_TABANI!E28*(1-0.928)*VERI_TABANI!$B$9, 0) + (VERI_TABANI!D28*B11*(VERI_TABANI!$B$13-VERI_TABANI!$B$14)*VERI_TABANI!G28) + (VERI_TABANI!D28*C11*(VERI_TABANI!$B$13-VERI_TABANI!$B$15)*VERI_TABANI!G28) + IF(ABS(IF(ISNUMBER(SEARCH("Var", D11)), 1, IF(ISNUMBER(SEARCH("Gri", D11)), -1, 0)))=1, VERI_TABANI!E28*(1-0.928)*0.00206091519919798*VERI_TABANI!G28, 0))) | H11: =(((VERI_TABANI!D23*B11*(VERI_TABANI!$B$13-VERI_TABANI!$B$14)) + (VERI_TABANI!D23*C11*(VERI_TABANI!$B$13-VERI_TABANI!$B$15)) + IF(ISNUMBER(SEARCH("Var", D11)), VERI_TABANI!F23*(0.00202-VERI_TABANI!$B$16), IF(ISNUMBER(SEARCH("Gri", D11)), VERI_TABANI!F23*(0.00202-VERI_TABANI!$B$17), 0))) + ((VERI_TABANI!D24*B11*(VERI_TABANI!$B$13-VERI_TABANI!$B$14)) + (VERI_TABANI!D24*C11*(VERI_TABANI!$B$13-VERI_TABANI!$B$15)) + IF(ISNUMBER(SEARCH("Var", D11)), VERI_TABANI!F24*(0.00202-VERI_TABANI!$B$16), IF(ISNUMBER(SEARCH("Gri", D11)), VERI_TABANI!F24*(0.00202-VERI_TABANI!$B$17), 0))) + ((VERI_TABANI!D25*B11*(VERI_TABANI!$B$13-VERI_TABANI!$B$14)) + (VERI_TABANI!D25*C11*(VERI_TABANI!$B$13-VERI_TABANI!$B$15)) + IF(ISNUMBER(SEARCH("Var", D11)), VERI_TABANI!F25*(0.00202-VERI_TABANI!$B$16), IF(ISNUMBER(SEARCH("Gri", D11)), VERI_TABANI!F25*(0.00202-VERI_TABANI!$B$17), 0))) + ((VERI_TABANI!D26*B11*(VERI_TABANI!$B$13-VERI_TABANI!$B$14)) + (VERI_TABANI!D26*C11*(VERI_TABANI!$B$13-VERI_TABANI!$B$15)) + IF(ISNUMBER(SEARCH("Var", D11)), VERI_TABANI!F26*(0.00202-VERI_TABANI!$B$16), IF(ISNUMBER(SEARCH("Gri", D11)), VERI_TABANI!F26*(0.00202-VERI_TABANI!$B$17), 0))) + ((VERI_TABANI!D27*B11*(VERI_TABANI!$B$13-VERI_TABANI!$B$14)) + (VERI_TABANI!D27*C11*(VERI_TABANI!$B$13-VERI_TABANI!$B$15)) + IF(ISNUMBER(SEARCH("Var", D11)), VERI_TABANI!F27*(0.00202-VERI_TABANI!$B$16), IF(ISNUMBER(SEARCH("Gri", D11)), VERI_TABANI!F27*(0.00202-VERI_TABANI!$B$17), 0))) + ((VERI_TABANI!D28*B11*(VERI_TABANI!$B$13-VERI_TABANI!$B$14)) + (VERI_TABANI!D28*C11*(VERI_TABANI!$B$13-VERI_TABANI!$B$15)) + IF(ISNUMBER(SEARCH("Var", D11)), VERI_TABANI!F28*(0.00202-VERI_TABANI!$B$16), IF(ISNUMBER(SEARCH("Gri", D11)), VERI_TABANI!F28*(0.00202-VERI_TABANI!$B$17), 0)))) | I11: =IFERROR(((VERI_TABANI!$D$29*B11*VERI_TABANI!$B$14 + VERI_TABANI!$D$29*C11*VERI_TABANI!$B$15 + IF(ISNUMBER(SEARCH("Var", D11)), VERI_TABANI!$F$29*VERI_TABANI!$B$16, 0))) / (((VERI_TABANI!$D$29*B11 + VERI_TABANI!$D$29*C11)*VERI_TABANI!$B$13 + IF(ISNUMBER(SEARCH("Var", D11)), VERI_TABANI!$E$29*(1-0.928)*VERI_TABANI!$B$18, 0))), 0) | J11: =IFERROR(F11/(G11/29), 0) | K11: =IF(F11>0, H11/F11, 0) | L11: =IF(F11>0, I11, 1000000000) | M11: =ABS((B11+C11)-1) | N11: =IF(F11>0, (G11/29)/F11, 0) | O11: =IF(AND((B11+C11)>=1, ISNUMBER(SEARCH("Var", D11))), F11, 1000000000) | P11: =IF(F11>0, SQRT((F11/MAX(F$5:F$886))^2 + (1 - H11/MAX(H$5:H$886))^2 + (J11/MAX(J$5:J$886))^2), 1000000000) | Q11: =IF(AND(ABS(B11-0.5)<0.01, ABS(C11-0.5)<0.01, ISNUMBER(SEARCH("Var", D11))), 1, 0) | R11: =IF(F11>0, J11, 1000000000) | S11: =IF(AND(F11<=DASHBOARD!$B$11, H11>=DASHBOARD!$B$13), G11, -1000000000000) | T11: =IF(AND(F11<=DASHBOARD!$B$11, H11>=DASHBOARD!$B$13), R11, 1000000000000) | U11: =IF(AND(F11<=DASHBOARD!$B$11, H11>=DASHBOARD!$B$13), N11, -1000000000000) | V11: =IF(AND(F11<=DASHBOARD!$B$11, H11>=DASHBOARD!$B$13), H11, -1000000000000) | W11: =IF(AND(F11<=DASHBOARD!$B$11, H11>=DASHBOARD!$B$13), K11, -1000000000000) | X11: =IF(AND(F11<=DASHBOARD!$B$11, H11>=DASHBOARD!$B$13), M11, 1000000000000) | Y11: =IF(AND(F11<=DASHBOARD!$B$10, H11>=DASHBOARD!$B$11), L11, 1000000000000) | Z11: =IF(AND(F11<=DASHBOARD!$B$10, H11>=DASHBOARD!$B$11), O11, 1000000000000) | AA11: =IF(AND(F11<=DASHBOARD!$B$10, H11>=DASHBOARD!$B$11), P11, 1000000000000) | AB11: =IF(AND(F11<=DASHBOARD!$B$10, H11>=DASHBOARD!$B$11), Q11, -1000000000000)
A12: 8 | B12: 0 | C12: 0.3 | D12: Var (%20) | E12: =IF((B12+C12)<=1, "Tam Mahsuplaşma (≤%100)", "Kısmi Satış (>%100)") | F12: =((VERI_TABANI!$D$29*B12/VERI_TABANI!$B$29)/VERI_TABANI!$B$3)*VERI_TABANI!$B$5 + ((VERI_TABANI!$D$29*C12/VERI_TABANI!$B$29)/VERI_TABANI!$B$4)*VERI_TABANI!$B$6 + IF(ISNUMBER(SEARCH("Var", D12)), (VERI_TABANI!$F$29/VERI_TABANI!$B$29)*(VERI_TABANI!$B$10+VERI_TABANI!$B$12), 0) | G12: =(((MIN(VERI_TABANI!D23, VERI_TABANI!D23*B12)*VERI_TABANI!$B$7 + MAX(0, VERI_TABANI!D23*B12-VERI_TABANI!D23)*VERI_TABANI!$B$8) + (MIN(MAX(0, VERI_TABANI!D23-VERI_TABANI!D23*B12), VERI_TABANI!D23*C12)*VERI_TABANI!$B$7 + MAX(0, VERI_TABANI!D23*C12-MAX(0, VERI_TABANI!D23-VERI_TABANI!D23*B12))*VERI_TABANI!$B$8) + IF(ABS(IF(ISNUMBER(SEARCH("Var", D12)), 1, IF(ISNUMBER(SEARCH("Gri", D12)), -1, 0)))=1, VERI_TABANI!E23*(1-0.928)*VERI_TABANI!$B$9, 0) + (VERI_TABANI!D23*B12*(VERI_TABANI!$B$13-VERI_TABANI!$B$14)*VERI_TABANI!G23) + (VERI_TABANI!D23*C12*(VERI_TABANI!$B$13-VERI_TABANI!$B$15)*VERI_TABANI!G23) + IF(ABS(IF(ISNUMBER(SEARCH("Var", D12)), 1, IF(ISNUMBER(SEARCH("Gri", D12)), -1, 0)))=1, VERI_TABANI!E23*(1-0.928)*0.00206091519919798*VERI_TABANI!G23, 0)) + ((MIN(VERI_TABANI!D24, VERI_TABANI!D24*B12)*VERI_TABANI!$B$7 + MAX(0, VERI_TABANI!D24*B12-VERI_TABANI!D24)*VERI_TABANI!$B$8) + (MIN(MAX(0, VERI_TABANI!D24-VERI_TABANI!D24*B12), VERI_TABANI!D24*C12)*VERI_TABANI!$B$7 + MAX(0, VERI_TABANI!D24*C12-MAX(0, VERI_TABANI!D24-VERI_TABANI!D24*B12))*VERI_TABANI!$B$8) + IF(ABS(IF(ISNUMBER(SEARCH("Var", D12)), 1, IF(ISNUMBER(SEARCH("Gri", D12)), -1, 0)))=1, VERI_TABANI!E24*(1-0.928)*VERI_TABANI!$B$9, 0) + (VERI_TABANI!D24*B12*(VERI_TABANI!$B$13-VERI_TABANI!$B$14)*VERI_TABANI!G24) + (VERI_TABANI!D24*C12*(VERI_TABANI!$B$13-VERI_TABANI!$B$15)*VERI_TABANI!G24) + IF(ABS(IF(ISNUMBER(SEARCH("Var", D12)), 1, IF(ISNUMBER(SEARCH("Gri", D12)), -1, 0)))=1, VERI_TABANI!E24*(1-0.928)*0.00206091519919798*VERI_TABANI!G24, 0)) + ((MIN(VERI_TABANI!D25, VERI_TABANI!D25*B12)*VERI_TABANI!$B$7 + MAX(0, VERI_TABANI!D25*B12-VERI_TABANI!D25)*VERI_TABANI!$B$8) + (MIN(MAX(0, VERI_TABANI!D25-VERI_TABANI!D25*B12), VERI_TABANI!D25*C12)*VERI_TABANI!$B$7 + MAX(0, VERI_TABANI!D25*C12-MAX(0, VERI_TABANI!D25-VERI_TABANI!D25*B12))*VERI_TABANI!$B$8) + IF(ABS(IF(ISNUMBER(SEARCH("Var", D12)), 1, IF(ISNUMBER(SEARCH("Gri", D12)), -1, 0)))=1, VERI_TABANI!E25*(1-0.928)*VERI_TABANI!$B$9, 0) + (VERI_TABANI!D25*B12*(VERI_TABANI!$B$13-VERI_TABANI!$B$14)*VERI_TABANI!G25) + (VERI_TABANI!D25*C12*(VERI_TABANI!$B$13-VERI_TABANI!$B$15)*VERI_TABANI!G25) + IF(ABS(IF(ISNUMBER(SEARCH("Var", D12)), 1, IF(ISNUMBER(SEARCH("Gri", D12)), -1, 0)))=1, VERI_TABANI!E25*(1-0.928)*0.00206091519919798*VERI_TABANI!G25, 0)) + ((MIN(VERI_TABANI!D26, VERI_TABANI!D26*B12)*VERI_TABANI!$B$7 + MAX(0, VERI_TABANI!D26*B12-VERI_TABANI!D26)*VERI_TABANI!$B$8) + (MIN(MAX(0, VERI_TABANI!D26-VERI_TABANI!D26*B12), VERI_TABANI!D26*C12)*VERI_TABANI!$B$7 + MAX(0, VERI_TABANI!D26*C12-MAX(0, VERI_TABANI!D26-VERI_TABANI!D26*B12))*VERI_TABANI!$B$8) + IF(ABS(IF(ISNUMBER(SEARCH("Var", D12)), 1, IF(ISNUMBER(SEARCH("Gri", D12)), -1, 0)))=1, VERI_TABANI!E26*(1-0.928)*VERI_TABANI!$B$9, 0) + (VERI_TABANI!D26*B12*(VERI_TABANI!$B$13-VERI_TABANI!$B$14)*VERI_TABANI!G26) + (VERI_TABANI!D26*C12*(VERI_TABANI!$B$13-VERI_TABANI!$B$15)*VERI_TABANI!G26) + IF(ABS(IF(ISNUMBER(SEARCH("Var", D12)), 1, IF(ISNUMBER(SEARCH("Gri", D12)), -1, 0)))=1, VERI_TABANI!E26*(1-0.928)*0.00206091519919798*VERI_TABANI!G26, 0)) + ((MIN(VERI_TABANI!D27, VERI_TABANI!D27*B12)*VERI_TABANI!$B$7 + MAX(0, VERI_TABANI!D27*B12-VERI_TABANI!D27)*VERI_TABANI!$B$8) + (MIN(MAX(0, VERI_TABANI!D27-VERI_TABANI!D27*B12), VERI_TABANI!D27*C12)*VERI_TABANI!$B$7 + MAX(0, VERI_TABANI!D27*C12-MAX(0, VERI_TABANI!D27-VERI_TABANI!D27*B12))*VERI_TABANI!$B$8) + IF(ABS(IF(ISNUMBER(SEARCH("Var", D12)), 1, IF(ISNUMBER(SEARCH("Gri", D12)), -1, 0)))=1, VERI_TABANI!E27*(1-0.928)*VERI_TABANI!$B$9, 0) + (VERI_TABANI!D27*B12*(VERI_TABANI!$B$13-VERI_TABANI!$B$14)*VERI_TABANI!G27) + (VERI_TABANI!D27*C12*(VERI_TABANI!$B$13-VERI_TABANI!$B$15)*VERI_TABANI!G27) + IF(ABS(IF(ISNUMBER(SEARCH("Var", D12)), 1, IF(ISNUMBER(SEARCH("Gri", D12)), -1, 0)))=1, VERI_TABANI!E27*(1-0.928)*0.00206091519919798*VERI_TABANI!G27, 0)) + ((MIN(VERI_TABANI!D28, VERI_TABANI!D28*B12)*VERI_TABANI!$B$7 + MAX(0, VERI_TABANI!D28*B12-VERI_TABANI!D28)*VERI_TABANI!$B$8) + (MIN(MAX(0, VERI_TABANI!D28-VERI_TABANI!D28*B12), VERI_TABANI!D28*C12)*VERI_TABANI!$B$7 + MAX(0, VERI_TABANI!D28*C12-MAX(0, VERI_TABANI!D28-VERI_TABANI!D28*B12))*VERI_TABANI!$B$8) + IF(ABS(IF(ISNUMBER(SEARCH("Var", D12)), 1, IF(ISNUMBER(SEARCH("Gri", D12)), -1, 0)))=1, VERI_TABANI!E28*(1-0.928)*VERI_TABANI!$B$9, 0) + (VERI_TABANI!D28*B12*(VERI_TABANI!$B$13-VERI_TABANI!$B$14)*VERI_TABANI!G28) + (VERI_TABANI!D28*C12*(VERI_TABANI!$B$13-VERI_TABANI!$B$15)*VERI_TABANI!G28) + IF(ABS(IF(ISNUMBER(SEARCH("Var", D12)), 1, IF(ISNUMBER(SEARCH("Gri", D12)), -1, 0)))=1, VERI_TABANI!E28*(1-0.928)*0.00206091519919798*VERI_TABANI!G28, 0))) | H12: =(((VERI_TABANI!D23*B12*(VERI_TABANI!$B$13-VERI_TABANI!$B$14)) + (VERI_TABANI!D23*C12*(VERI_TABANI!$B$13-VERI_TABANI!$B$15)) + IF(ISNUMBER(SEARCH("Var", D12)), VERI_TABANI!F23*(0.00202-VERI_TABANI!$B$16), IF(ISNUMBER(SEARCH("Gri", D12)), VERI_TABANI!F23*(0.00202-VERI_TABANI!$B$17), 0))) + ((VERI_TABANI!D24*B12*(VERI_TABANI!$B$13-VERI_TABANI!$B$14)) + (VERI_TABANI!D24*C12*(VERI_TABANI!$B$13-VERI_TABANI!$B$15)) + IF(ISNUMBER(SEARCH("Var", D12)), VERI_TABANI!F24*(0.00202-VERI_TABANI!$B$16), IF(ISNUMBER(SEARCH("Gri", D12)), VERI_TABANI!F24*(0.00202-VERI_TABANI!$B$17), 0))) + ((VERI_TABANI!D25*B12*(VERI_TABANI!$B$13-VERI_TABANI!$B$14)) + (VERI_TABANI!D25*C12*(VERI_TABANI!$B$13-VERI_TABANI!$B$15)) + IF(ISNUMBER(SEARCH("Var", D12)), VERI_TABANI!F25*(0.00202-VERI_TABANI!$B$16), IF(ISNUMBER(SEARCH("Gri", D12)), VERI_TABANI!F25*(0.00202-VERI_TABANI!$B$17), 0))) + ((VERI_TABANI!D26*B12*(VERI_TABANI!$B$13-VERI_TABANI!$B$14)) + (VERI_TABANI!D26*C12*(VERI_TABANI!$B$13-VERI_TABANI!$B$15)) + IF(ISNUMBER(SEARCH("Var", D12)), VERI_TABANI!F26*(0.00202-VERI_TABANI!$B$16), IF(ISNUMBER(SEARCH("Gri", D12)), VERI_TABANI!F26*(0.00202-VERI_TABANI!$B$17), 0))) + ((VERI_TABANI!D27*B12*(VERI_TABANI!$B$13-VERI_TABANI!$B$14)) + (VERI_TABANI!D27*C12*(VERI_TABANI!$B$13-VERI_TABANI!$B$15)) + IF(ISNUMBER(SEARCH("Var", D12)), VERI_TABANI!F27*(0.00202-VERI_TABANI!$B$16), IF(ISNUMBER(SEARCH("Gri", D12)), VERI_TABANI!F27*(0.00202-VERI_TABANI!$B$17), 0))) + ((VERI_TABANI!D28*B12*(VERI_TABANI!$B$13-VERI_TABANI!$B$14)) + (VERI_TABANI!D28*C12*(VERI_TABANI!$B$13-VERI_TABANI!$B$15)) + IF(ISNUMBER(SEARCH("Var", D12)), VERI_TABANI!F28*(0.00202-VERI_TABANI!$B$16), IF(ISNUMBER(SEARCH("Gri", D12)), VERI_TABANI!F28*(0.00202-VERI_TABANI!$B$17), 0)))) | I12: =IFERROR(((VERI_TABANI!$D$29*B12*VERI_TABANI!$B$14 + VERI_TABANI!$D$29*C12*VERI_TABANI!$B$15 + IF(ISNUMBER(SEARCH("Var", D12)), VERI_TABANI!$F$29*VERI_TABANI!$B$16, 0))) / (((VERI_TABANI!$D$29*B12 + VERI_TABANI!$D$29*C12)*VERI_TABANI!$B$13 + IF(ISNUMBER(SEARCH("Var", D12)), VERI_TABANI!$E$29*(1-0.928)*VERI_TABANI!$B$18, 0))), 0) | J12: =IFERROR(F12/(G12/29), 0) | K12: =IF(F12>0, H12/F12, 0) | L12: =IF(F12>0, I12, 1000000000) | M12: =ABS((B12+C12)-1) | N12: =IF(F12>0, (G12/29)/F12, 0) | O12: =IF(AND((B12+C12)>=1, ISNUMBER(SEARCH("Var", D12))), F12, 1000000000) | P12: =IF(F12>0, SQRT((F12/MAX(F$5:F$886))^2 + (1 - H12/MAX(H$5:H$886))^2 + (J12/MAX(J$5:J$886))^2), 1000000000) | Q12: =IF(AND(ABS(B12-0.5)<0.01, ABS(C12-0.5)<0.01, ISNUMBER(SEARCH("Var", D12))), 1, 0) | R12: =IF(F12>0, J12, 1000000000) | S12: =IF(AND(F12<=DASHBOARD!$B$11, H12>=DASHBOARD!$B$13), G12, -1000000000000) | T12: =IF(AND(F12<=DASHBOARD!$B$11, H12>=DASHBOARD!$B$13), R12, 1000000000000) | U12: =IF(AND(F12<=DASHBOARD!$B$11, H12>=DASHBOARD!$B$13), N12, -1000000000000) | V12: =IF(AND(F12<=DASHBOARD!$B$11, H12>=DASHBOARD!$B$13), H12, -1000000000000) | W12: =IF(AND(F12<=DASHBOARD!$B$11, H12>=DASHBOARD!$B$13), K12, -1000000000000) | X12: =IF(AND(F12<=DASHBOARD!$B$11, H12>=DASHBOARD!$B$13), M12, 1000000000000) | Y12: =IF(AND(F12<=DASHBOARD!$B$10, H12>=DASHBOARD!$B$11), L12, 1000000000000) | Z12: =IF(AND(F12<=DASHBOARD!$B$10, H12>=DASHBOARD!$B$11), O12, 1000000000000) | AA12: =IF(AND(F12<=DASHBOARD!$B$10, H12>=DASHBOARD!$B$11), P12, 1000000000000) | AB12: =IF(AND(F12<=DASHBOARD!$B$10, H12>=DASHBOARD!$B$11), Q12, -1000000000000)
A13: 9 | B13: 0 | C13: 0.4 | D13: Yok (%0) | E13: =IF((B13+C13)<=1, "Tam Mahsuplaşma (≤%100)", "Kısmi Satış (>%100)") | F13: =((VERI_TABANI!$D$29*B13/VERI_TABANI!$B$29)/VERI_TABANI!$B$3)*VERI_TABANI!$B$5 + ((VERI_TABANI!$D$29*C13/VERI_TABANI!$B$29)/VERI_TABANI!$B$4)*VERI_TABANI!$B$6 + IF(ISNUMBER(SEARCH("Var", D13)), (VERI_TABANI!$F$29/VERI_TABANI!$B$29)*(VERI_TABANI!$B$10+VERI_TABANI!$B$12), 0) | G13: =(((MIN(VERI_TABANI!D23, VERI_TABANI!D23*B13)*VERI_TABANI!$B$7 + MAX(0, VERI_TABANI!D23*B13-VERI_TABANI!D23)*VERI_TABANI!$B$8) + (MIN(MAX(0, VERI_TABANI!D23-VERI_TABANI!D23*B13), VERI_TABANI!D23*C13)*VERI_TABANI!$B$7 + MAX(0, VERI_TABANI!D23*C13-MAX(0, VERI_TABANI!D23-VERI_TABANI!D23*B13))*VERI_TABANI!$B$8) + IF(ABS(IF(ISNUMBER(SEARCH("Var", D13)), 1, IF(ISNUMBER(SEARCH("Gri", D13)), -1, 0)))=1, VERI_TABANI!E23*(1-0.928)*VERI_TABANI!$B$9, 0) + (VERI_TABANI!D23*B13*(VERI_TABANI!$B$13-VERI_TABANI!$B$14)*VERI_TABANI!G23) + (VERI_TABANI!D23*C13*(VERI_TABANI!$B$13-VERI_TABANI!$B$15)*VERI_TABANI!G23) + IF(ABS(IF(ISNUMBER(SEARCH("Var", D13)), 1, IF(ISNUMBER(SEARCH("Gri", D13)), -1, 0)))=1, VERI_TABANI!E23*(1-0.928)*0.00206091519919798*VERI_TABANI!G23, 0)) + ((MIN(VERI_TABANI!D24, VERI_TABANI!D24*B13)*VERI_TABANI!$B$7 + MAX(0, VERI_TABANI!D24*B13-VERI_TABANI!D24)*VERI_TABANI!$B$8) + (MIN(MAX(0, VERI_TABANI!D24-VERI_TABANI!D24*B13), VERI_TABANI!D24*C13)*VERI_TABANI!$B$7 + MAX(0, VERI_TABANI!D24*C13-MAX(0, VERI_TABANI!D24-VERI_TABANI!D24*B13))*VERI_TABANI!$B$8) + IF(ABS(IF(ISNUMBER(SEARCH("Var", D13)), 1, IF(ISNUMBER(SEARCH("Gri", D13)), -1, 0)))=1, VERI_TABANI!E24*(1-0.928)*VERI_TABANI!$B$9, 0) + (VERI_TABANI!D24*B13*(VERI_TABANI!$B$13-VERI_TABANI!$B$14)*VERI_TABANI!G24) + (VERI_TABANI!D24*C13*(VERI_TABANI!$B$13-VERI_TABANI!$B$15)*VERI_TABANI!G24) + IF(ABS(IF(ISNUMBER(SEARCH("Var", D13)), 1, IF(ISNUMBER(SEARCH("Gri", D13)), -1, 0)))=1, VERI_TABANI!E24*(1-0.928)*0.00206091519919798*VERI_TABANI!G24, 0)) + ((MIN(VERI_TABANI!D25, VERI_TABANI!D25*B13)*VERI_TABANI!$B$7 + MAX(0, VERI_TABANI!D25*B13-VERI_TABANI!D25)*VERI_TABANI!$B$8) + (MIN(MAX(0, VERI_TABANI!D25-VERI_TABANI!D25*B13), VERI_TABANI!D25*C13)*VERI_TABANI!$B$7 + MAX(0, VERI_TABANI!D25*C13-MAX(0, VERI_TABANI!D25-VERI_TABANI!D25*B13))*VERI_TABANI!$B$8) + IF(ABS(IF(ISNUMBER(SEARCH("Var", D13)), 1, IF(ISNUMBER(SEARCH("Gri", D13)), -1, 0)))=1, VERI_TABANI!E25*(1-0.928)*VERI_TABANI!$B$9, 0) + (VERI_TABANI!D25*B13*(VERI_TABANI!$B$13-VERI_TABANI!$B$14)*VERI_TABANI!G25) + (VERI_TABANI!D25*C13*(VERI_TABANI!$B$13-VERI_TABANI!$B$15)*VERI_TABANI!G25) + IF(ABS(IF(ISNUMBER(SEARCH("Var", D13)), 1, IF(ISNUMBER(SEARCH("Gri", D13)), -1, 0)))=1, VERI_TABANI!E25*(1-0.928)*0.00206091519919798*VERI_TABANI!G25, 0)) + ((MIN(VERI_TABANI!D26, VERI_TABANI!D26*B13)*VERI_TABANI!$B$7 + MAX(0, VERI_TABANI!D26*B13-VERI_TABANI!D26)*VERI_TABANI!$B$8) + (MIN(MAX(0, VERI_TABANI!D26-VERI_TABANI!D26*B13), VERI_TABANI!D26*C13)*VERI_TABANI!$B$7 + MAX(0, VERI_TABANI!D26*C13-MAX(0, VERI_TABANI!D26-VERI_TABANI!D26*B13))*VERI_TABANI!$B$8) + IF(ABS(IF(ISNUMBER(SEARCH("Var", D13)), 1, IF(ISNUMBER(SEARCH("Gri", D13)), -1, 0)))=1, VERI_TABANI!E26*(1-0.928)*VERI_TABANI!$B$9, 0) + (VERI_TABANI!D26*B13*(VERI_TABANI!$B$13-VERI_TABANI!$B$14)*VERI_TABANI!G26) + (VERI_TABANI!D26*C13*(VERI_TABANI!$B$13-VERI_TABANI!$B$15)*VERI_TABANI!G26) + IF(ABS(IF(ISNUMBER(SEARCH("Var", D13)), 1, IF(ISNUMBER(SEARCH("Gri", D13)), -1, 0)))=1, VERI_TABANI!E26*(1-0.928)*0.00206091519919798*VERI_TABANI!G26, 0)) + ((MIN(VERI_TABANI!D27, VERI_TABANI!D27*B13)*VERI_TABANI!$B$7 + MAX(0, VERI_TABANI!D27*B13-VERI_TABANI!D27)*VERI_TABANI!$B$8) + (MIN(MAX(0, VERI_TABANI!D27-VERI_TABANI!D27*B13), VERI_TABANI!D27*C13)*VERI_TABANI!$B$7 + MAX(0, VERI_TABANI!D27*C13-MAX(0, VERI_TABANI!D27-VERI_TABANI!D27*B13))*VERI_TABANI!$B$8) + IF(ABS(IF(ISNUMBER(SEARCH("Var", D13)), 1, IF(ISNUMBER(SEARCH("Gri", D13)), -1, 0)))=1, VERI_TABANI!E27*(1-0.928)*VERI_TABANI!$B$9, 0) + (VERI_TABANI!D27*B13*(VERI_TABANI!$B$13-VERI_TABANI!$B$14)*VERI_TABANI!G27) + (VERI_TABANI!D27*C13*(VERI_TABANI!$B$13-VERI_TABANI!$B$15)*VERI_TABANI!G27) + IF(ABS(IF(ISNUMBER(SEARCH("Var", D13)), 1, IF(ISNUMBER(SEARCH("Gri", D13)), -1, 0)))=1, VERI_TABANI!E27*(1-0.928)*0.00206091519919798*VERI_TABANI!G27, 0)) + ((MIN(VERI_TABANI!D28, VERI_TABANI!D28*B13)*VERI_TABANI!$B$7 + MAX(0, VERI_TABANI!D28*B13-VERI_TABANI!D28)*VERI_TABANI!$B$8) + (MIN(MAX(0, VERI_TABANI!D28-VERI_TABANI!D28*B13), VERI_TABANI!D28*C13)*VERI_TABANI!$B$7 + MAX(0, VERI_TABANI!D28*C13-MAX(0, VERI_TABANI!D28-VERI_TABANI!D28*B13))*VERI_TABANI!$B$8) + IF(ABS(IF(ISNUMBER(SEARCH("Var", D13)), 1, IF(ISNUMBER(SEARCH("Gri", D13)), -1, 0)))=1, VERI_TABANI!E28*(1-0.928)*VERI_TABANI!$B$9, 0) + (VERI_TABANI!D28*B13*(VERI_TABANI!$B$13-VERI_TABANI!$B$14)*VERI_TABANI!G28) + (VERI_TABANI!D28*C13*(VERI_TABANI!$B$13-VERI_TABANI!$B$15)*VERI_TABANI!G28) + IF(ABS(IF(ISNUMBER(SEARCH("Var", D13)), 1, IF(ISNUMBER(SEARCH("Gri", D13)), -1, 0)))=1, VERI_TABANI!E28*(1-0.928)*0.00206091519919798*VERI_TABANI!G28, 0))) | H13: =(((VERI_TABANI!D23*B13*(VERI_TABANI!$B$13-VERI_TABANI!$B$14)) + (VERI_TABANI!D23*C13*(VERI_TABANI!$B$13-VERI_TABANI!$B$15)) + IF(ISNUMBER(SEARCH("Var", D13)), VERI_TABANI!F23*(0.00202-VERI_TABANI!$B$16), IF(ISNUMBER(SEARCH("Gri", D13)), VERI_TABANI!F23*(0.00202-VERI_TABANI!$B$17), 0))) + ((VERI_TABANI!D24*B13*(VERI_TABANI!$B$13-VERI_TABANI!$B$14)) + (VERI_TABANI!D24*C13*(VERI_TABANI!$B$13-VERI_TABANI!$B$15)) + IF(ISNUMBER(SEARCH("Var", D13)), VERI_TABANI!F24*(0.00202-VERI_TABANI!$B$16), IF(ISNUMBER(SEARCH("Gri", D13)), VERI_TABANI!F24*(0.00202-VERI_TABANI!$B$17), 0))) + ((VERI_TABANI!D25*B13*(VERI_TABANI!$B$13-VERI_TABANI!$B$14)) + (VERI_TABANI!D25*C13*(VERI_TABANI!$B$13-VERI_TABANI!$B$15)) + IF(ISNUMBER(SEARCH("Var", D13)), VERI_TABANI!F25*(0.00202-VERI_TABANI!$B$16), IF(ISNUMBER(SEARCH("Gri", D13)), VERI_TABANI!F25*(0.00202-VERI_TABANI!$B$17), 0))) + ((VERI_TABANI!D26*B13*(VERI_TABANI!$B$13-VERI_TABANI!$B$14)) + (VERI_TABANI!D26*C13*(VERI_TABANI!$B$13-VERI_TABANI!$B$15)) + IF(ISNUMBER(SEARCH("Var", D13)), VERI_TABANI!F26*(0.00202-VERI_TABANI!$B$16), IF(ISNUMBER(SEARCH("Gri", D13)), VERI_TABANI!F26*(0.00202-VERI_TABANI!$B$17), 0))) + ((VERI_TABANI!D27*B13*(VERI_TABANI!$B$13-VERI_TABANI!$B$14)) + (VERI_TABANI!D27*C13*(VERI_TABANI!$B$13-VERI_TABANI!$B$15)) + IF(ISNUMBER(SEARCH("Var", D13)), VERI_TABANI!F27*(0.00202-VERI_TABANI!$B$16), IF(ISNUMBER(SEARCH("Gri", D13)), VERI_TABANI!F27*(0.00202-VERI_TABANI!$B$17), 0))) + ((VERI_TABANI!D28*B13*(VERI_TABANI!$B$13-VERI_TABANI!$B$14)) + (VERI_TABANI!D28*C13*(VERI_TABANI!$B$13-VERI_TABANI!$B$15)) + IF(ISNUMBER(SEARCH("Var", D13)), VERI_TABANI!F28*(0.00202-VERI_TABANI!$B$16), IF(ISNUMBER(SEARCH("Gri", D13)), VERI_TABANI!F28*(0.00202-VERI_TABANI!$B$17), 0)))) | I13: =IFERROR(((VERI_TABANI!$D$29*B13*VERI_TABANI!$B$14 + VERI_TABANI!$D$29*C13*VERI_TABANI!$B$15 + IF(ISNUMBER(SEARCH("Var", D13)), VERI_TABANI!$F$29*VERI_TABANI!$B$16, 0))) / (((VERI_TABANI!$D$29*B13 + VERI_TABANI!$D$29*C13)*VERI_TABANI!$B$13 + IF(ISNUMBER(SEARCH("Var", D13)), VERI_TABANI!$E$29*(1-0.928)*VERI_TABANI!$B$18, 0))), 0) | J13: =IFERROR(F13/(G13/29), 0) | K13: =IF(F13>0, H13/F13, 0) | L13: =IF(F13>0, I13, 1000000000) | M13: =ABS((B13+C13)-1) | N13: =IF(F13>0, (G13/29)/F13, 0) | O13: =IF(AND((B13+C13)>=1, ISNUMBER(SEARCH("Var", D13))), F13, 1000000000) | P13: =IF(F13>0, SQRT((F13/MAX(F$5:F$886))^2 + (1 - H13/MAX(H$5:H$886))^2 + (J13/MAX(J$5:J$886))^2), 1000000000) | Q13: =IF(AND(ABS(B13-0.5)<0.01, ABS(C13-0.5)<0.01, ISNUMBER(SEARCH("Var", D13))), 1, 0) | R13: =IF(F13>0, J13, 1000000000) | S13: =IF(AND(F13<=DASHBOARD!$B$11, H13>=DASHBOARD!$B$13), G13, -1000000000000) | T13: =IF(AND(F13<=DASHBOARD!$B$11, H13>=DASHBOARD!$B$13), R13, 1000000000000) | U13: =IF(AND(F13<=DASHBOARD!$B$11, H13>=DASHBOARD!$B$13), N13, -1000000000000) | V13: =IF(AND(F13<=DASHBOARD!$B$11, H13>=DASHBOARD!$B$13), H13, -1000000000000) | W13: =IF(AND(F13<=DASHBOARD!$B$11, H13>=DASHBOARD!$B$13), K13, -1000000000000) | X13: =IF(AND(F13<=DASHBOARD!$B$11, H13>=DASHBOARD!$B$13), M13, 1000000000000) | Y13: =IF(AND(F13<=DASHBOARD!$B$10, H13>=DASHBOARD!$B$11), L13, 1000000000000) | Z13: =IF(AND(F13<=DASHBOARD!$B$10, H13>=DASHBOARD!$B$11), O13, 1000000000000) | AA13: =IF(AND(F13<=DASHBOARD!$B$10, H13>=DASHBOARD!$B$11), P13, 1000000000000) | AB13: =IF(AND(F13<=DASHBOARD!$B$10, H13>=DASHBOARD!$B$11), Q13, -1000000000000)
A14: 10 | B14: 0 | C14: 0.4 | D14: Var (%20) | E14: =IF((B14+C14)<=1, "Tam Mahsuplaşma (≤%100)", "Kısmi Satış (>%100)") | F14: =((VERI_TABANI!$D$29*B14/VERI_TABANI!$B$29)/VERI_TABANI!$B$3)*VERI_TABANI!$B$5 + ((VERI_TABANI!$D$29*C14/VERI_TABANI!$B$29)/VERI_TABANI!$B$4)*VERI_TABANI!$B$6 + IF(ISNUMBER(SEARCH("Var", D14)), (VERI_TABANI!$F$29/VERI_TABANI!$B$29)*(VERI_TABANI!$B$10+VERI_TABANI!$B$12), 0) | G14: =(((MIN(VERI_TABANI!D23, VERI_TABANI!D23*B14)*VERI_TABANI!$B$7 + MAX(0, VERI_TABANI!D23*B14-VERI_TABANI!D23)*VERI_TABANI!$B$8) + (MIN(MAX(0, VERI_TABANI!D23-VERI_TABANI!D23*B14), VERI_TABANI!D23*C14)*VERI_TABANI!$B$7 + MAX(0, VERI_TABANI!D23*C14-MAX(0, VERI_TABANI!D23-VERI_TABANI!D23*B14))*VERI_TABANI!$B$8) + IF(ABS(IF(ISNUMBER(SEARCH("Var", D14)), 1, IF(ISNUMBER(SEARCH("Gri", D14)), -1, 0)))=1, VERI_TABANI!E23*(1-0.928)*VERI_TABANI!$B$9, 0) + (VERI_TABANI!D23*B14*(VERI_TABANI!$B$13-VERI_TABANI!$B$14)*VERI_TABANI!G23) + (VERI_TABANI!D23*C14*(VERI_TABANI!$B$13-VERI_TABANI!$B$15)*VERI_TABANI!G23) + IF(ABS(IF(ISNUMBER(SEARCH("Var", D14)), 1, IF(ISNUMBER(SEARCH("Gri", D14)), -1, 0)))=1, VERI_TABANI!E23*(1-0.928)*0.00206091519919798*VERI_TABANI!G23, 0)) + ((MIN(VERI_TABANI!D24, VERI_TABANI!D24*B14)*VERI_TABANI!$B$7 + MAX(0, VERI_TABANI!D24*B14-VERI_TABANI!D24)*VERI_TABANI!$B$8) + (MIN(MAX(0, VERI_TABANI!D24-VERI_TABANI!D24*B14), VERI_TABANI!D24*C14)*VERI_TABANI!$B$7 + MAX(0, VERI_TABANI!D24*C14-MAX(0, VERI_TABANI!D24-VERI_TABANI!D24*B14))*VERI_TABANI!$B$8) + IF(ABS(IF(ISNUMBER(SEARCH("Var", D14)), 1, IF(ISNUMBER(SEARCH("Gri", D14)), -1, 0)))=1, VERI_TABANI!E24*(1-0.928)*VERI_TABANI!$B$9, 0) + (VERI_TABANI!D24*B14*(VERI_TABANI!$B$13-VERI_TABANI!$B$14)*VERI_TABANI!G24) + (VERI_TABANI!D24*C14*(VERI_TABANI!$B$13-VERI_TABANI!$B$15)*VERI_TABANI!G24) + IF(ABS(IF(ISNUMBER(SEARCH("Var", D14)), 1, IF(ISNUMBER(SEARCH("Gri", D14)), -1, 0)))=1, VERI_TABANI!E24*(1-0.928)*0.00206091519919798*VERI_TABANI!G24, 0)) + ((MIN(VERI_TABANI!D25, VERI_TABANI!D25*B14)*VERI_TABANI!$B$7 + MAX(0, VERI_TABANI!D25*B14-VERI_TABANI!D25)*VERI_TABANI!$B$8) + (MIN(MAX(0, VERI_TABANI!D25-VERI_TABANI!D25*B14), VERI_TABANI!D25*C14)*VERI_TABANI!$B$7 + MAX(0, VERI_TABANI!D25*C14-MAX(0, VERI_TABANI!D25-VERI_TABANI!D25*B14))*VERI_TABANI!$B$8) + IF(ABS(IF(ISNUMBER(SEARCH("Var", D14)), 1, IF(ISNUMBER(SEARCH("Gri", D14)), -1, 0)))=1, VERI_TABANI!E25*(1-0.928)*VERI_TABANI!$B$9, 0) + (VERI_TABANI!D25*B14*(VERI_TABANI!$B$13-VERI_TABANI!$B$14)*VERI_TABANI!G25) + (VERI_TABANI!D25*C14*(VERI_TABANI!$B$13-VERI_TABANI!$B$15)*VERI_TABANI!G25) + IF(ABS(IF(ISNUMBER(SEARCH("Var", D14)), 1, IF(ISNUMBER(SEARCH("Gri", D14)), -1, 0)))=1, VERI_TABANI!E25*(1-0.928)*0.00206091519919798*VERI_TABANI!G25, 0)) + ((MIN(VERI_TABANI!D26, VERI_TABANI!D26*B14)*VERI_TABANI!$B$7 + MAX(0, VERI_TABANI!D26*B14-VERI_TABANI!D26)*VERI_TABANI!$B$8) + (MIN(MAX(0, VERI_TABANI!D26-VERI_TABANI!D26*B14), VERI_TABANI!D26*C14)*VERI_TABANI!$B$7 + MAX(0, VERI_TABANI!D26*C14-MAX(0, VERI_TABANI!D26-VERI_TABANI!D26*B14))*VERI_TABANI!$B$8) + IF(ABS(IF(ISNUMBER(SEARCH("Var", D14)), 1, IF(ISNUMBER(SEARCH("Gri", D14)), -1, 0)))=1, VERI_TABANI!E26*(1-0.928)*VERI_TABANI!$B$9, 0) + (VERI_TABANI!D26*B14*(VERI_TABANI!$B$13-VERI_TABANI!$B$14)*VERI_TABANI!G26) + (VERI_TABANI!D26*C14*(VERI_TABANI!$B$13-VERI_TABANI!$B$15)*VERI_TABANI!G26) + IF(ABS(IF(ISNUMBER(SEARCH("Var", D14)), 1, IF(ISNUMBER(SEARCH("Gri", D14)), -1, 0)))=1, VERI_TABANI!E26*(1-0.928)*0.00206091519919798*VERI_TABANI!G26, 0)) + ((MIN(VERI_TABANI!D27, VERI_TABANI!D27*B14)*VERI_TABANI!$B$7 + MAX(0, VERI_TABANI!D27*B14-VERI_TABANI!D27)*VERI_TABANI!$B$8) + (MIN(MAX(0, VERI_TABANI!D27-VERI_TABANI!D27*B14), VERI_TABANI!D27*C14)*VERI_TABANI!$B$7 + MAX(0, VERI_TABANI!D27*C14-MAX(0, VERI_TABANI!D27-VERI_TABANI!D27*B14))*VERI_TABANI!$B$8) + IF(ABS(IF(ISNUMBER(SEARCH("Var", D14)), 1, IF(ISNUMBER(SEARCH("Gri", D14)), -1, 0)))=1, VERI_TABANI!E27*(1-0.928)*VERI_TABANI!$B$9, 0) + (VERI_TABANI!D27*B14*(VERI_TABANI!$B$13-VERI_TABANI!$B$14)*VERI_TABANI!G27) + (VERI_TABANI!D27*C14*(VERI_TABANI!$B$13-VERI_TABANI!$B$15)*VERI_TABANI!G27) + IF(ABS(IF(ISNUMBER(SEARCH("Var", D14)), 1, IF(ISNUMBER(SEARCH("Gri", D14)), -1, 0)))=1, VERI_TABANI!E27*(1-0.928)*0.00206091519919798*VERI_TABANI!G27, 0)) + ((MIN(VERI_TABANI!D28, VERI_TABANI!D28*B14)*VERI_TABANI!$B$7 + MAX(0, VERI_TABANI!D28*B14-VERI_TABANI!D28)*VERI_TABANI!$B$8) + (MIN(MAX(0, VERI_TABANI!D28-VERI_TABANI!D28*B14), VERI_TABANI!D28*C14)*VERI_TABANI!$B$7 + MAX(0, VERI_TABANI!D28*C14-MAX(0, VERI_TABANI!D28-VERI_TABANI!D28*B14))*VERI_TABANI!$B$8) + IF(ABS(IF(ISNUMBER(SEARCH("Var", D14)), 1, IF(ISNUMBER(SEARCH("Gri", D14)), -1, 0)))=1, VERI_TABANI!E28*(1-0.928)*VERI_TABANI!$B$9, 0) + (VERI_TABANI!D28*B14*(VERI_TABANI!$B$13-VERI_TABANI!$B$14)*VERI_TABANI!G28) + (VERI_TABANI!D28*C14*(VERI_TABANI!$B$13-VERI_TABANI!$B$15)*VERI_TABANI!G28) + IF(ABS(IF(ISNUMBER(SEARCH("Var", D14)), 1, IF(ISNUMBER(SEARCH("Gri", D14)), -1, 0)))=1, VERI_TABANI!E28*(1-0.928)*0.00206091519919798*VERI_TABANI!G28, 0))) | H14: =(((VERI_TABANI!D23*B14*(VERI_TABANI!$B$13-VERI_TABANI!$B$14)) + (VERI_TABANI!D23*C14*(VERI_TABANI!$B$13-VERI_TABANI!$B$15)) + IF(ISNUMBER(SEARCH("Var", D14)), VERI_TABANI!F23*(0.00202-VERI_TABANI!$B$16), IF(ISNUMBER(SEARCH("Gri", D14)), VERI_TABANI!F23*(0.00202-VERI_TABANI!$B$17), 0))) + ((VERI_TABANI!D24*B14*(VERI_TABANI!$B$13-VERI_TABANI!$B$14)) + (VERI_TABANI!D24*C14*(VERI_TABANI!$B$13-VERI_TABANI!$B$15)) + IF(ISNUMBER(SEARCH("Var", D14)), VERI_TABANI!F24*(0.00202-VERI_TABANI!$B$16), IF(ISNUMBER(SEARCH("Gri", D14)), VERI_TABANI!F24*(0.00202-VERI_TABANI!$B$17), 0))) + ((VERI_TABANI!D25*B14*(VERI_TABANI!$B$13-VERI_TABANI!$B$14)) + (VERI_TABANI!D25*C14*(VERI_TABANI!$B$13-VERI_TABANI!$B$15)) + IF(ISNUMBER(SEARCH("Var", D14)), VERI_TABANI!F25*(0.00202-VERI_TABANI!$B$16), IF(ISNUMBER(SEARCH("Gri", D14)), VERI_TABANI!F25*(0.00202-VERI_TABANI!$B$17), 0))) + ((VERI_TABANI!D26*B14*(VERI_TABANI!$B$13-VERI_TABANI!$B$14)) + (VERI_TABANI!D26*C14*(VERI_TABANI!$B$13-VERI_TABANI!$B$15)) + IF(ISNUMBER(SEARCH("Var", D14)), VERI_TABANI!F26*(0.00202-VERI_TABANI!$B$16), IF(ISNUMBER(SEARCH("Gri", D14)), VERI_TABANI!F26*(0.00202-VERI_TABANI!$B$17), 0))) + ((VERI_TABANI!D27*B14*(VERI_TABANI!$B$13-VERI_TABANI!$B$14)) + (VERI_TABANI!D27*C14*(VERI_TABANI!$B$13-VERI_TABANI!$B$15)) + IF(ISNUMBER(SEARCH("Var", D14)), VERI_TABANI!F27*(0.00202-VERI_TABANI!$B$16), IF(ISNUMBER(SEARCH("Gri", D14)), VERI_TABANI!F27*(0.00202-VERI_TABANI!$B$17), 0))) + ((VERI_TABANI!D28*B14*(VERI_TABANI!$B$13-VERI_TABANI!$B$14)) + (VERI_TABANI!D28*C14*(VERI_TABANI!$B$13-VERI_TABANI!$B$15)) + IF(ISNUMBER(SEARCH("Var", D14)), VERI_TABANI!F28*(0.00202-VERI_TABANI!$B$16), IF(ISNUMBER(SEARCH("Gri", D14)), VERI_TABANI!F28*(0.00202-VERI_TABANI!$B$17), 0)))) | I14: =IFERROR(((VERI_TABANI!$D$29*B14*VERI_TABANI!$B$14 + VERI_TABANI!$D$29*C14*VERI_TABANI!$B$15 + IF(ISNUMBER(SEARCH("Var", D14)), VERI_TABANI!$F$29*VERI_TABANI!$B$16, 0))) / (((VERI_TABANI!$D$29*B14 + VERI_TABANI!$D$29*C14)*VERI_TABANI!$B$13 + IF(ISNUMBER(SEARCH("Var", D14)), VERI_TABANI!$E$29*(1-0.928)*VERI_TABANI!$B$18, 0))), 0) | J14: =IFERROR(F14/(G14/29), 0) | K14: =IF(F14>0, H14/F14, 0) | L14: =IF(F14>0, I14, 1000000000) | M14: =ABS((B14+C14)-1) | N14: =IF(F14>0, (G14/29)/F14, 0) | O14: =IF(AND((B14+C14)>=1, ISNUMBER(SEARCH("Var", D14))), F14, 1000000000) | P14: =IF(F14>0, SQRT((F14/MAX(F$5:F$886))^2 + (1 - H14/MAX(H$5:H$886))^2 + (J14/MAX(J$5:J$886))^2), 1000000000) | Q14: =IF(AND(ABS(B14-0.5)<0.01, ABS(C14-0.5)<0.01, ISNUMBER(SEARCH("Var", D14))), 1, 0) | R14: =IF(F14>0, J14, 1000000000) | S14: =IF(AND(F14<=DASHBOARD!$B$11, H14>=DASHBOARD!$B$13), G14, -1000000000000) | T14: =IF(AND(F14<=DASHBOARD!$B$11, H14>=DASHBOARD!$B$13), R14, 1000000000000) | U14: =IF(AND(F14<=DASHBOARD!$B$11, H14>=DASHBOARD!$B$13), N14, -1000000000000) | V14: =IF(AND(F14<=DASHBOARD!$B$11, H14>=DASHBOARD!$B$13), H14, -1000000000000) | W14: =IF(AND(F14<=DASHBOARD!$B$11, H14>=DASHBOARD!$B$13), K14, -1000000000000) | X14: =IF(AND(F14<=DASHBOARD!$B$11, H14>=DASHBOARD!$B$13), M14, 1000000000000) | Y14: =IF(AND(F14<=DASHBOARD!$B$10, H14>=DASHBOARD!$B$11), L14, 1000000000000) | Z14: =IF(AND(F14<=DASHBOARD!$B$10, H14>=DASHBOARD!$B$11), O14, 1000000000000) | AA14: =IF(AND(F14<=DASHBOARD!$B$10, H14>=DASHBOARD!$B$11), P14, 1000000000000) | AB14: =IF(AND(F14<=DASHBOARD!$B$10, H14>=DASHBOARD!$B$11), Q14, -1000000000000)
A15: 11 | B15: 0 | C15: 0.5 | D15: Yok (%0) | E15: =IF((B15+C15)<=1, "Tam Mahsuplaşma (≤%100)", "Kısmi Satış (>%100)") | F15: =((VERI_TABANI!$D$29*B15/VERI_TABANI!$B$29)/VERI_TABANI!$B$3)*VERI_TABANI!$B$5 + ((VERI_TABANI!$D$29*C15/VERI_TABANI!$B$29)/VERI_TABANI!$B$4)*VERI_TABANI!$B$6 + IF(ISNUMBER(SEARCH("Var", D15)), (VERI_TABANI!$F$29/VERI_TABANI!$B$29)*(VERI_TABANI!$B$10+VERI_TABANI!$B$12), 0) | G15: =(((MIN(VERI_TABANI!D23, VERI_TABANI!D23*B15)*VERI_TABANI!$B$7 + MAX(0, VERI_TABANI!D23*B15-VERI_TABANI!D23)*VERI_TABANI!$B$8) + (MIN(MAX(0, VERI_TABANI!D23-VERI_TABANI!D23*B15), VERI_TABANI!D23*C15)*VERI_TABANI!$B$7 + MAX(0, VERI_TABANI!D23*C15-MAX(0, VERI_TABANI!D23-VERI_TABANI!D23*B15))*VERI_TABANI!$B$8) + IF(ABS(IF(ISNUMBER(SEARCH("Var", D15)), 1, IF(ISNUMBER(SEARCH("Gri", D15)), -1, 0)))=1, VERI_TABANI!E23*(1-0.928)*VERI_TABANI!$B$9, 0) + (VERI_TABANI!D23*B15*(VERI_TABANI!$B$13-VERI_TABANI!$B$14)*VERI_TABANI!G23) + (VERI_TABANI!D23*C15*(VERI_TABANI!$B$13-VERI_TABANI!$B$15)*VERI_TABANI!G23) + IF(ABS(IF(ISNUMBER(SEARCH("Var", D15)), 1, IF(ISNUMBER(SEARCH("Gri", D15)), -1, 0)))=1, VERI_TABANI!E23*(1-0.928)*0.00206091519919798*VERI_TABANI!G23, 0)) + ((MIN(VERI_TABANI!D24, VERI_TABANI!D24*B15)*VERI_TABANI!$B$7 + MAX(0, VERI_TABANI!D24*B15-VERI_TABANI!D24)*VERI_TABANI!$B$8) + (MIN(MAX(0, VERI_TABANI!D24-VERI_TABANI!D24*B15), VERI_TABANI!D24*C15)*VERI_TABANI!$B$7 + MAX(0, VERI_TABANI!D24*C15-MAX(0, VERI_TABANI!D24-VERI_TABANI!D24*B15))*VERI_TABANI!$B$8) + IF(ABS(IF(ISNUMBER(SEARCH("Var", D15)), 1, IF(ISNUMBER(SEARCH("Gri", D15)), -1, 0)))=1, VERI_TABANI!E24*(1-0.928)*VERI_TABANI!$B$9, 0) + (VERI_TABANI!D24*B15*(VERI_TABANI!$B$13-VERI_TABANI!$B$14)*VERI_TABANI!G24) + (VERI_TABANI!D24*C15*(VERI_TABANI!$B$13-VERI_TABANI!$B$15)*VERI_TABANI!G24) + IF(ABS(IF(ISNUMBER(SEARCH("Var", D15)), 1, IF(ISNUMBER(SEARCH("Gri", D15)), -1, 0)))=1, VERI_TABANI!E24*(1-0.928)*0.00206091519919798*VERI_TABANI!G24, 0)) + ((MIN(VERI_TABANI!D25, VERI_TABANI!D25*B15)*VERI_TABANI!$B$7 + MAX(0, VERI_TABANI!D25*B15-VERI_TABANI!D25)*VERI_TABANI!$B$8) + (MIN(MAX(0, VERI_TABANI!D25-VERI_TABANI!D25*B15), VERI_TABANI!D25*C15)*VERI_TABANI!$B$7 + MAX(0, VERI_TABANI!D25*C15-MAX(0, VERI_TABANI!D25-VERI_TABANI!D25*B15))*VERI_TABANI!$B$8) + IF(ABS(IF(ISNUMBER(SEARCH("Var", D15)), 1, IF(ISNUMBER(SEARCH("Gri", D15)), -1, 0)))=1, VERI_TABANI!E25*(1-0.928)*VERI_TABANI!$B$9, 0) + (VERI_TABANI!D25*B15*(VERI_TABANI!$B$13-VERI_TABANI!$B$14)*VERI_TABANI!G25) + (VERI_TABANI!D25*C15*(VERI_TABANI!$B$13-VERI_TABANI!$B$15)*VERI_TABANI!G25) + IF(ABS(IF(ISNUMBER(SEARCH("Var", D15)), 1, IF(ISNUMBER(SEARCH("Gri", D15)), -1, 0)))=1, VERI_TABANI!E25*(1-0.928)*0.00206091519919798*VERI_TABANI!G25, 0)) + ((MIN(VERI_TABANI!D26, VERI_TABANI!D26*B15)*VERI_TABANI!$B$7 + MAX(0, VERI_TABANI!D26*B15-VERI_TABANI!D26)*VERI_TABANI!$B$8) + (MIN(MAX(0, VERI_TABANI!D26-VERI_TABANI!D26*B15), VERI_TABANI!D26*C15)*VERI_TABANI!$B$7 + MAX(0, VERI_TABANI!D26*C15-MAX(0, VERI_TABANI!D26-VERI_TABANI!D26*B15))*VERI_TABANI!$B$8) + IF(ABS(IF(ISNUMBER(SEARCH("Var", D15)), 1, IF(ISNUMBER(SEARCH("Gri", D15)), -1, 0)))=1, VERI_TABANI!E26*(1-0.928)*VERI_TABANI!$B$9, 0) + (VERI_TABANI!D26*B15*(VERI_TABANI!$B$13-VERI_TABANI!$B$14)*VERI_TABANI!G26) + (VERI_TABANI!D26*C15*(VERI_TABANI!$B$13-VERI_TABANI!$B$15)*VERI_TABANI!G26) + IF(ABS(IF(ISNUMBER(SEARCH("Var", D15)), 1, IF(ISNUMBER(SEARCH("Gri", D15)), -1, 0)))=1, VERI_TABANI!E26*(1-0.928)*0.00206091519919798*VERI_TABANI!G26, 0)) + ((MIN(VERI_TABANI!D27, VERI_TABANI!D27*B15)*VERI_TABANI!$B$7 + MAX(0, VERI_TABANI!D27*B15-VERI_TABANI!D27)*VERI_TABANI!$B$8) + (MIN(MAX(0, VERI_TABANI!D27-VERI_TABANI!D27*B15), VERI_TABANI!D27*C15)*VERI_TABANI!$B$7 + MAX(0, VERI_TABANI!D27*C15-MAX(0, VERI_TABANI!D27-VERI_TABANI!D27*B15))*VERI_TABANI!$B$8) + IF(ABS(IF(ISNUMBER(SEARCH("Var", D15)), 1, IF(ISNUMBER(SEARCH("Gri", D15)), -1, 0)))=1, VERI_TABANI!E27*(1-0.928)*VERI_TABANI!$B$9, 0) + (VERI_TABANI!D27*B15*(VERI_TABANI!$B$13-VERI_TABANI!$B$14)*VERI_TABANI!G27) + (VERI_TABANI!D27*C15*(VERI_TABANI!$B$13-VERI_TABANI!$B$15)*VERI_TABANI!G27) + IF(ABS(IF(ISNUMBER(SEARCH("Var", D15)), 1, IF(ISNUMBER(SEARCH("Gri", D15)), -1, 0)))=1, VERI_TABANI!E27*(1-0.928)*0.00206091519919798*VERI_TABANI!G27, 0)) + ((MIN(VERI_TABANI!D28, VERI_TABANI!D28*B15)*VERI_TABANI!$B$7 + MAX(0, VERI_TABANI!D28*B15-VERI_TABANI!D28)*VERI_TABANI!$B$8) + (MIN(MAX(0, VERI_TABANI!D28-VERI_TABANI!D28*B15), VERI_TABANI!D28*C15)*VERI_TABANI!$B$7 + MAX(0, VERI_TABANI!D28*C15-MAX(0, VERI_TABANI!D28-VERI_TABANI!D28*B15))*VERI_TABANI!$B$8) + IF(ABS(IF(ISNUMBER(SEARCH("Var", D15)), 1, IF(ISNUMBER(SEARCH("Gri", D15)), -1, 0)))=1, VERI_TABANI!E28*(1-0.928)*VERI_TABANI!$B$9, 0) + (VERI_TABANI!D28*B15*(VERI_TABANI!$B$13-VERI_TABANI!$B$14)*VERI_TABANI!G28) + (VERI_TABANI!D28*C15*(VERI_TABANI!$B$13-VERI_TABANI!$B$15)*VERI_TABANI!G28) + IF(ABS(IF(ISNUMBER(SEARCH("Var", D15)), 1, IF(ISNUMBER(SEARCH("Gri", D15)), -1, 0)))=1, VERI_TABANI!E28*(1-0.928)*0.00206091519919798*VERI_TABANI!G28, 0))) | H15: =(((VERI_TABANI!D23*B15*(VERI_TABANI!$B$13-VERI_TABANI!$B$14)) + (VERI_TABANI!D23*C15*(VERI_TABANI!$B$13-VERI_TABANI!$B$15)) + IF(ISNUMBER(SEARCH("Var", D15)), VERI_TABANI!F23*(0.00202-VERI_TABANI!$B$16), IF(ISNUMBER(SEARCH("Gri", D15)), VERI_TABANI!F23*(0.00202-VERI_TABANI!$B$17), 0))) + ((VERI_TABANI!D24*B15*(VERI_TABANI!$B$13-VERI_TABANI!$B$14)) + (VERI_TABANI!D24*C15*(VERI_TABANI!$B$13-VERI_TABANI!$B$15)) + IF(ISNUMBER(SEARCH("Var", D15)), VERI_TABANI!F24*(0.00202-VERI_TABANI!$B$16), IF(ISNUMBER(SEARCH("Gri", D15)), VERI_TABANI!F24*(0.00202-VERI_TABANI!$B$17), 0))) + ((VERI_TABANI!D25*B15*(VERI_TABANI!$B$13-VERI_TABANI!$B$14)) + (VERI_TABANI!D25*C15*(VERI_TABANI!$B$13-VERI_TABANI!$B$15)) + IF(ISNUMBER(SEARCH("Var", D15)), VERI_TABANI!F25*(0.00202-VERI_TABANI!$B$16), IF(ISNUMBER(SEARCH("Gri", D15)), VERI_TABANI!F25*(0.00202-VERI_TABANI!$B$17), 0))) + ((VERI_TABANI!D26*B15*(VERI_TABANI!$B$13-VERI_TABANI!$B$14)) + (VERI_TABANI!D26*C15*(VERI_TABANI!$B$13-VERI_TABANI!$B$15)) + IF(ISNUMBER(SEARCH("Var", D15)), VERI_TABANI!F26*(0.00202-VERI_TABANI!$B$16), IF(ISNUMBER(SEARCH("Gri", D15)), VERI_TABANI!F26*(0.00202-VERI_TABANI!$B$17), 0))) + ((VERI_TABANI!D27*B15*(VERI_TABANI!$B$13-VERI_TABANI!$B$14)) + (VERI_TABANI!D27*C15*(VERI_TABANI!$B$13-VERI_TABANI!$B$15)) + IF(ISNUMBER(SEARCH("Var", D15)), VERI_TABANI!F27*(0.00202-VERI_TABANI!$B$16), IF(ISNUMBER(SEARCH("Gri", D15)), VERI_TABANI!F27*(0.00202-VERI_TABANI!$B$17), 0))) + ((VERI_TABANI!D28*B15*(VERI_TABANI!$B$13-VERI_TABANI!$B$14)) + (VERI_TABANI!D28*C15*(VERI_TABANI!$B$13-VERI_TABANI!$B$15)) + IF(ISNUMBER(SEARCH("Var", D15)), VERI_TABANI!F28*(0.00202-VERI_TABANI!$B$16), IF(ISNUMBER(SEARCH("Gri", D15)), VERI_TABANI!F28*(0.00202-VERI_TABANI!$B$17), 0)))) | I15: =IFERROR(((VERI_TABANI!$D$29*B15*VERI_TABANI!$B$14 + VERI_TABANI!$D$29*C15*VERI_TABANI!$B$15 + IF(ISNUMBER(SEARCH("Var", D15)), VERI_TABANI!$F$29*VERI_TABANI!$B$16, 0))) / (((VERI_TABANI!$D$29*B15 + VERI_TABANI!$D$29*C15)*VERI_TABANI!$B$13 + IF(ISNUMBER(SEARCH("Var", D15)), VERI_TABANI!$E$29*(1-0.928)*VERI_TABANI!$B$18, 0))), 0) | J15: =IFERROR(F15/(G15/29), 0) | K15: =IF(F15>0, H15/F15, 0) | L15: =IF(F15>0, I15, 1000000000) | M15: =ABS((B15+C15)-1) | N15: =IF(F15>0, (G15/29)/F15, 0) | O15: =IF(AND((B15+C15)>=1, ISNUMBER(SEARCH("Var", D15))), F15, 1000000000) | P15: =IF(F15>0, SQRT((F15/MAX(F$5:F$886))^2 + (1 - H15/MAX(H$5:H$886))^2 + (J15/MAX(J$5:J$886))^2), 1000000000) | Q15: =IF(AND(ABS(B15-0.5)<0.01, ABS(C15-0.5)<0.01, ISNUMBER(SEARCH("Var", D15))), 1, 0) | R15: =IF(F15>0, J15, 1000000000) | S15: =IF(AND(F15<=DASHBOARD!$B$11, H15>=DASHBOARD!$B$13), G15, -1000000000000) | T15: =IF(AND(F15<=DASHBOARD!$B$11, H15>=DASHBOARD!$B$13), R15, 1000000000000) | U15: =IF(AND(F15<=DASHBOARD!$B$11, H15>=DASHBOARD!$B$13), N15, -1000000000000) | V15: =IF(AND(F15<=DASHBOARD!$B$11, H15>=DASHBOARD!$B$13), H15, -1000000000000) | W15: =IF(AND(F15<=DASHBOARD!$B$11, H15>=DASHBOARD!$B$13), K15, -1000000000000) | X15: =IF(AND(F15<=DASHBOARD!$B$11, H15>=DASHBOARD!$B$13), M15, 1000000000000) | Y15: =IF(AND(F15<=DASHBOARD!$B$10, H15>=DASHBOARD!$B$11), L15, 1000000000000) | Z15: =IF(AND(F15<=DASHBOARD!$B$10, H15>=DASHBOARD!$B$11), O15, 1000000000000) | AA15: =IF(AND(F15<=DASHBOARD!$B$10, H15>=DASHBOARD!$B$11), P15, 1000000000000) | AB15: =IF(AND(F15<=DASHBOARD!$B$10, H15>=DASHBOARD!$B$11), Q15, -1000000000000)
A16: 12 | B16: 0 | C16: 0.5 | D16: Var (%20) | E16: =IF((B16+C16)<=1, "Tam Mahsuplaşma (≤%100)", "Kısmi Satış (>%100)") | F16: =((VERI_TABANI!$D$29*B16/VERI_TABANI!$B$29)/VERI_TABANI!$B$3)*VERI_TABANI!$B$5 + ((VERI_TABANI!$D$29*C16/VERI_TABANI!$B$29)/VERI_TABANI!$B$4)*VERI_TABANI!$B$6 + IF(ISNUMBER(SEARCH("Var", D16)), (VERI_TABANI!$F$29/VERI_TABANI!$B$29)*(VERI_TABANI!$B$10+VERI_TABANI!$B$12), 0) | G16: =(((MIN(VERI_TABANI!D23, VERI_TABANI!D23*B16)*VERI_TABANI!$B$7 + MAX(0, VERI_TABANI!D23*B16-VERI_TABANI!D23)*VERI_TABANI!$B$8) + (MIN(MAX(0, VERI_TABANI!D23-VERI_TABANI!D23*B16), VERI_TABANI!D23*C16)*VERI_TABANI!$B$7 + MAX(0, VERI_TABANI!D23*C16-MAX(0, VERI_TABANI!D23-VERI_TABANI!D23*B16))*VERI_TABANI!$B$8) + IF(ABS(IF(ISNUMBER(SEARCH("Var", D16)), 1, IF(ISNUMBER(SEARCH("Gri", D16)), -1, 0)))=1, VERI_TABANI!E23*(1-0.928)*VERI_TABANI!$B$9, 0) + (VERI_TABANI!D23*B16*(VERI_TABANI!$B$13-VERI_TABANI!$B$14)*VERI_TABANI!G23) + (VERI_TABANI!D23*C16*(VERI_TABANI!$B$13-VERI_TABANI!$B$15)*VERI_TABANI!G23) + IF(ABS(IF(ISNUMBER(SEARCH("Var", D16)), 1, IF(ISNUMBER(SEARCH("Gri", D16)), -1, 0)))=1, VERI_TABANI!E23*(1-0.928)*0.00206091519919798*VERI_TABANI!G23, 0)) + ((MIN(VERI_TABANI!D24, VERI_TABANI!D24*B16)*VERI_TABANI!$B$7 + MAX(0, VERI_TABANI!D24*B16-VERI_TABANI!D24)*VERI_TABANI!$B$8) + (MIN(MAX(0, VERI_TABANI!D24-VERI_TABANI!D24*B16), VERI_TABANI!D24*C16)*VERI_TABANI!$B$7 + MAX(0, VERI_TABANI!D24*C16-MAX(0, VERI_TABANI!D24-VERI_TABANI!D24*B16))*VERI_TABANI!$B$8) + IF(ABS(IF(ISNUMBER(SEARCH("Var", D16)), 1, IF(ISNUMBER(SEARCH("Gri", D16)), -1, 0)))=1, VERI_TABANI!E24*(1-0.928)*VERI_TABANI!$B$9, 0) + (VERI_TABANI!D24*B16*(VERI_TABANI!$B$13-VERI_TABANI!$B$14)*VERI_TABANI!G24) + (VERI_TABANI!D24*C16*(VERI_TABANI!$B$13-VERI_TABANI!$B$15)*VERI_TABANI!G24) + IF(ABS(IF(ISNUMBER(SEARCH("Var", D16)), 1, IF(ISNUMBER(SEARCH("Gri", D16)), -1, 0)))=1, VERI_TABANI!E24*(1-0.928)*0.00206091519919798*VERI_TABANI!G24, 0)) + ((MIN(VERI_TABANI!D25, VERI_TABANI!D25*B16)*VERI_TABANI!$B$7 + MAX(0, VERI_TABANI!D25*B16-VERI_TABANI!D25)*VERI_TABANI!$B$8) + (MIN(MAX(0, VERI_TABANI!D25-VERI_TABANI!D25*B16), VERI_TABANI!D25*C16)*VERI_TABANI!$B$7 + MAX(0, VERI_TABANI!D25*C16-MAX(0, VERI_TABANI!D25-VERI_TABANI!D25*B16))*VERI_TABANI!$B$8) + IF(ABS(IF(ISNUMBER(SEARCH("Var", D16)), 1, IF(ISNUMBER(SEARCH("Gri", D16)), -1, 0)))=1, VERI_TABANI!E25*(1-0.928)*VERI_TABANI!$B$9, 0) + (VERI_TABANI!D25*B16*(VERI_TABANI!$B$13-VERI_TABANI!$B$14)*VERI_TABANI!G25) + (VERI_TABANI!D25*C16*(VERI_TABANI!$B$13-VERI_TABANI!$B$15)*VERI_TABANI!G25) + IF(ABS(IF(ISNUMBER(SEARCH("Var", D16)), 1, IF(ISNUMBER(SEARCH("Gri", D16)), -1, 0)))=1, VERI_TABANI!E25*(1-0.928)*0.00206091519919798*VERI_TABANI!G25, 0)) + ((MIN(VERI_TABANI!D26, VERI_TABANI!D26*B16)*VERI_TABANI!$B$7 + MAX(0, VERI_TABANI!D26*B16-VERI_TABANI!D26)*VERI_TABANI!$B$8) + (MIN(MAX(0, VERI_TABANI!D26-VERI_TABANI!D26*B16), VERI_TABANI!D26*C16)*VERI_TABANI!$B$7 + MAX(0, VERI_TABANI!D26*C16-MAX(0, VERI_TABANI!D26-VERI_TABANI!D26*B16))*VERI_TABANI!$B$8) + IF(ABS(IF(ISNUMBER(SEARCH("Var", D16)), 1, IF(ISNUMBER(SEARCH("Gri", D16)), -1, 0)))=1, VERI_TABANI!E26*(1-0.928)*VERI_TABANI!$B$9, 0) + (VERI_TABANI!D26*B16*(VERI_TABANI!$B$13-VERI_TABANI!$B$14)*VERI_TABANI!G26) + (VERI_TABANI!D26*C16*(VERI_TABANI!$B$13-VERI_TABANI!$B$15)*VERI_TABANI!G26) + IF(ABS(IF(ISNUMBER(SEARCH("Var", D16)), 1, IF(ISNUMBER(SEARCH("Gri", D16)), -1, 0)))=1, VERI_TABANI!E26*(1-0.928)*0.00206091519919798*VERI_TABANI!G26, 0)) + ((MIN(VERI_TABANI!D27, VERI_TABANI!D27*B16)*VERI_TABANI!$B$7 + MAX(0, VERI_TABANI!D27*B16-VERI_TABANI!D27)*VERI_TABANI!$B$8) + (MIN(MAX(0, VERI_TABANI!D27-VERI_TABANI!D27*B16), VERI_TABANI!D27*C16)*VERI_TABANI!$B$7 + MAX(0, VERI_TABANI!D27*C16-MAX(0, VERI_TABANI!D27-VERI_TABANI!D27*B16))*VERI_TABANI!$B$8) + IF(ABS(IF(ISNUMBER(SEARCH("Var", D16)), 1, IF(ISNUMBER(SEARCH("Gri", D16)), -1, 0)))=1, VERI_TABANI!E27*(1-0.928)*VERI_TABANI!$B$9, 0) + (VERI_TABANI!D27*B16*(VERI_TABANI!$B$13-VERI_TABANI!$B$14)*VERI_TABANI!G27) + (VERI_TABANI!D27*C16*(VERI_TABANI!$B$13-VERI_TABANI!$B$15)*VERI_TABANI!G27) + IF(ABS(IF(ISNUMBER(SEARCH("Var", D16)), 1, IF(ISNUMBER(SEARCH("Gri", D16)), -1, 0)))=1, VERI_TABANI!E27*(1-0.928)*0.00206091519919798*VERI_TABANI!G27, 0)) + ((MIN(VERI_TABANI!D28, VERI_TABANI!D28*B16)*VERI_TABANI!$B$7 + MAX(0, VERI_TABANI!D28*B16-VERI_TABANI!D28)*VERI_TABANI!$B$8) + (MIN(MAX(0, VERI_TABANI!D28-VERI_TABANI!D28*B16), VERI_TABANI!D28*C16)*VERI_TABANI!$B$7 + MAX(0, VERI_TABANI!D28*C16-MAX(0, VERI_TABANI!D28-VERI_TABANI!D28*B16))*VERI_TABANI!$B$8) + IF(ABS(IF(ISNUMBER(SEARCH("Var", D16)), 1, IF(ISNUMBER(SEARCH("Gri", D16)), -1, 0)))=1, VERI_TABANI!E28*(1-0.928)*VERI_TABANI!$B$9, 0) + (VERI_TABANI!D28*B16*(VERI_TABANI!$B$13-VERI_TABANI!$B$14)*VERI_TABANI!G28) + (VERI_TABANI!D28*C16*(VERI_TABANI!$B$13-VERI_TABANI!$B$15)*VERI_TABANI!G28) + IF(ABS(IF(ISNUMBER(SEARCH("Var", D16)), 1, IF(ISNUMBER(SEARCH("Gri", D16)), -1, 0)))=1, VERI_TABANI!E28*(1-0.928)*0.00206091519919798*VERI_TABANI!G28, 0))) | H16: =(((VERI_TABANI!D23*B16*(VERI_TABANI!$B$13-VERI_TABANI!$B$14)) + (VERI_TABANI!D23*C16*(VERI_TABANI!$B$13-VERI_TABANI!$B$15)) + IF(ISNUMBER(SEARCH("Var", D16)), VERI_TABANI!F23*(0.00202-VERI_TABANI!$B$16), IF(ISNUMBER(SEARCH("Gri", D16)), VERI_TABANI!F23*(0.00202-VERI_TABANI!$B$17), 0))) + ((VERI_TABANI!D24*B16*(VERI_TABANI!$B$13-VERI_TABANI!$B$14)) + (VERI_TABANI!D24*C16*(VERI_TABANI!$B$13-VERI_TABANI!$B$15)) + IF(ISNUMBER(SEARCH("Var", D16)), VERI_TABANI!F24*(0.00202-VERI_TABANI!$B$16), IF(ISNUMBER(SEARCH("Gri", D16)), VERI_TABANI!F24*(0.00202-VERI_TABANI!$B$17), 0))) + ((VERI_TABANI!D25*B16*(VERI_TABANI!$B$13-VERI_TABANI!$B$14)) + (VERI_TABANI!D25*C16*(VERI_TABANI!$B$13-VERI_TABANI!$B$15)) + IF(ISNUMBER(SEARCH("Var", D16)), VERI_TABANI!F25*(0.00202-VERI_TABANI!$B$16), IF(ISNUMBER(SEARCH("Gri", D16)), VERI_TABANI!F25*(0.00202-VERI_TABANI!$B$17), 0))) + ((VERI_TABANI!D26*B16*(VERI_TABANI!$B$13-VERI_TABANI!$B$14)) + (VERI_TABANI!D26*C16*(VERI_TABANI!$B$13-VERI_TABANI!$B$15)) + IF(ISNUMBER(SEARCH("Var", D16)), VERI_TABANI!F26*(0.00202-VERI_TABANI!$B$16), IF(ISNUMBER(SEARCH("Gri", D16)), VERI_TABANI!F26*(0.00202-VERI_TABANI!$B$17), 0))) + ((VERI_TABANI!D27*B16*(VERI_TABANI!$B$13-VERI_TABANI!$B$14)) + (VERI_TABANI!D27*C16*(VERI_TABANI!$B$13-VERI_TABANI!$B$15)) + IF(ISNUMBER(SEARCH("Var", D16)), VERI_TABANI!F27*(0.00202-VERI_TABANI!$B$16), IF(ISNUMBER(SEARCH("Gri", D16)), VERI_TABANI!F27*(0.00202-VERI_TABANI!$B$17), 0))) + ((VERI_TABANI!D28*B16*(VERI_TABANI!$B$13-VERI_TABANI!$B$14)) + (VERI_TABANI!D28*C16*(VERI_TABANI!$B$13-VERI_TABANI!$B$15)) + IF(ISNUMBER(SEARCH("Var", D16)), VERI_TABANI!F28*(0.00202-VERI_TABANI!$B$16), IF(ISNUMBER(SEARCH("Gri", D16)), VERI_TABANI!F28*(0.00202-VERI_TABANI!$B$17), 0)))) | I16: =IFERROR(((VERI_TABANI!$D$29*B16*VERI_TABANI!$B$14 + VERI_TABANI!$D$29*C16*VERI_TABANI!$B$15 + IF(ISNUMBER(SEARCH("Var", D16)), VERI_TABANI!$F$29*VERI_TABANI!$B$16, 0))) / (((VERI_TABANI!$D$29*B16 + VERI_TABANI!$D$29*C16)*VERI_TABANI!$B$13 + IF(ISNUMBER(SEARCH("Var", D16)), VERI_TABANI!$E$29*(1-0.928)*VERI_TABANI!$B$18, 0))), 0) | J16: =IFERROR(F16/(G16/29), 0) | K16: =IF(F16>0, H16/F16, 0) | L16: =IF(F16>0, I16, 1000000000) | M16: =ABS((B16+C16)-1) | N16: =IF(F16>0, (G16/29)/F16, 0) | O16: =IF(AND((B16+C16)>=1, ISNUMBER(SEARCH("Var", D16))), F16, 1000000000) | P16: =IF(F16>0, SQRT((F16/MAX(F$5:F$886))^2 + (1 - H16/MAX(H$5:H$886))^2 + (J16/MAX(J$5:J$886))^2), 1000000000) | Q16: =IF(AND(ABS(B16-0.5)<0.01, ABS(C16-0.5)<0.01, ISNUMBER(SEARCH("Var", D16))), 1, 0) | R16: =IF(F16>0, J16, 1000000000) | S16: =IF(AND(F16<=DASHBOARD!$B$11, H16>=DASHBOARD!$B$13), G16, -1000000000000) | T16: =IF(AND(F16<=DASHBOARD!$B$11, H16>=DASHBOARD!$B$13), R16, 1000000000000) | U16: =IF(AND(F16<=DASHBOARD!$B$11, H16>=DASHBOARD!$B$13), N16, -1000000000000) | V16: =IF(AND(F16<=DASHBOARD!$B$11, H16>=DASHBOARD!$B$13), H16, -1000000000000) | W16: =IF(AND(F16<=DASHBOARD!$B$11, H16>=DASHBOARD!$B$13), K16, -1000000000000) | X16: =IF(AND(F16<=DASHBOARD!$B$11, H16>=DASHBOARD!$B$13), M16, 1000000000000) | Y16: =IF(AND(F16<=DASHBOARD!$B$10, H16>=DASHBOARD!$B$11), L16, 1000000000000) | Z16: =IF(AND(F16<=DASHBOARD!$B$10, H16>=DASHBOARD!$B$11), O16, 1000000000000) | AA16: =IF(AND(F16<=DASHBOARD!$B$10, H16>=DASHBOARD!$B$11), P16, 1000000000000) | AB16: =IF(AND(F16<=DASHBOARD!$B$10, H16>=DASHBOARD!$B$11), Q16, -1000000000000)
A17: 13 | B17: 0 | C17: 0.6 | D17: Yok (%0) | E17: =IF((B17+C17)<=1, "Tam Mahsuplaşma (≤%100)", "Kısmi Satış (>%100)") | F17: =((VERI_TABANI!$D$29*B17/VERI_TABANI!$B$29)/VERI_TABANI!$B$3)*VERI_TABANI!$B$5 + ((VERI_TABANI!$D$29*C17/VERI_TABANI!$B$29)/VERI_TABANI!$B$4)*VERI_TABANI!$B$6 + IF(ISNUMBER(SEARCH("Var", D17)), (VERI_TABANI!$F$29/VERI_TABANI!$B$29)*(VERI_TABANI!$B$10+VERI_TABANI!$B$12), 0) | G17: =(((MIN(VERI_TABANI!D23, VERI_TABANI!D23*B17)*VERI_TABANI!$B$7 + MAX(0, VERI_TABANI!D23*B17-VERI_TABANI!D23)*VERI_TABANI!$B$8) + (MIN(MAX(0, VERI_TABANI!D23-VERI_TABANI!D23*B17), VERI_TABANI!D23*C17)*VERI_TABANI!$B$7 + MAX(0, VERI_TABANI!D23*C17-MAX(0, VERI_TABANI!D23-VERI_TABANI!D23*B17))*VERI_TABANI!$B$8) + IF(ABS(IF(ISNUMBER(SEARCH("Var", D17)), 1, IF(ISNUMBER(SEARCH("Gri", D17)), -1, 0)))=1, VERI_TABANI!E23*(1-0.928)*VERI_TABANI!$B$9, 0) + (VERI_TABANI!D23*B17*(VERI_TABANI!$B$13-VERI_TABANI!$B$14)*VERI_TABANI!G23) + (VERI_TABANI!D23*C17*(VERI_TABANI!$B$13-VERI_TABANI!$B$15)*VERI_TABANI!G23) + IF(ABS(IF(ISNUMBER(SEARCH("Var", D17)), 1, IF(ISNUMBER(SEARCH("Gri", D17)), -1, 0)))=1, VERI_TABANI!E23*(1-0.928)*0.00206091519919798*VERI_TABANI!G23, 0)) + ((MIN(VERI_TABANI!D24, VERI_TABANI!D24*B17)*VERI_TABANI!$B$7 + MAX(0, VERI_TABANI!D24*B17-VERI_TABANI!D24)*VERI_TABANI!$B$8) + (MIN(MAX(0, VERI_TABANI!D24-VERI_TABANI!D24*B17), VERI_TABANI!D24*C17)*VERI_TABANI!$B$7 + MAX(0, VERI_TABANI!D24*C17-MAX(0, VERI_TABANI!D24-VERI_TABANI!D24*B17))*VERI_TABANI!$B$8) + IF(ABS(IF(ISNUMBER(SEARCH("Var", D17)), 1, IF(ISNUMBER(SEARCH("Gri", D17)), -1, 0)))=1, VERI_TABANI!E24*(1-0.928)*VERI_TABANI!$B$9, 0) + (VERI_TABANI!D24*B17*(VERI_TABANI!$B$13-VERI_TABANI!$B$14)*VERI_TABANI!G24) + (VERI_TABANI!D24*C17*(VERI_TABANI!$B$13-VERI_TABANI!$B$15)*VERI_TABANI!G24) + IF(ABS(IF(ISNUMBER(SEARCH("Var", D17)), 1, IF(ISNUMBER(SEARCH("Gri", D17)), -1, 0)))=1, VERI_TABANI!E24*(1-0.928)*0.00206091519919798*VERI_TABANI!G24, 0)) + ((MIN(VERI_TABANI!D25, VERI_TABANI!D25*B17)*VERI_TABANI!$B$7 + MAX(0, VERI_TABANI!D25*B17-VERI_TABANI!D25)*VERI_TABANI!$B$8) + (MIN(MAX(0, VERI_TABANI!D25-VERI_TABANI!D25*B17), VERI_TABANI!D25*C17)*VERI_TABANI!$B$7 + MAX(0, VERI_TABANI!D25*C17-MAX(0, VERI_TABANI!D25-VERI_TABANI!D25*B17))*VERI_TABANI!$B$8) + IF(ABS(IF(ISNUMBER(SEARCH("Var", D17)), 1, IF(ISNUMBER(SEARCH("Gri", D17)), -1, 0)))=1, VERI_TABANI!E25*(1-0.928)*VERI_TABANI!$B$9, 0) + (VERI_TABANI!D25*B17*(VERI_TABANI!$B$13-VERI_TABANI!$B$14)*VERI_TABANI!G25) + (VERI_TABANI!D25*C17*(VERI_TABANI!$B$13-VERI_TABANI!$B$15)*VERI_TABANI!G25) + IF(ABS(IF(ISNUMBER(SEARCH("Var", D17)), 1, IF(ISNUMBER(SEARCH("Gri", D17)), -1, 0)))=1, VERI_TABANI!E25*(1-0.928)*0.00206091519919798*VERI_TABANI!G25, 0)) + ((MIN(VERI_TABANI!D26, VERI_TABANI!D26*B17)*VERI_TABANI!$B$7 + MAX(0, VERI_TABANI!D26*B17-VERI_TABANI!D26)*VERI_TABANI!$B$8) + (MIN(MAX(0, VERI_TABANI!D26-VERI_TABANI!D26*B17), VERI_TABANI!D26*C17)*VERI_TABANI!$B$7 + MAX(0, VERI_TABANI!D26*C17-MAX(0, VERI_TABANI!D26-VERI_TABANI!D26*B17))*VERI_TABANI!$B$8) + IF(ABS(IF(ISNUMBER(SEARCH("Var", D17)), 1, IF(ISNUMBER(SEARCH("Gri", D17)), -1, 0)))=1, VERI_TABANI!E26*(1-0.928)*VERI_TABANI!$B$9, 0) + (VERI_TABANI!D26*B17*(VERI_TABANI!$B$13-VERI_TABANI!$B$14)*VERI_TABANI!G26) + (VERI_TABANI!D26*C17*(VERI_TABANI!$B$13-VERI_TABANI!$B$15)*VERI_TABANI!G26) + IF(ABS(IF(ISNUMBER(SEARCH("Var", D17)), 1, IF(ISNUMBER(SEARCH("Gri", D17)), -1, 0)))=1, VERI_TABANI!E26*(1-0.928)*0.00206091519919798*VERI_TABANI!G26, 0)) + ((MIN(VERI_TABANI!D27, VERI_TABANI!D27*B17)*VERI_TABANI!$B$7 + MAX(0, VERI_TABANI!D27*B17-VERI_TABANI!D27)*VERI_TABANI!$B$8) + (MIN(MAX(0, VERI_TABANI!D27-VERI_TABANI!D27*B17), VERI_TABANI!D27*C17)*VERI_TABANI!$B$7 + MAX(0, VERI_TABANI!D27*C17-MAX(0, VERI_TABANI!D27-VERI_TABANI!D27*B17))*VERI_TABANI!$B$8) + IF(ABS(IF(ISNUMBER(SEARCH("Var", D17)), 1, IF(ISNUMBER(SEARCH("Gri", D17)), -1, 0)))=1, VERI_TABANI!E27*(1-0.928)*VERI_TABANI!$B$9, 0) + (VERI_TABANI!D27*B17*(VERI_TABANI!$B$13-VERI_TABANI!$B$14)*VERI_TABANI!G27) + (VERI_TABANI!D27*C17*(VERI_TABANI!$B$13-VERI_TABANI!$B$15)*VERI_TABANI!G27) + IF(ABS(IF(ISNUMBER(SEARCH("Var", D17)), 1, IF(ISNUMBER(SEARCH("Gri", D17)), -1, 0)))=1, VERI_TABANI!E27*(1-0.928)*0.00206091519919798*VERI_TABANI!G27, 0)) + ((MIN(VERI_TABANI!D28, VERI_TABANI!D28*B17)*VERI_TABANI!$B$7 + MAX(0, VERI_TABANI!D28*B17-VERI_TABANI!D28)*VERI_TABANI!$B$8) + (MIN(MAX(0, VERI_TABANI!D28-VERI_TABANI!D28*B17), VERI_TABANI!D28*C17)*VERI_TABANI!$B$7 + MAX(0, VERI_TABANI!D28*C17-MAX(0, VERI_TABANI!D28-VERI_TABANI!D28*B17))*VERI_TABANI!$B$8) + IF(ABS(IF(ISNUMBER(SEARCH("Var", D17)), 1, IF(ISNUMBER(SEARCH("Gri", D17)), -1, 0)))=1, VERI_TABANI!E28*(1-0.928)*VERI_TABANI!$B$9, 0) + (VERI_TABANI!D28*B17*(VERI_TABANI!$B$13-VERI_TABANI!$B$14)*VERI_TABANI!G28) + (VERI_TABANI!D28*C17*(VERI_TABANI!$B$13-VERI_TABANI!$B$15)*VERI_TABANI!G28) + IF(ABS(IF(ISNUMBER(SEARCH("Var", D17)), 1, IF(ISNUMBER(SEARCH("Gri", D17)), -1, 0)))=1, VERI_TABANI!E28*(1-0.928)*0.00206091519919798*VERI_TABANI!G28, 0))) | H17: =(((VERI_TABANI!D23*B17*(VERI_TABANI!$B$13-VERI_TABANI!$B$14)) + (VERI_TABANI!D23*C17*(VERI_TABANI!$B$13-VERI_TABANI!$B$15)) + IF(ISNUMBER(SEARCH("Var", D17)), VERI_TABANI!F23*(0.00202-VERI_TABANI!$B$16), IF(ISNUMBER(SEARCH("Gri", D17)), VERI_TABANI!F23*(0.00202-VERI_TABANI!$B$17), 0))) + ((VERI_TABANI!D24*B17*(VERI_TABANI!$B$13-VERI_TABANI!$B$14)) + (VERI_TABANI!D24*C17*(VERI_TABANI!$B$13-VERI_TABANI!$B$15)) + IF(ISNUMBER(SEARCH("Var", D17)), VERI_TABANI!F24*(0.00202-VERI_TABANI!$B$16), IF(ISNUMBER(SEARCH("Gri", D17)), VERI_TABANI!F24*(0.00202-VERI_TABANI!$B$17), 0))) + ((VERI_TABANI!D25*B17*(VERI_TABANI!$B$13-VERI_TABANI!$B$14)) + (VERI_TABANI!D25*C17*(VERI_TABANI!$B$13-VERI_TABANI!$B$15)) + IF(ISNUMBER(SEARCH("Var", D17)), VERI_TABANI!F25*(0.00202-VERI_TABANI!$B$16), IF(ISNUMBER(SEARCH("Gri", D17)), VERI_TABANI!F25*(0.00202-VERI_TABANI!$B$17), 0))) + ((VERI_TABANI!D26*B17*(VERI_TABANI!$B$13-VERI_TABANI!$B$14)) + (VERI_TABANI!D26*C17*(VERI_TABANI!$B$13-VERI_TABANI!$B$15)) + IF(ISNUMBER(SEARCH("Var", D17)), VERI_TABANI!F26*(0.00202-VERI_TABANI!$B$16), IF(ISNUMBER(SEARCH("Gri", D17)), VERI_TABANI!F26*(0.00202-VERI_TABANI!$B$17), 0))) + ((VERI_TABANI!D27*B17*(VERI_TABANI!$B$13-VERI_TABANI!$B$14)) + (VERI_TABANI!D27*C17*(VERI_TABANI!$B$13-VERI_TABANI!$B$15)) + IF(ISNUMBER(SEARCH("Var", D17)), VERI_TABANI!F27*(0.00202-VERI_TABANI!$B$16), IF(ISNUMBER(SEARCH("Gri", D17)), VERI_TABANI!F27*(0.00202-VERI_TABANI!$B$17), 0))) + ((VERI_TABANI!D28*B17*(VERI_TABANI!$B$13-VERI_TABANI!$B$14)) + (VERI_TABANI!D28*C17*(VERI_TABANI!$B$13-VERI_TABANI!$B$15)) + IF(ISNUMBER(SEARCH("Var", D17)), VERI_TABANI!F28*(0.00202-VERI_TABANI!$B$16), IF(ISNUMBER(SEARCH("Gri", D17)), VERI_TABANI!F28*(0.00202-VERI_TABANI!$B$17), 0)))) | I17: =IFERROR(((VERI_TABANI!$D$29*B17*VERI_TABANI!$B$14 + VERI_TABANI!$D$29*C17*VERI_TABANI!$B$15 + IF(ISNUMBER(SEARCH("Var", D17)), VERI_TABANI!$F$29*VERI_TABANI!$B$16, 0))) / (((VERI_TABANI!$D$29*B17 + VERI_TABANI!$D$29*C17)*VERI_TABANI!$B$13 + IF(ISNUMBER(SEARCH("Var", D17)), VERI_TABANI!$E$29*(1-0.928)*VERI_TABANI!$B$18, 0))), 0) | J17: =IFERROR(F17/(G17/29), 0) | K17: =IF(F17>0, H17/F17, 0) | L17: =IF(F17>0, I17, 1000000000) | M17: =ABS((B17+C17)-1) | N17: =IF(F17>0, (G17/29)/F17, 0) | O17: =IF(AND((B17+C17)>=1, ISNUMBER(SEARCH("Var", D17))), F17, 1000000000) | P17: =IF(F17>0, SQRT((F17/MAX(F$5:F$886))^2 + (1 - H17/MAX(H$5:H$886))^2 + (J17/MAX(J$5:J$886))^2), 1000000000) | Q17: =IF(AND(ABS(B17-0.5)<0.01, ABS(C17-0.5)<0.01, ISNUMBER(SEARCH("Var", D17))), 1, 0) | R17: =IF(F17>0, J17, 1000000000) | S17: =IF(AND(F17<=DASHBOARD!$B$11, H17>=DASHBOARD!$B$13), G17, -1000000000000) | T17: =IF(AND(F17<=DASHBOARD!$B$11, H17>=DASHBOARD!$B$13), R17, 1000000000000) | U17: =IF(AND(F17<=DASHBOARD!$B$11, H17>=DASHBOARD!$B$13), N17, -1000000000000) | V17: =IF(AND(F17<=DASHBOARD!$B$11, H17>=DASHBOARD!$B$13), H17, -1000000000000) | W17: =IF(AND(F17<=DASHBOARD!$B$11, H17>=DASHBOARD!$B$13), K17, -1000000000000) | X17: =IF(AND(F17<=DASHBOARD!$B$11, H17>=DASHBOARD!$B$13), M17, 1000000000000) | Y17: =IF(AND(F17<=DASHBOARD!$B$10, H17>=DASHBOARD!$B$11), L17, 1000000000000) | Z17: =IF(AND(F17<=DASHBOARD!$B$10, H17>=DASHBOARD!$B$11), O17, 1000000000000) | AA17: =IF(AND(F17<=DASHBOARD!$B$10, H17>=DASHBOARD!$B$11), P17, 1000000000000) | AB17: =IF(AND(F17<=DASHBOARD!$B$10, H17>=DASHBOARD!$B$11), Q17, -1000000000000)
A18: 14 | B18: 0 | C18: 0.6 | D18: Var (%20) | E18: =IF((B18+C18)<=1, "Tam Mahsuplaşma (≤%100)", "Kısmi Satış (>%100)") | F18: =((VERI_TABANI!$D$29*B18/VERI_TABANI!$B$29)/VERI_TABANI!$B$3)*VERI_TABANI!$B$5 + ((VERI_TABANI!$D$29*C18/VERI_TABANI!$B$29)/VERI_TABANI!$B$4)*VERI_TABANI!$B$6 + IF(ISNUMBER(SEARCH("Var", D18)), (VERI_TABANI!$F$29/VERI_TABANI!$B$29)*(VERI_TABANI!$B$10+VERI_TABANI!$B$12), 0) | G18: =(((MIN(VERI_TABANI!D23, VERI_TABANI!D23*B18)*VERI_TABANI!$B$7 + MAX(0, VERI_TABANI!D23*B18-VERI_TABANI!D23)*VERI_TABANI!$B$8) + (MIN(MAX(0, VERI_TABANI!D23-VERI_TABANI!D23*B18), VERI_TABANI!D23*C18)*VERI_TABANI!$B$7 + MAX(0, VERI_TABANI!D23*C18-MAX(0, VERI_TABANI!D23-VERI_TABANI!D23*B18))*VERI_TABANI!$B$8) + IF(ABS(IF(ISNUMBER(SEARCH("Var", D18)), 1, IF(ISNUMBER(SEARCH("Gri", D18)), -1, 0)))=1, VERI_TABANI!E23*(1-0.928)*VERI_TABANI!$B$9, 0) + (VERI_TABANI!D23*B18*(VERI_TABANI!$B$13-VERI_TABANI!$B$14)*VERI_TABANI!G23) + (VERI_TABANI!D23*C18*(VERI_TABANI!$B$13-VERI_TABANI!$B$15)*VERI_TABANI!G23) + IF(ABS(IF(ISNUMBER(SEARCH("Var", D18)), 1, IF(ISNUMBER(SEARCH("Gri", D18)), -1, 0)))=1, VERI_TABANI!E23*(1-0.928)*0.00206091519919798*VERI_TABANI!G23, 0)) + ((MIN(VERI_TABANI!D24, VERI_TABANI!D24*B18)*VERI_TABANI!$B$7 + MAX(0, VERI_TABANI!D24*B18-VERI_TABANI!D24)*VERI_TABANI!$B$8) + (MIN(MAX(0, VERI_TABANI!D24-VERI_TABANI!D24*B18), VERI_TABANI!D24*C18)*VERI_TABANI!$B$7 + MAX(0, VERI_TABANI!D24*C18-MAX(0, VERI_TABANI!D24-VERI_TABANI!D24*B18))*VERI_TABANI!$B$8) + IF(ABS(IF(ISNUMBER(SEARCH("Var", D18)), 1, IF(ISNUMBER(SEARCH("Gri", D18)), -1, 0)))=1, VERI_TABANI!E24*(1-0.928)*VERI_TABANI!$B$9, 0) + (VERI_TABANI!D24*B18*(VERI_TABANI!$B$13-VERI_TABANI!$B$14)*VERI_TABANI!G24) + (VERI_TABANI!D24*C18*(VERI_TABANI!$B$13-VERI_TABANI!$B$15)*VERI_TABANI!G24) + IF(ABS(IF(ISNUMBER(SEARCH("Var", D18)), 1, IF(ISNUMBER(SEARCH("Gri", D18)), -1, 0)))=1, VERI_TABANI!E24*(1-0.928)*0.00206091519919798*VERI_TABANI!G24, 0)) + ((MIN(VERI_TABANI!D25, VERI_TABANI!D25*B18)*VERI_TABANI!$B$7 + MAX(0, VERI_TABANI!D25*B18-VERI_TABANI!D25)*VERI_TABANI!$B$8) + (MIN(MAX(0, VERI_TABANI!D25-VERI_TABANI!D25*B18), VERI_TABANI!D25*C18)*VERI_TABANI!$B$7 + MAX(0, VERI_TABANI!D25*C18-MAX(0, VERI_TABANI!D25-VERI_TABANI!D25*B18))*VERI_TABANI!$B$8) + IF(ABS(IF(ISNUMBER(SEARCH("Var", D18)), 1, IF(ISNUMBER(SEARCH("Gri", D18)), -1, 0)))=1, VERI_TABANI!E25*(1-0.928)*VERI_TABANI!$B$9, 0) + (VERI_TABANI!D25*B18*(VERI_TABANI!$B$13-VERI_TABANI!$B$14)*VERI_TABANI!G25) + (VERI_TABANI!D25*C18*(VERI_TABANI!$B$13-VERI_TABANI!$B$15)*VERI_TABANI!G25) + IF(ABS(IF(ISNUMBER(SEARCH("Var", D18)), 1, IF(ISNUMBER(SEARCH("Gri", D18)), -1, 0)))=1, VERI_TABANI!E25*(1-0.928)*0.00206091519919798*VERI_TABANI!G25, 0)) + ((MIN(VERI_TABANI!D26, VERI_TABANI!D26*B18)*VERI_TABANI!$B$7 + MAX(0, VERI_TABANI!D26*B18-VERI_TABANI!D26)*VERI_TABANI!$B$8) + (MIN(MAX(0, VERI_TABANI!D26-VERI_TABANI!D26*B18), VERI_TABANI!D26*C18)*VERI_TABANI!$B$7 + MAX(0, VERI_TABANI!D26*C18-MAX(0, VERI_TABANI!D26-VERI_TABANI!D26*B18))*VERI_TABANI!$B$8) + IF(ABS(IF(ISNUMBER(SEARCH("Var", D18)), 1, IF(ISNUMBER(SEARCH("Gri", D18)), -1, 0)))=1, VERI_TABANI!E26*(1-0.928)*VERI_TABANI!$B$9, 0) + (VERI_TABANI!D26*B18*(VERI_TABANI!$B$13-VERI_TABANI!$B$14)*VERI_TABANI!G26) + (VERI_TABANI!D26*C18*(VERI_TABANI!$B$13-VERI_TABANI!$B$15)*VERI_TABANI!G26) + IF(ABS(IF(ISNUMBER(SEARCH("Var", D18)), 1, IF(ISNUMBER(SEARCH("Gri", D18)), -1, 0)))=1, VERI_TABANI!E26*(1-0.928)*0.00206091519919798*VERI_TABANI!G26, 0)) + ((MIN(VERI_TABANI!D27, VERI_TABANI!D27*B18)*VERI_TABANI!$B$7 + MAX(0, VERI_TABANI!D27*B18-VERI_TABANI!D27)*VERI_TABANI!$B$8) + (MIN(MAX(0, VERI_TABANI!D27-VERI_TABANI!D27*B18), VERI_TABANI!D27*C18)*VERI_TABANI!$B$7 + MAX(0, VERI_TABANI!D27*C18-MAX(0, VERI_TABANI!D27-VERI_TABANI!D27*B18))*VERI_TABANI!$B$8) + IF(ABS(IF(ISNUMBER(SEARCH("Var", D18)), 1, IF(ISNUMBER(SEARCH("Gri", D18)), -1, 0)))=1, VERI_TABANI!E27*(1-0.928)*VERI_TABANI!$B$9, 0) + (VERI_TABANI!D27*B18*(VERI_TABANI!$B$13-VERI_TABANI!$B$14)*VERI_TABANI!G27) + (VERI_TABANI!D27*C18*(VERI_TABANI!$B$13-VERI_TABANI!$B$15)*VERI_TABANI!G27) + IF(ABS(IF(ISNUMBER(SEARCH("Var", D18)), 1, IF(ISNUMBER(SEARCH("Gri", D18)), -1, 0)))=1, VERI_TABANI!E27*(1-0.928)*0.00206091519919798*VERI_TABANI!G27, 0)) + ((MIN(VERI_TABANI!D28, VERI_TABANI!D28*B18)*VERI_TABANI!$B$7 + MAX(0, VERI_TABANI!D28*B18-VERI_TABANI!D28)*VERI_TABANI!$B$8) + (MIN(MAX(0, VERI_TABANI!D28-VERI_TABANI!D28*B18), VERI_TABANI!D28*C18)*VERI_TABANI!$B$7 + MAX(0, VERI_TABANI!D28*C18-MAX(0, VERI_TABANI!D28-VERI_TABANI!D28*B18))*VERI_TABANI!$B$8) + IF(ABS(IF(ISNUMBER(SEARCH("Var", D18)), 1, IF(ISNUMBER(SEARCH("Gri", D18)), -1, 0)))=1, VERI_TABANI!E28*(1-0.928)*VERI_TABANI!$B$9, 0) + (VERI_TABANI!D28*B18*(VERI_TABANI!$B$13-VERI_TABANI!$B$14)*VERI_TABANI!G28) + (VERI_TABANI!D28*C18*(VERI_TABANI!$B$13-VERI_TABANI!$B$15)*VERI_TABANI!G28) + IF(ABS(IF(ISNUMBER(SEARCH("Var", D18)), 1, IF(ISNUMBER(SEARCH("Gri", D18)), -1, 0)))=1, VERI_TABANI!E28*(1-0.928)*0.00206091519919798*VERI_TABANI!G28, 0))) | H18: =(((VERI_TABANI!D23*B18*(VERI_TABANI!$B$13-VERI_TABANI!$B$14)) + (VERI_TABANI!D23*C18*(VERI_TABANI!$B$13-VERI_TABANI!$B$15)) + IF(ISNUMBER(SEARCH("Var", D18)), VERI_TABANI!F23*(0.00202-VERI_TABANI!$B$16), IF(ISNUMBER(SEARCH("Gri", D18)), VERI_TABANI!F23*(0.00202-VERI_TABANI!$B$17), 0))) + ((VERI_TABANI!D24*B18*(VERI_TABANI!$B$13-VERI_TABANI!$B$14)) + (VERI_TABANI!D24*C18*(VERI_TABANI!$B$13-VERI_TABANI!$B$15)) + IF(ISNUMBER(SEARCH("Var", D18)), VERI_TABANI!F24*(0.00202-VERI_TABANI!$B$16), IF(ISNUMBER(SEARCH("Gri", D18)), VERI_TABANI!F24*(0.00202-VERI_TABANI!$B$17), 0))) + ((VERI_TABANI!D25*B18*(VERI_TABANI!$B$13-VERI_TABANI!$B$14)) + (VERI_TABANI!D25*C18*(VERI_TABANI!$B$13-VERI_TABANI!$B$15)) + IF(ISNUMBER(SEARCH("Var", D18)), VERI_TABANI!F25*(0.00202-VERI_TABANI!$B$16), IF(ISNUMBER(SEARCH("Gri", D18)), VERI_TABANI!F25*(0.00202-VERI_TABANI!$B$17), 0))) + ((VERI_TABANI!D26*B18*(VERI_TABANI!$B$13-VERI_TABANI!$B$14)) + (VERI_TABANI!D26*C18*(VERI_TABANI!$B$13-VERI_TABANI!$B$15)) + IF(ISNUMBER(SEARCH("Var", D18)), VERI_TABANI!F26*(0.00202-VERI_TABANI!$B$16), IF(ISNUMBER(SEARCH("Gri", D18)), VERI_TABANI!F26*(0.00202-VERI_TABANI!$B$17), 0))) + ((VERI_TABANI!D27*B18*(VERI_TABANI!$B$13-VERI_TABANI!$B$14)) + (VERI_TABANI!D27*C18*(VERI_TABANI!$B$13-VERI_TABANI!$B$15)) + IF(ISNUMBER(SEARCH("Var", D18)), VERI_TABANI!F27*(0.00202-VERI_TABANI!$B$16), IF(ISNUMBER(SEARCH("Gri", D18)), VERI_TABANI!F27*(0.00202-VERI_TABANI!$B$17), 0))) + ((VERI_TABANI!D28*B18*(VERI_TABANI!$B$13-VERI_TABANI!$B$14)) + (VERI_TABANI!D28*C18*(VERI_TABANI!$B$13-VERI_TABANI!$B$15)) + IF(ISNUMBER(SEARCH("Var", D18)), VERI_TABANI!F28*(0.00202-VERI_TABANI!$B$16), IF(ISNUMBER(SEARCH("Gri", D18)), VERI_TABANI!F28*(0.00202-VERI_TABANI!$B$17), 0)))) | I18: =IFERROR(((VERI_TABANI!$D$29*B18*VERI_TABANI!$B$14 + VERI_TABANI!$D$29*C18*VERI_TABANI!$B$15 + IF(ISNUMBER(SEARCH("Var", D18)), VERI_TABANI!$F$29*VERI_TABANI!$B$16, 0))) / (((VERI_TABANI!$D$29*B18 + VERI_TABANI!$D$29*C18)*VERI_TABANI!$B$13 + IF(ISNUMBER(SEARCH("Var", D18)), VERI_TABANI!$E$29*(1-0.928)*VERI_TABANI!$B$18, 0))), 0) | J18: =IFERROR(F18/(G18/29), 0) | K18: =IF(F18>0, H18/F18, 0) | L18: =IF(F18>0, I18, 1000000000) | M18: =ABS((B18+C18)-1) | N18: =IF(F18>0, (G18/29)/F18, 0) | O18: =IF(AND((B18+C18)>=1, ISNUMBER(SEARCH("Var", D18))), F18, 1000000000) | P18: =IF(F18>0, SQRT((F18/MAX(F$5:F$886))^2 + (1 - H18/MAX(H$5:H$886))^2 + (J18/MAX(J$5:J$886))^2), 1000000000) | Q18: =IF(AND(ABS(B18-0.5)<0.01, ABS(C18-0.5)<0.01, ISNUMBER(SEARCH("Var", D18))), 1, 0) | R18: =IF(F18>0, J18, 1000000000) | S18: =IF(AND(F18<=DASHBOARD!$B$11, H18>=DASHBOARD!$B$13), G18, -1000000000000) | T18: =IF(AND(F18<=DASHBOARD!$B$11, H18>=DASHBOARD!$B$13), R18, 1000000000000) | U18: =IF(AND(F18<=DASHBOARD!$B$11, H18>=DASHBOARD!$B$13), N18, -1000000000000) | V18: =IF(AND(F18<=DASHBOARD!$B$11, H18>=DASHBOARD!$B$13), H18, -1000000000000) | W18: =IF(AND(F18<=DASHBOARD!$B$11, H18>=DASHBOARD!$B$13), K18, -1000000000000) | X18: =IF(AND(F18<=DASHBOARD!$B$11, H18>=DASHBOARD!$B$13), M18, 1000000000000) | Y18: =IF(AND(F18<=DASHBOARD!$B$10, H18>=DASHBOARD!$B$11), L18, 1000000000000) | Z18: =IF(AND(F18<=DASHBOARD!$B$10, H18>=DASHBOARD!$B$11), O18, 1000000000000) | AA18: =IF(AND(F18<=DASHBOARD!$B$10, H18>=DASHBOARD!$B$11), P18, 1000000000000) | AB18: =IF(AND(F18<=DASHBOARD!$B$10, H18>=DASHBOARD!$B$11), Q18, -1000000000000)
A19: 15 | B19: 0 | C19: 0.7 | D19: Yok (%0) | E19: =IF((B19+C19)<=1, "Tam Mahsuplaşma (≤%100)", "Kısmi Satış (>%100)") | F19: =((VERI_TABANI!$D$29*B19/VERI_TABANI!$B$29)/VERI_TABANI!$B$3)*VERI_TABANI!$B$5 + ((VERI_TABANI!$D$29*C19/VERI_TABANI!$B$29)/VERI_TABANI!$B$4)*VERI_TABANI!$B$6 + IF(ISNUMBER(SEARCH("Var", D19)), (VERI_TABANI!$F$29/VERI_TABANI!$B$29)*(VERI_TABANI!$B$10+VERI_TABANI!$B$12), 0) | G19: =(((MIN(VERI_TABANI!D23, VERI_TABANI!D23*B19)*VERI_TABANI!$B$7 + MAX(0, VERI_TABANI!D23*B19-VERI_TABANI!D23)*VERI_TABANI!$B$8) + (MIN(MAX(0, VERI_TABANI!D23-VERI_TABANI!D23*B19), VERI_TABANI!D23*C19)*VERI_TABANI!$B$7 + MAX(0, VERI_TABANI!D23*C19-MAX(0, VERI_TABANI!D23-VERI_TABANI!D23*B19))*VERI_TABANI!$B$8) + IF(ABS(IF(ISNUMBER(SEARCH("Var", D19)), 1, IF(ISNUMBER(SEARCH("Gri", D19)), -1, 0)))=1, VERI_TABANI!E23*(1-0.928)*VERI_TABANI!$B$9, 0) + (VERI_TABANI!D23*B19*(VERI_TABANI!$B$13-VERI_TABANI!$B$14)*VERI_TABANI!G23) + (VERI_TABANI!D23*C19*(VERI_TABANI!$B$13-VERI_TABANI!$B$15)*VERI_TABANI!G23) + IF(ABS(IF(ISNUMBER(SEARCH("Var", D19)), 1, IF(ISNUMBER(SEARCH("Gri", D19)), -1, 0)))=1, VERI_TABANI!E23*(1-0.928)*0.00206091519919798*VERI_TABANI!G23, 0)) + ((MIN(VERI_TABANI!D24, VERI_TABANI!D24*B19)*VERI_TABANI!$B$7 + MAX(0, VERI_TABANI!D24*B19-VERI_TABANI!D24)*VERI_TABANI!$B$8) + (MIN(MAX(0, VERI_TABANI!D24-VERI_TABANI!D24*B19), VERI_TABANI!D24*C19)*VERI_TABANI!$B$7 + MAX(0, VERI_TABANI!D24*C19-MAX(0, VERI_TABANI!D24-VERI_TABANI!D24*B19))*VERI_TABANI!$B$8) + IF(ABS(IF(ISNUMBER(SEARCH("Var", D19)), 1, IF(ISNUMBER(SEARCH("Gri", D19)), -1, 0)))=1, VERI_TABANI!E24*(1-0.928)*VERI_TABANI!$B$9, 0) + (VERI_TABANI!D24*B19*(VERI_TABANI!$B$13-VERI_TABANI!$B$14)*VERI_TABANI!G24) + (VERI_TABANI!D24*C19*(VERI_TABANI!$B$13-VERI_TABANI!$B$15)*VERI_TABANI!G24) + IF(ABS(IF(ISNUMBER(SEARCH("Var", D19)), 1, IF(ISNUMBER(SEARCH("Gri", D19)), -1, 0)))=1, VERI_TABANI!E24*(1-0.928)*0.00206091519919798*VERI_TABANI!G24, 0)) + ((MIN(VERI_TABANI!D25, VERI_TABANI!D25*B19)*VERI_TABANI!$B$7 + MAX(0, VERI_TABANI!D25*B19-VERI_TABANI!D25)*VERI_TABANI!$B$8) + (MIN(MAX(0, VERI_TABANI!D25-VERI_TABANI!D25*B19), VERI_TABANI!D25*C19)*VERI_TABANI!$B$7 + MAX(0, VERI_TABANI!D25*C19-MAX(0, VERI_TABANI!D25-VERI_TABANI!D25*B19))*VERI_TABANI!$B$8) + IF(ABS(IF(ISNUMBER(SEARCH("Var", D19)), 1, IF(ISNUMBER(SEARCH("Gri", D19)), -1, 0)))=1, VERI_TABANI!E25*(1-0.928)*VERI_TABANI!$B$9, 0) + (VERI_TABANI!D25*B19*(VERI_TABANI!$B$13-VERI_TABANI!$B$14)*VERI_TABANI!G25) + (VERI_TABANI!D25*C19*(VERI_TABANI!$B$13-VERI_TABANI!$B$15)*VERI_TABANI!G25) + IF(ABS(IF(ISNUMBER(SEARCH("Var", D19)), 1, IF(ISNUMBER(SEARCH("Gri", D19)), -1, 0)))=1, VERI_TABANI!E25*(1-0.928)*0.00206091519919798*VERI_TABANI!G25, 0)) + ((MIN(VERI_TABANI!D26, VERI_TABANI!D26*B19)*VERI_TABANI!$B$7 + MAX(0, VERI_TABANI!D26*B19-VERI_TABANI!D26)*VERI_TABANI!$B$8) + (MIN(MAX(0, VERI_TABANI!D26-VERI_TABANI!D26*B19), VERI_TABANI!D26*C19)*VERI_TABANI!$B$7 + MAX(0, VERI_TABANI!D26*C19-MAX(0, VERI_TABANI!D26-VERI_TABANI!D26*B19))*VERI_TABANI!$B$8) + IF(ABS(IF(ISNUMBER(SEARCH("Var", D19)), 1, IF(ISNUMBER(SEARCH("Gri", D19)), -1, 0)))=1, VERI_TABANI!E26*(1-0.928)*VERI_TABANI!$B$9, 0) + (VERI_TABANI!D26*B19*(VERI_TABANI!$B$13-VERI_TABANI!$B$14)*VERI_TABANI!G26) + (VERI_TABANI!D26*C19*(VERI_TABANI!$B$13-VERI_TABANI!$B$15)*VERI_TABANI!G26) + IF(ABS(IF(ISNUMBER(SEARCH("Var", D19)), 1, IF(ISNUMBER(SEARCH("Gri", D19)), -1, 0)))=1, VERI_TABANI!E26*(1-0.928)*0.00206091519919798*VERI_TABANI!G26, 0)) + ((MIN(VERI_TABANI!D27, VERI_TABANI!D27*B19)*VERI_TABANI!$B$7 + MAX(0, VERI_TABANI!D27*B19-VERI_TABANI!D27)*VERI_TABANI!$B$8) + (MIN(MAX(0, VERI_TABANI!D27-VERI_TABANI!D27*B19), VERI_TABANI!D27*C19)*VERI_TABANI!$B$7 + MAX(0, VERI_TABANI!D27*C19-MAX(0, VERI_TABANI!D27-VERI_TABANI!D27*B19))*VERI_TABANI!$B$8) + IF(ABS(IF(ISNUMBER(SEARCH("Var", D19)), 1, IF(ISNUMBER(SEARCH("Gri", D19)), -1, 0)))=1, VERI_TABANI!E27*(1-0.928)*VERI_TABANI!$B$9, 0) + (VERI_TABANI!D27*B19*(VERI_TABANI!$B$13-VERI_TABANI!$B$14)*VERI_TABANI!G27) + (VERI_TABANI!D27*C19*(VERI_TABANI!$B$13-VERI_TABANI!$B$15)*VERI_TABANI!G27) + IF(ABS(IF(ISNUMBER(SEARCH("Var", D19)), 1, IF(ISNUMBER(SEARCH("Gri", D19)), -1, 0)))=1, VERI_TABANI!E27*(1-0.928)*0.00206091519919798*VERI_TABANI!G27, 0)) + ((MIN(VERI_TABANI!D28, VERI_TABANI!D28*B19)*VERI_TABANI!$B$7 + MAX(0, VERI_TABANI!D28*B19-VERI_TABANI!D28)*VERI_TABANI!$B$8) + (MIN(MAX(0, VERI_TABANI!D28-VERI_TABANI!D28*B19), VERI_TABANI!D28*C19)*VERI_TABANI!$B$7 + MAX(0, VERI_TABANI!D28*C19-MAX(0, VERI_TABANI!D28-VERI_TABANI!D28*B19))*VERI_TABANI!$B$8) + IF(ABS(IF(ISNUMBER(SEARCH("Var", D19)), 1, IF(ISNUMBER(SEARCH("Gri", D19)), -1, 0)))=1, VERI_TABANI!E28*(1-0.928)*VERI_TABANI!$B$9, 0) + (VERI_TABANI!D28*B19*(VERI_TABANI!$B$13-VERI_TABANI!$B$14)*VERI_TABANI!G28) + (VERI_TABANI!D28*C19*(VERI_TABANI!$B$13-VERI_TABANI!$B$15)*VERI_TABANI!G28) + IF(ABS(IF(ISNUMBER(SEARCH("Var", D19)), 1, IF(ISNUMBER(SEARCH("Gri", D19)), -1, 0)))=1, VERI_TABANI!E28*(1-0.928)*0.00206091519919798*VERI_TABANI!G28, 0))) | H19: =(((VERI_TABANI!D23*B19*(VERI_TABANI!$B$13-VERI_TABANI!$B$14)) + (VERI_TABANI!D23*C19*(VERI_TABANI!$B$13-VERI_TABANI!$B$15)) + IF(ISNUMBER(SEARCH("Var", D19)), VERI_TABANI!F23*(0.00202-VERI_TABANI!$B$16), IF(ISNUMBER(SEARCH("Gri", D19)), VERI_TABANI!F23*(0.00202-VERI_TABANI!$B$17), 0))) + ((VERI_TABANI!D24*B19*(VERI_TABANI!$B$13-VERI_TABANI!$B$14)) + (VERI_TABANI!D24*C19*(VERI_TABANI!$B$13-VERI_TABANI!$B$15)) + IF(ISNUMBER(SEARCH("Var", D19)), VERI_TABANI!F24*(0.00202-VERI_TABANI!$B$16), IF(ISNUMBER(SEARCH("Gri", D19)), VERI_TABANI!F24*(0.00202-VERI_TABANI!$B$17), 0))) + ((VERI_TABANI!D25*B19*(VERI_TABANI!$B$13-VERI_TABANI!$B$14)) + (VERI_TABANI!D25*C19*(VERI_TABANI!$B$13-VERI_TABANI!$B$15)) + IF(ISNUMBER(SEARCH("Var", D19)), VERI_TABANI!F25*(0.00202-VERI_TABANI!$B$16), IF(ISNUMBER(SEARCH("Gri", D19)), VERI_TABANI!F25*(0.00202-VERI_TABANI!$B$17), 0))) + ((VERI_TABANI!D26*B19*(VERI_TABANI!$B$13-VERI_TABANI!$B$14)) + (VERI_TABANI!D26*C19*(VERI_TABANI!$B$13-VERI_TABANI!$B$15)) + IF(ISNUMBER(SEARCH("Var", D19)), VERI_TABANI!F26*(0.00202-VERI_TABANI!$B$16), IF(ISNUMBER(SEARCH("Gri", D19)), VERI_TABANI!F26*(0.00202-VERI_TABANI!$B$17), 0))) + ((VERI_TABANI!D27*B19*(VERI_TABANI!$B$13-VERI_TABANI!$B$14)) + (VERI_TABANI!D27*C19*(VERI_TABANI!$B$13-VERI_TABANI!$B$15)) + IF(ISNUMBER(SEARCH("Var", D19)), VERI_TABANI!F27*(0.00202-VERI_TABANI!$B$16), IF(ISNUMBER(SEARCH("Gri", D19)), VERI_TABANI!F27*(0.00202-VERI_TABANI!$B$17), 0))) + ((VERI_TABANI!D28*B19*(VERI_TABANI!$B$13-VERI_TABANI!$B$14)) + (VERI_TABANI!D28*C19*(VERI_TABANI!$B$13-VERI_TABANI!$B$15)) + IF(ISNUMBER(SEARCH("Var", D19)), VERI_TABANI!F28*(0.00202-VERI_TABANI!$B$16), IF(ISNUMBER(SEARCH("Gri", D19)), VERI_TABANI!F28*(0.00202-VERI_TABANI!$B$17), 0)))) | I19: =IFERROR(((VERI_TABANI!$D$29*B19*VERI_TABANI!$B$14 + VERI_TABANI!$D$29*C19*VERI_TABANI!$B$15 + IF(ISNUMBER(SEARCH("Var", D19)), VERI_TABANI!$F$29*VERI_TABANI!$B$16, 0))) / (((VERI_TABANI!$D$29*B19 + VERI_TABANI!$D$29*C19)*VERI_TABANI!$B$13 + IF(ISNUMBER(SEARCH("Var", D19)), VERI_TABANI!$E$29*(1-0.928)*VERI_TABANI!$B$18, 0))), 0) | J19: =IFERROR(F19/(G19/29), 0) | K19: =IF(F19>0, H19/F19, 0) | L19: =IF(F19>0, I19, 1000000000) | M19: =ABS((B19+C19)-1) | N19: =IF(F19>0, (G19/29)/F19, 0) | O19: =IF(AND((B19+C19)>=1, ISNUMBER(SEARCH("Var", D19))), F19, 1000000000) | P19: =IF(F19>0, SQRT((F19/MAX(F$5:F$886))^2 + (1 - H19/MAX(H$5:H$886))^2 + (J19/MAX(J$5:J$886))^2), 1000000000) | Q19: =IF(AND(ABS(B19-0.5)<0.01, ABS(C19-0.5)<0.01, ISNUMBER(SEARCH("Var", D19))), 1, 0) | R19: =IF(F19>0, J19, 1000000000) | S19: =IF(AND(F19<=DASHBOARD!$B$11, H19>=DASHBOARD!$B$13), G19, -1000000000000) | T19: =IF(AND(F19<=DASHBOARD!$B$11, H19>=DASHBOARD!$B$13), R19, 1000000000000) | U19: =IF(AND(F19<=DASHBOARD!$B$11, H19>=DASHBOARD!$B$13), N19, -1000000000000) | V19: =IF(AND(F19<=DASHBOARD!$B$11, H19>=DASHBOARD!$B$13), H19, -1000000000000) | W19: =IF(AND(F19<=DASHBOARD!$B$11, H19>=DASHBOARD!$B$13), K19, -1000000000000) | X19: =IF(AND(F19<=DASHBOARD!$B$11, H19>=DASHBOARD!$B$13), M19, 1000000000000) | Y19: =IF(AND(F19<=DASHBOARD!$B$10, H19>=DASHBOARD!$B$11), L19, 1000000000000) | Z19: =IF(AND(F19<=DASHBOARD!$B$10, H19>=DASHBOARD!$B$11), O19, 1000000000000) | AA19: =IF(AND(F19<=DASHBOARD!$B$10, H19>=DASHBOARD!$B$11), P19, 1000000000000) | AB19: =IF(AND(F19<=DASHBOARD!$B$10, H19>=DASHBOARD!$B$11), Q19, -1000000000000)
A20: 16 | B20: 0 | C20: 0.7 | D20: Var (%20) | E20: =IF((B20+C20)<=1, "Tam Mahsuplaşma (≤%100)", "Kısmi Satış (>%100)") | F20: =((VERI_TABANI!$D$29*B20/VERI_TABANI!$B$29)/VERI_TABANI!$B$3)*VERI_TABANI!$B$5 + ((VERI_TABANI!$D$29*C20/VERI_TABANI!$B$29)/VERI_TABANI!$B$4)*VERI_TABANI!$B$6 + IF(ISNUMBER(SEARCH("Var", D20)), (VERI_TABANI!$F$29/VERI_TABANI!$B$29)*(VERI_TABANI!$B$10+VERI_TABANI!$B$12), 0) | G20: =(((MIN(VERI_TABANI!D23, VERI_TABANI!D23*B20)*VERI_TABANI!$B$7 + MAX(0, VERI_TABANI!D23*B20-VERI_TABANI!D23)*VERI_TABANI!$B$8) + (MIN(MAX(0, VERI_TABANI!D23-VERI_TABANI!D23*B20), VERI_TABANI!D23*C20)*VERI_TABANI!$B$7 + MAX(0, VERI_TABANI!D23*C20-MAX(0, VERI_TABANI!D23-VERI_TABANI!D23*B20))*VERI_TABANI!$B$8) + IF(ABS(IF(ISNUMBER(SEARCH("Var", D20)), 1, IF(ISNUMBER(SEARCH("Gri", D20)), -1, 0)))=1, VERI_TABANI!E23*(1-0.928)*VERI_TABANI!$B$9, 0) + (VERI_TABANI!D23*B20*(VERI_TABANI!$B$13-VERI_TABANI!$B$14)*VERI_TABANI!G23) + (VERI_TABANI!D23*C20*(VERI_TABANI!$B$13-VERI_TABANI!$B$15)*VERI_TABANI!G23) + IF(ABS(IF(ISNUMBER(SEARCH("Var", D20)), 1, IF(ISNUMBER(SEARCH("Gri", D20)), -1, 0)))=1, VERI_TABANI!E23*(1-0.928)*0.00206091519919798*VERI_TABANI!G23, 0)) + ((MIN(VERI_TABANI!D24, VERI_TABANI!D24*B20)*VERI_TABANI!$B$7 + MAX(0, VERI_TABANI!D24*B20-VERI_TABANI!D24)*VERI_TABANI!$B$8) + (MIN(MAX(0, VERI_TABANI!D24-VERI_TABANI!D24*B20), VERI_TABANI!D24*C20)*VERI_TABANI!$B$7 + MAX(0, VERI_TABANI!D24*C20-MAX(0, VERI_TABANI!D24-VERI_TABANI!D24*B20))*VERI_TABANI!$B$8) + IF(ABS(IF(ISNUMBER(SEARCH("Var", D20)), 1, IF(ISNUMBER(SEARCH("Gri", D20)), -1, 0)))=1, VERI_TABANI!E24*(1-0.928)*VERI_TABANI!$B$9, 0) + (VERI_TABANI!D24*B20*(VERI_TABANI!$B$13-VERI_TABANI!$B$14)*VERI_TABANI!G24) + (VERI_TABANI!D24*C20*(VERI_TABANI!$B$13-VERI_TABANI!$B$15)*VERI_TABANI!G24) + IF(ABS(IF(ISNUMBER(SEARCH("Var", D20)), 1, IF(ISNUMBER(SEARCH("Gri", D20)), -1, 0)))=1, VERI_TABANI!E24*(1-0.928)*0.00206091519919798*VERI_TABANI!G24, 0)) + ((MIN(VERI_TABANI!D25, VERI_TABANI!D25*B20)*VERI_TABANI!$B$7 + MAX(0, VERI_TABANI!D25*B20-VERI_TABANI!D25)*VERI_TABANI!$B$8) + (MIN(MAX(0, VERI_TABANI!D25-VERI_TABANI!D25*B20), VERI_TABANI!D25*C20)*VERI_TABANI!$B$7 + MAX(0, VERI_TABANI!D25*C20-MAX(0, VERI_TABANI!D25-VERI_TABANI!D25*B20))*VERI_TABANI!$B$8) + IF(ABS(IF(ISNUMBER(SEARCH("Var", D20)), 1, IF(ISNUMBER(SEARCH("Gri", D20)), -1, 0)))=1, VERI_TABANI!E25*(1-0.928)*VERI_TABANI!$B$9, 0) + (VERI_TABANI!D25*B20*(VERI_TABANI!$B$13-VERI_TABANI!$B$14)*VERI_TABANI!G25) + (VERI_TABANI!D25*C20*(VERI_TABANI!$B$13-VERI_TABANI!$B$15)*VERI_TABANI!G25) + IF(ABS(IF(ISNUMBER(SEARCH("Var", D20)), 1, IF(ISNUMBER(SEARCH("Gri", D20)), -1, 0)))=1, VERI_TABANI!E25*(1-0.928)*0.00206091519919798*VERI_TABANI!G25, 0)) + ((MIN(VERI_TABANI!D26, VERI_TABANI!D26*B20)*VERI_TABANI!$B$7 + MAX(0, VERI_TABANI!D26*B20-VERI_TABANI!D26)*VERI_TABANI!$B$8) + (MIN(MAX(0, VERI_TABANI!D26-VERI_TABANI!D26*B20), VERI_TABANI!D26*C20)*VERI_TABANI!$B$7 + MAX(0, VERI_TABANI!D26*C20-MAX(0, VERI_TABANI!D26-VERI_TABANI!D26*B20))*VERI_TABANI!$B$8) + IF(ABS(IF(ISNUMBER(SEARCH("Var", D20)), 1, IF(ISNUMBER(SEARCH("Gri", D20)), -1, 0)))=1, VERI_TABANI!E26*(1-0.928)*VERI_TABANI!$B$9, 0) + (VERI_TABANI!D26*B20*(VERI_TABANI!$B$13-VERI_TABANI!$B$14)*VERI_TABANI!G26) + (VERI_TABANI!D26*C20*(VERI_TABANI!$B$13-VERI_TABANI!$B$15)*VERI_TABANI!G26) + IF(ABS(IF(ISNUMBER(SEARCH("Var", D20)), 1, IF(ISNUMBER(SEARCH("Gri", D20)), -1, 0)))=1, VERI_TABANI!E26*(1-0.928)*0.00206091519919798*VERI_TABANI!G26, 0)) + ((MIN(VERI_TABANI!D27, VERI_TABANI!D27*B20)*VERI_TABANI!$B$7 + MAX(0, VERI_TABANI!D27*B20-VERI_TABANI!D27)*VERI_TABANI!$B$8) + (MIN(MAX(0, VERI_TABANI!D27-VERI_TABANI!D27*B20), VERI_TABANI!D27*C20)*VERI_TABANI!$B$7 + MAX(0, VERI_TABANI!D27*C20-MAX(0, VERI_TABANI!D27-VERI_TABANI!D27*B20))*VERI_TABANI!$B$8) + IF(ABS(IF(ISNUMBER(SEARCH("Var", D20)), 1, IF(ISNUMBER(SEARCH("Gri", D20)), -1, 0)))=1, VERI_TABANI!E27*(1-0.928)*VERI_TABANI!$B$9, 0) + (VERI_TABANI!D27*B20*(VERI_TABANI!$B$13-VERI_TABANI!$B$14)*VERI_TABANI!G27) + (VERI_TABANI!D27*C20*(VERI_TABANI!$B$13-VERI_TABANI!$B$15)*VERI_TABANI!G27) + IF(ABS(IF(ISNUMBER(SEARCH("Var", D20)), 1, IF(ISNUMBER(SEARCH("Gri", D20)), -1, 0)))=1, VERI_TABANI!E27*(1-0.928)*0.00206091519919798*VERI_TABANI!G27, 0)) + ((MIN(VERI_TABANI!D28, VERI_TABANI!D28*B20)*VERI_TABANI!$B$7 + MAX(0, VERI_TABANI!D28*B20-VERI_TABANI!D28)*VERI_TABANI!$B$8) + (MIN(MAX(0, VERI_TABANI!D28-VERI_TABANI!D28*B20), VERI_TABANI!D28*C20)*VERI_TABANI!$B$7 + MAX(0, VERI_TABANI!D28*C20-MAX(0, VERI_TABANI!D28-VERI_TABANI!D28*B20))*VERI_TABANI!$B$8) + IF(ABS(IF(ISNUMBER(SEARCH("Var", D20)), 1, IF(ISNUMBER(SEARCH("Gri", D20)), -1, 0)))=1, VERI_TABANI!E28*(1-0.928)*VERI_TABANI!$B$9, 0) + (VERI_TABANI!D28*B20*(VERI_TABANI!$B$13-VERI_TABANI!$B$14)*VERI_TABANI!G28) + (VERI_TABANI!D28*C20*(VERI_TABANI!$B$13-VERI_TABANI!$B$15)*VERI_TABANI!G28) + IF(ABS(IF(ISNUMBER(SEARCH("Var", D20)), 1, IF(ISNUMBER(SEARCH("Gri", D20)), -1, 0)))=1, VERI_TABANI!E28*(1-0.928)*0.00206091519919798*VERI_TABANI!G28, 0))) | H20: =(((VERI_TABANI!D23*B20*(VERI_TABANI!$B$13-VERI_TABANI!$B$14)) + (VERI_TABANI!D23*C20*(VERI_TABANI!$B$13-VERI_TABANI!$B$15)) + IF(ISNUMBER(SEARCH("Var", D20)), VERI_TABANI!F23*(0.00202-VERI_TABANI!$B$16), IF(ISNUMBER(SEARCH("Gri", D20)), VERI_TABANI!F23*(0.00202-VERI_TABANI!$B$17), 0))) + ((VERI_TABANI!D24*B20*(VERI_TABANI!$B$13-VERI_TABANI!$B$14)) + (VERI_TABANI!D24*C20*(VERI_TABANI!$B$13-VERI_TABANI!$B$15)) + IF(ISNUMBER(SEARCH("Var", D20)), VERI_TABANI!F24*(0.00202-VERI_TABANI!$B$16), IF(ISNUMBER(SEARCH("Gri", D20)), VERI_TABANI!F24*(0.00202-VERI_TABANI!$B$17), 0))) + ((VERI_TABANI!D25*B20*(VERI_TABANI!$B$13-VERI_TABANI!$B$14)) + (VERI_TABANI!D25*C20*(VERI_TABANI!$B$13-VERI_TABANI!$B$15)) + IF(ISNUMBER(SEARCH("Var", D20)), VERI_TABANI!F25*(0.00202-VERI_TABANI!$B$16), IF(ISNUMBER(SEARCH("Gri", D20)), VERI_TABANI!F25*(0.00202-VERI_TABANI!$B$17), 0))) + ((VERI_TABANI!D26*B20*(VERI_TABANI!$B$13-VERI_TABANI!$B$14)) + (VERI_TABANI!D26*C20*(VERI_TABANI!$B$13-VERI_TABANI!$B$15)) + IF(ISNUMBER(SEARCH("Var", D20)), VERI_TABANI!F26*(0.00202-VERI_TABANI!$B$16), IF(ISNUMBER(SEARCH("Gri", D20)), VERI_TABANI!F26*(0.00202-VERI_TABANI!$B$17), 0))) + ((VERI_TABANI!D27*B20*(VERI_TABANI!$B$13-VERI_TABANI!$B$14)) + (VERI_TABANI!D27*C20*(VERI_TABANI!$B$13-VERI_TABANI!$B$15)) + IF(ISNUMBER(SEARCH("Var", D20)), VERI_TABANI!F27*(0.00202-VERI_TABANI!$B$16), IF(ISNUMBER(SEARCH("Gri", D20)), VERI_TABANI!F27*(0.00202-VERI_TABANI!$B$17), 0))) + ((VERI_TABANI!D28*B20*(VERI_TABANI!$B$13-VERI_TABANI!$B$14)) + (VERI_TABANI!D28*C20*(VERI_TABANI!$B$13-VERI_TABANI!$B$15)) + IF(ISNUMBER(SEARCH("Var", D20)), VERI_TABANI!F28*(0.00202-VERI_TABANI!$B$16), IF(ISNUMBER(SEARCH("Gri", D20)), VERI_TABANI!F28*(0.00202-VERI_TABANI!$B$17), 0)))) | I20: =IFERROR(((VERI_TABANI!$D$29*B20*VERI_TABANI!$B$14 + VERI_TABANI!$D$29*C20*VERI_TABANI!$B$15 + IF(ISNUMBER(SEARCH("Var", D20)), VERI_TABANI!$F$29*VERI_TABANI!$B$16, 0))) / (((VERI_TABANI!$D$29*B20 + VERI_TABANI!$D$29*C20)*VERI_TABANI!$B$13 + IF(ISNUMBER(SEARCH("Var", D20)), VERI_TABANI!$E$29*(1-0.928)*VERI_TABANI!$B$18, 0))), 0) | J20: =IFERROR(F20/(G20/29), 0) | K20: =IF(F20>0, H20/F20, 0) | L20: =IF(F20>0, I20, 1000000000) | M20: =ABS((B20+C20)-1) | N20: =IF(F20>0, (G20/29)/F20, 0) | O20: =IF(AND((B20+C20)>=1, ISNUMBER(SEARCH("Var", D20))), F20, 1000000000) | P20: =IF(F20>0, SQRT((F20/MAX(F$5:F$886))^2 + (1 - H20/MAX(H$5:H$886))^2 + (J20/MAX(J$5:J$886))^2), 1000000000) | Q20: =IF(AND(ABS(B20-0.5)<0.01, ABS(C20-0.5)<0.01, ISNUMBER(SEARCH("Var", D20))), 1, 0) | R20: =IF(F20>0, J20, 1000000000) | S20: =IF(AND(F20<=DASHBOARD!$B$11, H20>=DASHBOARD!$B$13), G20, -1000000000000) | T20: =IF(AND(F20<=DASHBOARD!$B$11, H20>=DASHBOARD!$B$13), R20, 1000000000000) | U20: =IF(AND(F20<=DASHBOARD!$B$11, H20>=DASHBOARD!$B$13), N20, -1000000000000) | V20: =IF(AND(F20<=DASHBOARD!$B$11, H20>=DASHBOARD!$B$13), H20, -1000000000000) | W20: =IF(AND(F20<=DASHBOARD!$B$11, H20>=DASHBOARD!$B$13), K20, -1000000000000) | X20: =IF(AND(F20<=DASHBOARD!$B$11, H20>=DASHBOARD!$B$13), M20, 1000000000000) | Y20: =IF(AND(F20<=DASHBOARD!$B$10, H20>=DASHBOARD!$B$11), L20, 1000000000000) | Z20: =IF(AND(F20<=DASHBOARD!$B$10, H20>=DASHBOARD!$B$11), O20, 1000000000000) | AA20: =IF(AND(F20<=DASHBOARD!$B$10, H20>=DASHBOARD!$B$11), P20, 1000000000000) | AB20: =IF(AND(F20<=DASHBOARD!$B$10, H20>=DASHBOARD!$B$11), Q20, -1000000000000)
A21: 17 | B21: 0 | C21: 0.8 | D21: Yok (%0) | E21: =IF((B21+C21)<=1, "Tam Mahsuplaşma (≤%100)", "Kısmi Satış (>%100)") | F21: =((VERI_TABANI!$D$29*B21/VERI_TABANI!$B$29)/VERI_TABANI!$B$3)*VERI_TABANI!$B$5 + ((VERI_TABANI!$D$29*C21/VERI_TABANI!$B$29)/VERI_TABANI!$B$4)*VERI_TABANI!$B$6 + IF(ISNUMBER(SEARCH("Var", D21)), (VERI_TABANI!$F$29/VERI_TABANI!$B$29)*(VERI_TABANI!$B$10+VERI_TABANI!$B$12), 0) | G21: =(((MIN(VERI_TABANI!D23, VERI_TABANI!D23*B21)*VERI_TABANI!$B$7 + MAX(0, VERI_TABANI!D23*B21-VERI_TABANI!D23)*VERI_TABANI!$B$8) + (MIN(MAX(0, VERI_TABANI!D23-VERI_TABANI!D23*B21), VERI_TABANI!D23*C21)*VERI_TABANI!$B$7 + MAX(0, VERI_TABANI!D23*C21-MAX(0, VERI_TABANI!D23-VERI_TABANI!D23*B21))*VERI_TABANI!$B$8) + IF(ABS(IF(ISNUMBER(SEARCH("Var", D21)), 1, IF(ISNUMBER(SEARCH("Gri", D21)), -1, 0)))=1, VERI_TABANI!E23*(1-0.928)*VERI_TABANI!$B$9, 0) + (VERI_TABANI!D23*B21*(VERI_TABANI!$B$13-VERI_TABANI!$B$14)*VERI_TABANI!G23) + (VERI_TABANI!D23*C21*(VERI_TABANI!$B$13-VERI_TABANI!$B$15)*VERI_TABANI!G23) + IF(ABS(IF(ISNUMBER(SEARCH("Var", D21)), 1, IF(ISNUMBER(SEARCH("Gri", D21)), -1, 0)))=1, VERI_TABANI!E23*(1-0.928)*0.00206091519919798*VERI_TABANI!G23, 0)) + ((MIN(VERI_TABANI!D24, VERI_TABANI!D24*B21)*VERI_TABANI!$B$7 + MAX(0, VERI_TABANI!D24*B21-VERI_TABANI!D24)*VERI_TABANI!$B$8) + (MIN(MAX(0, VERI_TABANI!D24-VERI_TABANI!D24*B21), VERI_TABANI!D24*C21)*VERI_TABANI!$B$7 + MAX(0, VERI_TABANI!D24*C21-MAX(0, VERI_TABANI!D24-VERI_TABANI!D24*B21))*VERI_TABANI!$B$8) + IF(ABS(IF(ISNUMBER(SEARCH("Var", D21)), 1, IF(ISNUMBER(SEARCH("Gri", D21)), -1, 0)))=1, VERI_TABANI!E24*(1-0.928)*VERI_TABANI!$B$9, 0) + (VERI_TABANI!D24*B21*(VERI_TABANI!$B$13-VERI_TABANI!$B$14)*VERI_TABANI!G24) + (VERI_TABANI!D24*C21*(VERI_TABANI!$B$13-VERI_TABANI!$B$15)*VERI_TABANI!G24) + IF(ABS(IF(ISNUMBER(SEARCH("Var", D21)), 1, IF(ISNUMBER(SEARCH("Gri", D21)), -1, 0)))=1, VERI_TABANI!E24*(1-0.928)*0.00206091519919798*VERI_TABANI!G24, 0)) + ((MIN(VERI_TABANI!D25, VERI_TABANI!D25*B21)*VERI_TABANI!$B$7 + MAX(0, VERI_TABANI!D25*B21-VERI_TABANI!D25)*VERI_TABANI!$B$8) + (MIN(MAX(0, VERI_TABANI!D25-VERI_TABANI!D25*B21), VERI_TABANI!D25*C21)*VERI_TABANI!$B$7 + MAX(0, VERI_TABANI!D25*C21-MAX(0, VERI_TABANI!D25-VERI_TABANI!D25*B21))*VERI_TABANI!$B$8) + IF(ABS(IF(ISNUMBER(SEARCH("Var", D21)), 1, IF(ISNUMBER(SEARCH("Gri", D21)), -1, 0)))=1, VERI_TABANI!E25*(1-0.928)*VERI_TABANI!$B$9, 0) + (VERI_TABANI!D25*B21*(VERI_TABANI!$B$13-VERI_TABANI!$B$14)*VERI_TABANI!G25) + (VERI_TABANI!D25*C21*(VERI_TABANI!$B$13-VERI_TABANI!$B$15)*VERI_TABANI!G25) + IF(ABS(IF(ISNUMBER(SEARCH("Var", D21)), 1, IF(ISNUMBER(SEARCH("Gri", D21)), -1, 0)))=1, VERI_TABANI!E25*(1-0.928)*0.00206091519919798*VERI_TABANI!G25, 0)) + ((MIN(VERI_TABANI!D26, VERI_TABANI!D26*B21)*VERI_TABANI!$B$7 + MAX(0, VERI_TABANI!D26*B21-VERI_TABANI!D26)*VERI_TABANI!$B$8) + (MIN(MAX(0, VERI_TABANI!D26-VERI_TABANI!D26*B21), VERI_TABANI!D26*C21)*VERI_TABANI!$B$7 + MAX(0, VERI_TABANI!D26*C21-MAX(0, VERI_TABANI!D26-VERI_TABANI!D26*B21))*VERI_TABANI!$B$8) + IF(ABS(IF(ISNUMBER(SEARCH("Var", D21)), 1, IF(ISNUMBER(SEARCH("Gri", D21)), -1, 0)))=1, VERI_TABANI!E26*(1-0.928)*VERI_TABANI!$B$9, 0) + (VERI_TABANI!D26*B21*(VERI_TABANI!$B$13-VERI_TABANI!$B$14)*VERI_TABANI!G26) + (VERI_TABANI!D26*C21*(VERI_TABANI!$B$13-VERI_TABANI!$B$15)*VERI_TABANI!G26) + IF(ABS(IF(ISNUMBER(SEARCH("Var", D21)), 1, IF(ISNUMBER(SEARCH("Gri", D21)), -1, 0)))=1, VERI_TABANI!E26*(1-0.928)*0.00206091519919798*VERI_TABANI!G26, 0)) + ((MIN(VERI_TABANI!D27, VERI_TABANI!D27*B21)*VERI_TABANI!$B$7 + MAX(0, VERI_TABANI!D27*B21-VERI_TABANI!D27)*VERI_TABANI!$B$8) + (MIN(MAX(0, VERI_TABANI!D27-VERI_TABANI!D27*B21), VERI_TABANI!D27*C21)*VERI_TABANI!$B$7 + MAX(0, VERI_TABANI!D27*C21-MAX(0, VERI_TABANI!D27-VERI_TABANI!D27*B21))*VERI_TABANI!$B$8) + IF(ABS(IF(ISNUMBER(SEARCH("Var", D21)), 1, IF(ISNUMBER(SEARCH("Gri", D21)), -1, 0)))=1, VERI_TABANI!E27*(1-0.928)*VERI_TABANI!$B$9, 0) + (VERI_TABANI!D27*B21*(VERI_TABANI!$B$13-VERI_TABANI!$B$14)*VERI_TABANI!G27) + (VERI_TABANI!D27*C21*(VERI_TABANI!$B$13-VERI_TABANI!$B$15)*VERI_TABANI!G27) + IF(ABS(IF(ISNUMBER(SEARCH("Var", D21)), 1, IF(ISNUMBER(SEARCH("Gri", D21)), -1, 0)))=1, VERI_TABANI!E27*(1-0.928)*0.00206091519919798*VERI_TABANI!G27, 0)) + ((MIN(VERI_TABANI!D28, VERI_TABANI!D28*B21)*VERI_TABANI!$B$7 + MAX(0, VERI_TABANI!D28*B21-VERI_TABANI!D28)*VERI_TABANI!$B$8) + (MIN(MAX(0, VERI_TABANI!D28-VERI_TABANI!D28*B21), VERI_TABANI!D28*C21)*VERI_TABANI!$B$7 + MAX(0, VERI_TABANI!D28*C21-MAX(0, VERI_TABANI!D28-VERI_TABANI!D28*B21))*VERI_TABANI!$B$8) + IF(ABS(IF(ISNUMBER(SEARCH("Var", D21)), 1, IF(ISNUMBER(SEARCH("Gri", D21)), -1, 0)))=1, VERI_TABANI!E28*(1-0.928)*VERI_TABANI!$B$9, 0) + (VERI_TABANI!D28*B21*(VERI_TABANI!$B$13-VERI_TABANI!$B$14)*VERI_TABANI!G28) + (VERI_TABANI!D28*C21*(VERI_TABANI!$B$13-VERI_TABANI!$B$15)*VERI_TABANI!G28) + IF(ABS(IF(ISNUMBER(SEARCH("Var", D21)), 1, IF(ISNUMBER(SEARCH("Gri", D21)), -1, 0)))=1, VERI_TABANI!E28*(1-0.928)*0.00206091519919798*VERI_TABANI!G28, 0))) | H21: =(((VERI_TABANI!D23*B21*(VERI_TABANI!$B$13-VERI_TABANI!$B$14)) + (VERI_TABANI!D23*C21*(VERI_TABANI!$B$13-VERI_TABANI!$B$15)) + IF(ISNUMBER(SEARCH("Var", D21)), VERI_TABANI!F23*(0.00202-VERI_TABANI!$B$16), IF(ISNUMBER(SEARCH("Gri", D21)), VERI_TABANI!F23*(0.00202-VERI_TABANI!$B$17), 0))) + ((VERI_TABANI!D24*B21*(VERI_TABANI!$B$13-VERI_TABANI!$B$14)) + (VERI_TABANI!D24*C21*(VERI_TABANI!$B$13-VERI_TABANI!$B$15)) + IF(ISNUMBER(SEARCH("Var", D21)), VERI_TABANI!F24*(0.00202-VERI_TABANI!$B$16), IF(ISNUMBER(SEARCH("Gri", D21)), VERI_TABANI!F24*(0.00202-VERI_TABANI!$B$17), 0))) + ((VERI_TABANI!D25*B21*(VERI_TABANI!$B$13-VERI_TABANI!$B$14)) + (VERI_TABANI!D25*C21*(VERI_TABANI!$B$13-VERI_TABANI!$B$15)) + IF(ISNUMBER(SEARCH("Var", D21)), VERI_TABANI!F25*(0.00202-VERI_TABANI!$B$16), IF(ISNUMBER(SEARCH("Gri", D21)), VERI_TABANI!F25*(0.00202-VERI_TABANI!$B$17), 0))) + ((VERI_TABANI!D26*B21*(VERI_TABANI!$B$13-VERI_TABANI!$B$14)) + (VERI_TABANI!D26*C21*(VERI_TABANI!$B$13-VERI_TABANI!$B$15)) + IF(ISNUMBER(SEARCH("Var", D21)), VERI_TABANI!F26*(0.00202-VERI_TABANI!$B$16), IF(ISNUMBER(SEARCH("Gri", D21)), VERI_TABANI!F26*(0.00202-VERI_TABANI!$B$17), 0))) + ((VERI_TABANI!D27*B21*(VERI_TABANI!$B$13-VERI_TABANI!$B$14)) + (VERI_TABANI!D27*C21*(VERI_TABANI!$B$13-VERI_TABANI!$B$15)) + IF(ISNUMBER(SEARCH("Var", D21)), VERI_TABANI!F27*(0.00202-VERI_TABANI!$B$16), IF(ISNUMBER(SEARCH("Gri", D21)), VERI_TABANI!F27*(0.00202-VERI_TABANI!$B$17), 0))) + ((VERI_TABANI!D28*B21*(VERI_TABANI!$B$13-VERI_TABANI!$B$14)) + (VERI_TABANI!D28*C21*(VERI_TABANI!$B$13-VERI_TABANI!$B$15)) + IF(ISNUMBER(SEARCH("Var", D21)), VERI_TABANI!F28*(0.00202-VERI_TABANI!$B$16), IF(ISNUMBER(SEARCH("Gri", D21)), VERI_TABANI!F28*(0.00202-VERI_TABANI!$B$17), 0)))) | I21: =IFERROR(((VERI_TABANI!$D$29*B21*VERI_TABANI!$B$14 + VERI_TABANI!$D$29*C21*VERI_TABANI!$B$15 + IF(ISNUMBER(SEARCH("Var", D21)), VERI_TABANI!$F$29*VERI_TABANI!$B$16, 0))) / (((VERI_TABANI!$D$29*B21 + VERI_TABANI!$D$29*C21)*VERI_TABANI!$B$13 + IF(ISNUMBER(SEARCH("Var", D21)), VERI_TABANI!$E$29*(1-0.928)*VERI_TABANI!$B$18, 0))), 0) | J21: =IFERROR(F21/(G21/29), 0) | K21: =IF(F21>0, H21/F21, 0) | L21: =IF(F21>0, I21, 1000000000) | M21: =ABS((B21+C21)-1) | N21: =IF(F21>0, (G21/29)/F21, 0) | O21: =IF(AND((B21+C21)>=1, ISNUMBER(SEARCH("Var", D21))), F21, 1000000000) | P21: =IF(F21>0, SQRT((F21/MAX(F$5:F$886))^2 + (1 - H21/MAX(H$5:H$886))^2 + (J21/MAX(J$5:J$886))^2), 1000000000) | Q21: =IF(AND(ABS(B21-0.5)<0.01, ABS(C21-0.5)<0.01, ISNUMBER(SEARCH("Var", D21))), 1, 0) | R21: =IF(F21>0, J21, 1000000000) | S21: =IF(AND(F21<=DASHBOARD!$B$11, H21>=DASHBOARD!$B$13), G21, -1000000000000) | T21: =IF(AND(F21<=DASHBOARD!$B$11, H21>=DASHBOARD!$B$13), R21, 1000000000000) | U21: =IF(AND(F21<=DASHBOARD!$B$11, H21>=DASHBOARD!$B$13), N21, -1000000000000) | V21: =IF(AND(F21<=DASHBOARD!$B$11, H21>=DASHBOARD!$B$13), H21, -1000000000000) | W21: =IF(AND(F21<=DASHBOARD!$B$11, H21>=DASHBOARD!$B$13), K21, -1000000000000) | X21: =IF(AND(F21<=DASHBOARD!$B$11, H21>=DASHBOARD!$B$13), M21, 1000000000000) | Y21: =IF(AND(F21<=DASHBOARD!$B$10, H21>=DASHBOARD!$B$11), L21, 1000000000000) | Z21: =IF(AND(F21<=DASHBOARD!$B$10, H21>=DASHBOARD!$B$11), O21, 1000000000000) | AA21: =IF(AND(F21<=DASHBOARD!$B$10, H21>=DASHBOARD!$B$11), P21, 1000000000000) | AB21: =IF(AND(F21<=DASHBOARD!$B$10, H21>=DASHBOARD!$B$11), Q21, -1000000000000)
A22: 18 | B22: 0 | C22: 0.8 | D22: Var (%20) | E22: =IF((B22+C22)<=1, "Tam Mahsuplaşma (≤%100)", "Kısmi Satış (>%100)") | F22: =((VERI_TABANI!$D$29*B22/VERI_TABANI!$B$29)/VERI_TABANI!$B$3)*VERI_TABANI!$B$5 + ((VERI_TABANI!$D$29*C22/VERI_TABANI!$B$29)/VERI_TABANI!$B$4)*VERI_TABANI!$B$6 + IF(ISNUMBER(SEARCH("Var", D22)), (VERI_TABANI!$F$29/VERI_TABANI!$B$29)*(VERI_TABANI!$B$10+VERI_TABANI!$B$12), 0) | G22: =(((MIN(VERI_TABANI!D23, VERI_TABANI!D23*B22)*VERI_TABANI!$B$7 + MAX(0, VERI_TABANI!D23*B22-VERI_TABANI!D23)*VERI_TABANI!$B$8) + (MIN(MAX(0, VERI_TABANI!D23-VERI_TABANI!D23*B22), VERI_TABANI!D23*C22)*VERI_TABANI!$B$7 + MAX(0, VERI_TABANI!D23*C22-MAX(0, VERI_TABANI!D23-VERI_TABANI!D23*B22))*VERI_TABANI!$B$8) + IF(ABS(IF(ISNUMBER(SEARCH("Var", D22)), 1, IF(ISNUMBER(SEARCH("Gri", D22)), -1, 0)))=1, VERI_TABANI!E23*(1-0.928)*VERI_TABANI!$B$9, 0) + (VERI_TABANI!D23*B22*(VERI_TABANI!$B$13-VERI_TABANI!$B$14)*VERI_TABANI!G23) + (VERI_TABANI!D23*C22*(VERI_TABANI!$B$13-VERI_TABANI!$B$15)*VERI_TABANI!G23) + IF(ABS(IF(ISNUMBER(SEARCH("Var", D22)), 1, IF(ISNUMBER(SEARCH("Gri", D22)), -1, 0)))=1, VERI_TABANI!E23*(1-0.928)*0.00206091519919798*VERI_TABANI!G23, 0)) + ((MIN(VERI_TABANI!D24, VERI_TABANI!D24*B22)*VERI_TABANI!$B$7 + MAX(0, VERI_TABANI!D24*B22-VERI_TABANI!D24)*VERI_TABANI!$B$8) + (MIN(MAX(0, VERI_TABANI!D24-VERI_TABANI!D24*B22), VERI_TABANI!D24*C22)*VERI_TABANI!$B$7 + MAX(0, VERI_TABANI!D24*C22-MAX(0, VERI_TABANI!D24-VERI_TABANI!D24*B22))*VERI_TABANI!$B$8) + IF(ABS(IF(ISNUMBER(SEARCH("Var", D22)), 1, IF(ISNUMBER(SEARCH("Gri", D22)), -1, 0)))=1, VERI_TABANI!E24*(1-0.928)*VERI_TABANI!$B$9, 0) + (VERI_TABANI!D24*B22*(VERI_TABANI!$B$13-VERI_TABANI!$B$14)*VERI_TABANI!G24) + (VERI_TABANI!D24*C22*(VERI_TABANI!$B$13-VERI_TABANI!$B$15)*VERI_TABANI!G24) + IF(ABS(IF(ISNUMBER(SEARCH("Var", D22)), 1, IF(ISNUMBER(SEARCH("Gri", D22)), -1, 0)))=1, VERI_TABANI!E24*(1-0.928)*0.00206091519919798*VERI_TABANI!G24, 0)) + ((MIN(VERI_TABANI!D25, VERI_TABANI!D25*B22)*VERI_TABANI!$B$7 + MAX(0, VERI_TABANI!D25*B22-VERI_TABANI!D25)*VERI_TABANI!$B$8) + (MIN(MAX(0, VERI_TABANI!D25-VERI_TABANI!D25*B22), VERI_TABANI!D25*C22)*VERI_TABANI!$B$7 + MAX(0, VERI_TABANI!D25*C22-MAX(0, VERI_TABANI!D25-VERI_TABANI!D25*B22))*VERI_TABANI!$B$8) + IF(ABS(IF(ISNUMBER(SEARCH("Var", D22)), 1, IF(ISNUMBER(SEARCH("Gri", D22)), -1, 0)))=1, VERI_TABANI!E25*(1-0.928)*VERI_TABANI!$B$9, 0) + (VERI_TABANI!D25*B22*(VERI_TABANI!$B$13-VERI_TABANI!$B$14)*VERI_TABANI!G25) + (VERI_TABANI!D25*C22*(VERI_TABANI!$B$13-VERI_TABANI!$B$15)*VERI_TABANI!G25) + IF(ABS(IF(ISNUMBER(SEARCH("Var", D22)), 1, IF(ISNUMBER(SEARCH("Gri", D22)), -1, 0)))=1, VERI_TABANI!E25*(1-0.928)*0.00206091519919798*VERI_TABANI!G25, 0)) + ((MIN(VERI_TABANI!D26, VERI_TABANI!D26*B22)*VERI_TABANI!$B$7 + MAX(0, VERI_TABANI!D26*B22-VERI_TABANI!D26)*VERI_TABANI!$B$8) + (MIN(MAX(0, VERI_TABANI!D26-VERI_TABANI!D26*B22), VERI_TABANI!D26*C22)*VERI_TABANI!$B$7 + MAX(0, VERI_TABANI!D26*C22-MAX(0, VERI_TABANI!D26-VERI_TABANI!D26*B22))*VERI_TABANI!$B$8) + IF(ABS(IF(ISNUMBER(SEARCH("Var", D22)), 1, IF(ISNUMBER(SEARCH("Gri", D22)), -1, 0)))=1, VERI_TABANI!E26*(1-0.928)*VERI_TABANI!$B$9, 0) + (VERI_TABANI!D26*B22*(VERI_TABANI!$B$13-VERI_TABANI!$B$14)*VERI_TABANI!G26) + (VERI_TABANI!D26*C22*(VERI_TABANI!$B$13-VERI_TABANI!$B$15)*VERI_TABANI!G26) + IF(ABS(IF(ISNUMBER(SEARCH("Var", D22)), 1, IF(ISNUMBER(SEARCH("Gri", D22)), -1, 0)))=1, VERI_TABANI!E26*(1-0.928)*0.00206091519919798*VERI_TABANI!G26, 0)) + ((MIN(VERI_TABANI!D27, VERI_TABANI!D27*B22)*VERI_TABANI!$B$7 + MAX(0, VERI_TABANI!D27*B22-VERI_TABANI!D27)*VERI_TABANI!$B$8) + (MIN(MAX(0, VERI_TABANI!D27-VERI_TABANI!D27*B22), VERI_TABANI!D27*C22)*VERI_TABANI!$B$7 + MAX(0, VERI_TABANI!D27*C22-MAX(0, VERI_TABANI!D27-VERI_TABANI!D27*B22))*VERI_TABANI!$B$8) + IF(ABS(IF(ISNUMBER(SEARCH("Var", D22)), 1, IF(ISNUMBER(SEARCH("Gri", D22)), -1, 0)))=1, VERI_TABANI!E27*(1-0.928)*VERI_TABANI!$B$9, 0) + (VERI_TABANI!D27*B22*(VERI_TABANI!$B$13-VERI_TABANI!$B$14)*VERI_TABANI!G27) + (VERI_TABANI!D27*C22*(VERI_TABANI!$B$13-VERI_TABANI!$B$15)*VERI_TABANI!G27) + IF(ABS(IF(ISNUMBER(SEARCH("Var", D22)), 1, IF(ISNUMBER(SEARCH("Gri", D22)), -1, 0)))=1, VERI_TABANI!E27*(1-0.928)*0.00206091519919798*VERI_TABANI!G27, 0)) + ((MIN(VERI_TABANI!D28, VERI_TABANI!D28*B22)*VERI_TABANI!$B$7 + MAX(0, VERI_TABANI!D28*B22-VERI_TABANI!D28)*VERI_TABANI!$B$8) + (MIN(MAX(0, VERI_TABANI!D28-VERI_TABANI!D28*B22), VERI_TABANI!D28*C22)*VERI_TABANI!$B$7 + MAX(0, VERI_TABANI!D28*C22-MAX(0, VERI_TABANI!D28-VERI_TABANI!D28*B22))*VERI_TABANI!$B$8) + IF(ABS(IF(ISNUMBER(SEARCH("Var", D22)), 1, IF(ISNUMBER(SEARCH("Gri", D22)), -1, 0)))=1, VERI_TABANI!E28*(1-0.928)*VERI_TABANI!$B$9, 0) + (VERI_TABANI!D28*B22*(VERI_TABANI!$B$13-VERI_TABANI!$B$14)*VERI_TABANI!G28) + (VERI_TABANI!D28*C22*(VERI_TABANI!$B$13-VERI_TABANI!$B$15)*VERI_TABANI!G28) + IF(ABS(IF(ISNUMBER(SEARCH("Var", D22)), 1, IF(ISNUMBER(SEARCH("Gri", D22)), -1, 0)))=1, VERI_TABANI!E28*(1-0.928)*0.00206091519919798*VERI_TABANI!G28, 0))) | H22: =(((VERI_TABANI!D23*B22*(VERI_TABANI!$B$13-VERI_TABANI!$B$14)) + (VERI_TABANI!D23*C22*(VERI_TABANI!$B$13-VERI_TABANI!$B$15)) + IF(ISNUMBER(SEARCH("Var", D22)), VERI_TABANI!F23*(0.00202-VERI_TABANI!$B$16), IF(ISNUMBER(SEARCH("Gri", D22)), VERI_TABANI!F23*(0.00202-VERI_TABANI!$B$17), 0))) + ((VERI_TABANI!D24*B22*(VERI_TABANI!$B$13-VERI_TABANI!$B$14)) + (VERI_TABANI!D24*C22*(VERI_TABANI!$B$13-VERI_TABANI!$B$15)) + IF(ISNUMBER(SEARCH("Var", D22)), VERI_TABANI!F24*(0.00202-VERI_TABANI!$B$16), IF(ISNUMBER(SEARCH("Gri", D22)), VERI_TABANI!F24*(0.00202-VERI_TABANI!$B$17), 0))) + ((VERI_TABANI!D25*B22*(VERI_TABANI!$B$13-VERI_TABANI!$B$14)) + (VERI_TABANI!D25*C22*(VERI_TABANI!$B$13-VERI_TABANI!$B$15)) + IF(ISNUMBER(SEARCH("Var", D22)), VERI_TABANI!F25*(0.00202-VERI_TABANI!$B$16), IF(ISNUMBER(SEARCH("Gri", D22)), VERI_TABANI!F25*(0.00202-VERI_TABANI!$B$17), 0))) + ((VERI_TABANI!D26*B22*(VERI_TABANI!$B$13-VERI_TABANI!$B$14)) + (VERI_TABANI!D26*C22*(VERI_TABANI!$B$13-VERI_TABANI!$B$15)) + IF(ISNUMBER(SEARCH("Var", D22)), VERI_TABANI!F26*(0.00202-VERI_TABANI!$B$16), IF(ISNUMBER(SEARCH("Gri", D22)), VERI_TABANI!F26*(0.00202-VERI_TABANI!$B$17), 0))) + ((VERI_TABANI!D27*B22*(VERI_TABANI!$B$13-VERI_TABANI!$B$14)) + (VERI_TABANI!D27*C22*(VERI_TABANI!$B$13-VERI_TABANI!$B$15)) + IF(ISNUMBER(SEARCH("Var", D22)), VERI_TABANI!F27*(0.00202-VERI_TABANI!$B$16), IF(ISNUMBER(SEARCH("Gri", D22)), VERI_TABANI!F27*(0.00202-VERI_TABANI!$B$17), 0))) + ((VERI_TABANI!D28*B22*(VERI_TABANI!$B$13-VERI_TABANI!$B$14)) + (VERI_TABANI!D28*C22*(VERI_TABANI!$B$13-VERI_TABANI!$B$15)) + IF(ISNUMBER(SEARCH("Var", D22)), VERI_TABANI!F28*(0.00202-VERI_TABANI!$B$16), IF(ISNUMBER(SEARCH("Gri", D22)), VERI_TABANI!F28*(0.00202-VERI_TABANI!$B$17), 0)))) | I22: =IFERROR(((VERI_TABANI!$D$29*B22*VERI_TABANI!$B$14 + VERI_TABANI!$D$29*C22*VERI_TABANI!$B$15 + IF(ISNUMBER(SEARCH("Var", D22)), VERI_TABANI!$F$29*VERI_TABANI!$B$16, 0))) / (((VERI_TABANI!$D$29*B22 + VERI_TABANI!$D$29*C22)*VERI_TABANI!$B$13 + IF(ISNUMBER(SEARCH("Var", D22)), VERI_TABANI!$E$29*(1-0.928)*VERI_TABANI!$B$18, 0))), 0) | J22: =IFERROR(F22/(G22/29), 0) | K22: =IF(F22>0, H22/F22, 0) | L22: =IF(F22>0, I22, 1000000000) | M22: =ABS((B22+C22)-1) | N22: =IF(F22>0, (G22/29)/F22, 0) | O22: =IF(AND((B22+C22)>=1, ISNUMBER(SEARCH("Var", D22))), F22, 1000000000) | P22: =IF(F22>0, SQRT((F22/MAX(F$5:F$886))^2 + (1 - H22/MAX(H$5:H$886))^2 + (J22/MAX(J$5:J$886))^2), 1000000000) | Q22: =IF(AND(ABS(B22-0.5)<0.01, ABS(C22-0.5)<0.01, ISNUMBER(SEARCH("Var", D22))), 1, 0) | R22: =IF(F22>0, J22, 1000000000) | S22: =IF(AND(F22<=DASHBOARD!$B$11, H22>=DASHBOARD!$B$13), G22, -1000000000000) | T22: =IF(AND(F22<=DASHBOARD!$B$11, H22>=DASHBOARD!$B$13), R22, 1000000000000) | U22: =IF(AND(F22<=DASHBOARD!$B$11, H22>=DASHBOARD!$B$13), N22, -1000000000000) | V22: =IF(AND(F22<=DASHBOARD!$B$11, H22>=DASHBOARD!$B$13), H22, -1000000000000) | W22: =IF(AND(F22<=DASHBOARD!$B$11, H22>=DASHBOARD!$B$13), K22, -1000000000000) | X22: =IF(AND(F22<=DASHBOARD!$B$11, H22>=DASHBOARD!$B$13), M22, 1000000000000) | Y22: =IF(AND(F22<=DASHBOARD!$B$10, H22>=DASHBOARD!$B$11), L22, 1000000000000) | Z22: =IF(AND(F22<=DASHBOARD!$B$10, H22>=DASHBOARD!$B$11), O22, 1000000000000) | AA22: =IF(AND(F22<=DASHBOARD!$B$10, H22>=DASHBOARD!$B$11), P22, 1000000000000) | AB22: =IF(AND(F22<=DASHBOARD!$B$10, H22>=DASHBOARD!$B$11), Q22, -1000000000000)
A23: 19 | B23: 0 | C23: 0.9 | D23: Yok (%0) | E23: =IF((B23+C23)<=1, "Tam Mahsuplaşma (≤%100)", "Kısmi Satış (>%100)") | F23: =((VERI_TABANI!$D$29*B23/VERI_TABANI!$B$29)/VERI_TABANI!$B$3)*VERI_TABANI!$B$5 + ((VERI_TABANI!$D$29*C23/VERI_TABANI!$B$29)/VERI_TABANI!$B$4)*VERI_TABANI!$B$6 + IF(ISNUMBER(SEARCH("Var", D23)), (VERI_TABANI!$F$29/VERI_TABANI!$B$29)*(VERI_TABANI!$B$10+VERI_TABANI!$B$12), 0) | G23: =(((MIN(VERI_TABANI!D23, VERI_TABANI!D23*B23)*VERI_TABANI!$B$7 + MAX(0, VERI_TABANI!D23*B23-VERI_TABANI!D23)*VERI_TABANI!$B$8) + (MIN(MAX(0, VERI_TABANI!D23-VERI_TABANI!D23*B23), VERI_TABANI!D23*C23)*VERI_TABANI!$B$7 + MAX(0, VERI_TABANI!D23*C23-MAX(0, VERI_TABANI!D23-VERI_TABANI!D23*B23))*VERI_TABANI!$B$8) + IF(ABS(IF(ISNUMBER(SEARCH("Var", D23)), 1, IF(ISNUMBER(SEARCH("Gri", D23)), -1, 0)))=1, VERI_TABANI!E23*(1-0.928)*VERI_TABANI!$B$9, 0) + (VERI_TABANI!D23*B23*(VERI_TABANI!$B$13-VERI_TABANI!$B$14)*VERI_TABANI!G23) + (VERI_TABANI!D23*C23*(VERI_TABANI!$B$13-VERI_TABANI!$B$15)*VERI_TABANI!G23) + IF(ABS(IF(ISNUMBER(SEARCH("Var", D23)), 1, IF(ISNUMBER(SEARCH("Gri", D23)), -1, 0)))=1, VERI_TABANI!E23*(1-0.928)*0.00206091519919798*VERI_TABANI!G23, 0)) + ((MIN(VERI_TABANI!D24, VERI_TABANI!D24*B23)*VERI_TABANI!$B$7 + MAX(0, VERI_TABANI!D24*B23-VERI_TABANI!D24)*VERI_TABANI!$B$8) + (MIN(MAX(0, VERI_TABANI!D24-VERI_TABANI!D24*B23), VERI_TABANI!D24*C23)*VERI_TABANI!$B$7 + MAX(0, VERI_TABANI!D24*C23-MAX(0, VERI_TABANI!D24-VERI_TABANI!D24*B23))*VERI_TABANI!$B$8) + IF(ABS(IF(ISNUMBER(SEARCH("Var", D23)), 1, IF(ISNUMBER(SEARCH("Gri", D23)), -1, 0)))=1, VERI_TABANI!E24*(1-0.928)*VERI_TABANI!$B$9, 0) + (VERI_TABANI!D24*B23*(VERI_TABANI!$B$13-VERI_TABANI!$B$14)*VERI_TABANI!G24) + (VERI_TABANI!D24*C23*(VERI_TABANI!$B$13-VERI_TABANI!$B$15)*VERI_TABANI!G24) + IF(ABS(IF(ISNUMBER(SEARCH("Var", D23)), 1, IF(ISNUMBER(SEARCH("Gri", D23)), -1, 0)))=1, VERI_TABANI!E24*(1-0.928)*0.00206091519919798*VERI_TABANI!G24, 0)) + ((MIN(VERI_TABANI!D25, VERI_TABANI!D25*B23)*VERI_TABANI!$B$7 + MAX(0, VERI_TABANI!D25*B23-VERI_TABANI!D25)*VERI_TABANI!$B$8) + (MIN(MAX(0, VERI_TABANI!D25-VERI_TABANI!D25*B23), VERI_TABANI!D25*C23)*VERI_TABANI!$B$7 + MAX(0, VERI_TABANI!D25*C23-MAX(0, VERI_TABANI!D25-VERI_TABANI!D25*B23))*VERI_TABANI!$B$8) + IF(ABS(IF(ISNUMBER(SEARCH("Var", D23)), 1, IF(ISNUMBER(SEARCH("Gri", D23)), -1, 0)))=1, VERI_TABANI!E25*(1-0.928)*VERI_TABANI!$B$9, 0) + (VERI_TABANI!D25*B23*(VERI_TABANI!$B$13-VERI_TABANI!$B$14)*VERI_TABANI!G25) + (VERI_TABANI!D25*C23*(VERI_TABANI!$B$13-VERI_TABANI!$B$15)*VERI_TABANI!G25) + IF(ABS(IF(ISNUMBER(SEARCH("Var", D23)), 1, IF(ISNUMBER(SEARCH("Gri", D23)), -1, 0)))=1, VERI_TABANI!E25*(1-0.928)*0.00206091519919798*VERI_TABANI!G25, 0)) + ((MIN(VERI_TABANI!D26, VERI_TABANI!D26*B23)*VERI_TABANI!$B$7 + MAX(0, VERI_TABANI!D26*B23-VERI_TABANI!D26)*VERI_TABANI!$B$8) + (MIN(MAX(0, VERI_TABANI!D26-VERI_TABANI!D26*B23), VERI_TABANI!D26*C23)*VERI_TABANI!$B$7 + MAX(0, VERI_TABANI!D26*C23-MAX(0, VERI_TABANI!D26-VERI_TABANI!D26*B23))*VERI_TABANI!$B$8) + IF(ABS(IF(ISNUMBER(SEARCH("Var", D23)), 1, IF(ISNUMBER(SEARCH("Gri", D23)), -1, 0)))=1, VERI_TABANI!E26*(1-0.928)*VERI_TABANI!$B$9, 0) + (VERI_TABANI!D26*B23*(VERI_TABANI!$B$13-VERI_TABANI!$B$14)*VERI_TABANI!G26) + (VERI_TABANI!D26*C23*(VERI_TABANI!$B$13-VERI_TABANI!$B$15)*VERI_TABANI!G26) + IF(ABS(IF(ISNUMBER(SEARCH("Var", D23)), 1, IF(ISNUMBER(SEARCH("Gri", D23)), -1, 0)))=1, VERI_TABANI!E26*(1-0.928)*0.00206091519919798*VERI_TABANI!G26, 0)) + ((MIN(VERI_TABANI!D27, VERI_TABANI!D27*B23)*VERI_TABANI!$B$7 + MAX(0, VERI_TABANI!D27*B23-VERI_TABANI!D27)*VERI_TABANI!$B$8) + (MIN(MAX(0, VERI_TABANI!D27-VERI_TABANI!D27*B23), VERI_TABANI!D27*C23)*VERI_TABANI!$B$7 + MAX(0, VERI_TABANI!D27*C23-MAX(0, VERI_TABANI!D27-VERI_TABANI!D27*B23))*VERI_TABANI!$B$8) + IF(ABS(IF(ISNUMBER(SEARCH("Var", D23)), 1, IF(ISNUMBER(SEARCH("Gri", D23)), -1, 0)))=1, VERI_TABANI!E27*(1-0.928)*VERI_TABANI!$B$9, 0) + (VERI_TABANI!D27*B23*(VERI_TABANI!$B$13-VERI_TABANI!$B$14)*VERI_TABANI!G27) + (VERI_TABANI!D27*C23*(VERI_TABANI!$B$13-VERI_TABANI!$B$15)*VERI_TABANI!G27) + IF(ABS(IF(ISNUMBER(SEARCH("Var", D23)), 1, IF(ISNUMBER(SEARCH("Gri", D23)), -1, 0)))=1, VERI_TABANI!E27*(1-0.928)*0.00206091519919798*VERI_TABANI!G27, 0)) + ((MIN(VERI_TABANI!D28, VERI_TABANI!D28*B23)*VERI_TABANI!$B$7 + MAX(0, VERI_TABANI!D28*B23-VERI_TABANI!D28)*VERI_TABANI!$B$8) + (MIN(MAX(0, VERI_TABANI!D28-VERI_TABANI!D28*B23), VERI_TABANI!D28*C23)*VERI_TABANI!$B$7 + MAX(0, VERI_TABANI!D28*C23-MAX(0, VERI_TABANI!D28-VERI_TABANI!D28*B23))*VERI_TABANI!$B$8) + IF(ABS(IF(ISNUMBER(SEARCH("Var", D23)), 1, IF(ISNUMBER(SEARCH("Gri", D23)), -1, 0)))=1, VERI_TABANI!E28*(1-0.928)*VERI_TABANI!$B$9, 0) + (VERI_TABANI!D28*B23*(VERI_TABANI!$B$13-VERI_TABANI!$B$14)*VERI_TABANI!G28) + (VERI_TABANI!D28*C23*(VERI_TABANI!$B$13-VERI_TABANI!$B$15)*VERI_TABANI!G28) + IF(ABS(IF(ISNUMBER(SEARCH("Var", D23)), 1, IF(ISNUMBER(SEARCH("Gri", D23)), -1, 0)))=1, VERI_TABANI!E28*(1-0.928)*0.00206091519919798*VERI_TABANI!G28, 0))) | H23: =(((VERI_TABANI!D23*B23*(VERI_TABANI!$B$13-VERI_TABANI!$B$14)) + (VERI_TABANI!D23*C23*(VERI_TABANI!$B$13-VERI_TABANI!$B$15)) + IF(ISNUMBER(SEARCH("Var", D23)), VERI_TABANI!F23*(0.00202-VERI_TABANI!$B$16), IF(ISNUMBER(SEARCH("Gri", D23)), VERI_TABANI!F23*(0.00202-VERI_TABANI!$B$17), 0))) + ((VERI_TABANI!D24*B23*(VERI_TABANI!$B$13-VERI_TABANI!$B$14)) + (VERI_TABANI!D24*C23*(VERI_TABANI!$B$13-VERI_TABANI!$B$15)) + IF(ISNUMBER(SEARCH("Var", D23)), VERI_TABANI!F24*(0.00202-VERI_TABANI!$B$16), IF(ISNUMBER(SEARCH("Gri", D23)), VERI_TABANI!F24*(0.00202-VERI_TABANI!$B$17), 0))) + ((VERI_TABANI!D25*B23*(VERI_TABANI!$B$13-VERI_TABANI!$B$14)) + (VERI_TABANI!D25*C23*(VERI_TABANI!$B$13-VERI_TABANI!$B$15)) + IF(ISNUMBER(SEARCH("Var", D23)), VERI_TABANI!F25*(0.00202-VERI_TABANI!$B$16), IF(ISNUMBER(SEARCH("Gri", D23)), VERI_TABANI!F25*(0.00202-VERI_TABANI!$B$17), 0))) + ((VERI_TABANI!D26*B23*(VERI_TABANI!$B$13-VERI_TABANI!$B$14)) + (VERI_TABANI!D26*C23*(VERI_TABANI!$B$13-VERI_TABANI!$B$15)) + IF(ISNUMBER(SEARCH("Var", D23)), VERI_TABANI!F26*(0.00202-VERI_TABANI!$B$16), IF(ISNUMBER(SEARCH("Gri", D23)), VERI_TABANI!F26*(0.00202-VERI_TABANI!$B$17), 0))) + ((VERI_TABANI!D27*B23*(VERI_TABANI!$B$13-VERI_TABANI!$B$14)) + (VERI_TABANI!D27*C23*(VERI_TABANI!$B$13-VERI_TABANI!$B$15)) + IF(ISNUMBER(SEARCH("Var", D23)), VERI_TABANI!F27*(0.00202-VERI_TABANI!$B$16), IF(ISNUMBER(SEARCH("Gri", D23)), VERI_TABANI!F27*(0.00202-VERI_TABANI!$B$17), 0))) + ((VERI_TABANI!D28*B23*(VERI_TABANI!$B$13-VERI_TABANI!$B$14)) + (VERI_TABANI!D28*C23*(VERI_TABANI!$B$13-VERI_TABANI!$B$15)) + IF(ISNUMBER(SEARCH("Var", D23)), VERI_TABANI!F28*(0.00202-VERI_TABANI!$B$16), IF(ISNUMBER(SEARCH("Gri", D23)), VERI_TABANI!F28*(0.00202-VERI_TABANI!$B$17), 0)))) | I23: =IFERROR(((VERI_TABANI!$D$29*B23*VERI_TABANI!$B$14 + VERI_TABANI!$D$29*C23*VERI_TABANI!$B$15 + IF(ISNUMBER(SEARCH("Var", D23)), VERI_TABANI!$F$29*VERI_TABANI!$B$16, 0))) / (((VERI_TABANI!$D$29*B23 + VERI_TABANI!$D$29*C23)*VERI_TABANI!$B$13 + IF(ISNUMBER(SEARCH("Var", D23)), VERI_TABANI!$E$29*(1-0.928)*VERI_TABANI!$B$18, 0))), 0) | J23: =IFERROR(F23/(G23/29), 0) | K23: =IF(F23>0, H23/F23, 0) | L23: =IF(F23>0, I23, 1000000000) | M23: =ABS((B23+C23)-1) | N23: =IF(F23>0, (G23/29)/F23, 0) | O23: =IF(AND((B23+C23)>=1, ISNUMBER(SEARCH("Var", D23))), F23, 1000000000) | P23: =IF(F23>0, SQRT((F23/MAX(F$5:F$886))^2 + (1 - H23/MAX(H$5:H$886))^2 + (J23/MAX(J$5:J$886))^2), 1000000000) | Q23: =IF(AND(ABS(B23-0.5)<0.01, ABS(C23-0.5)<0.01, ISNUMBER(SEARCH("Var", D23))), 1, 0) | R23: =IF(F23>0, J23, 1000000000) | S23: =IF(AND(F23<=DASHBOARD!$B$11, H23>=DASHBOARD!$B$13), G23, -1000000000000) | T23: =IF(AND(F23<=DASHBOARD!$B$11, H23>=DASHBOARD!$B$13), R23, 1000000000000) | U23: =IF(AND(F23<=DASHBOARD!$B$11, H23>=DASHBOARD!$B$13), N23, -1000000000000) | V23: =IF(AND(F23<=DASHBOARD!$B$11, H23>=DASHBOARD!$B$13), H23, -1000000000000) | W23: =IF(AND(F23<=DASHBOARD!$B$11, H23>=DASHBOARD!$B$13), K23, -1000000000000) | X23: =IF(AND(F23<=DASHBOARD!$B$11, H23>=DASHBOARD!$B$13), M23, 1000000000000) | Y23: =IF(AND(F23<=DASHBOARD!$B$10, H23>=DASHBOARD!$B$11), L23, 1000000000000) | Z23: =IF(AND(F23<=DASHBOARD!$B$10, H23>=DASHBOARD!$B$11), O23, 1000000000000) | AA23: =IF(AND(F23<=DASHBOARD!$B$10, H23>=DASHBOARD!$B$11), P23, 1000000000000) | AB23: =IF(AND(F23<=DASHBOARD!$B$10, H23>=DASHBOARD!$B$11), Q23, -1000000000000)
A24: 20 | B24: 0 | C24: 0.9 | D24: Var (%20) | E24: =IF((B24+C24)<=1, "Tam Mahsuplaşma (≤%100)", "Kısmi Satış (>%100)") | F24: =((VERI_TABANI!$D$29*B24/VERI_TABANI!$B$29)/VERI_TABANI!$B$3)*VERI_TABANI!$B$5 + ((VERI_TABANI!$D$29*C24/VERI_TABANI!$B$29)/VERI_TABANI!$B$4)*VERI_TABANI!$B$6 + IF(ISNUMBER(SEARCH("Var", D24)), (VERI_TABANI!$F$29/VERI_TABANI!$B$29)*(VERI_TABANI!$B$10+VERI_TABANI!$B$12), 0) | G24: =(((MIN(VERI_TABANI!D23, VERI_TABANI!D23*B24)*VERI_TABANI!$B$7 + MAX(0, VERI_TABANI!D23*B24-VERI_TABANI!D23)*VERI_TABANI!$B$8) + (MIN(MAX(0, VERI_TABANI!D23-VERI_TABANI!D23*B24), VERI_TABANI!D23*C24)*VERI_TABANI!$B$7 + MAX(0, VERI_TABANI!D23*C24-MAX(0, VERI_TABANI!D23-VERI_TABANI!D23*B24))*VERI_TABANI!$B$8) + IF(ABS(IF(ISNUMBER(SEARCH("Var", D24)), 1, IF(ISNUMBER(SEARCH("Gri", D24)), -1, 0)))=1, VERI_TABANI!E23*(1-0.928)*VERI_TABANI!$B$9, 0) + (VERI_TABANI!D23*B24*(VERI_TABANI!$B$13-VERI_TABANI!$B$14)*VERI_TABANI!G23) + (VERI_TABANI!D23*C24*(VERI_TABANI!$B$13-VERI_TABANI!$B$15)*VERI_TABANI!G23) + IF(ABS(IF(ISNUMBER(SEARCH("Var", D24)), 1, IF(ISNUMBER(SEARCH("Gri", D24)), -1, 0)))=1, VERI_TABANI!E23*(1-0.928)*0.00206091519919798*VERI_TABANI!G23, 0)) + ((MIN(VERI_TABANI!D24, VERI_TABANI!D24*B24)*VERI_TABANI!$B$7 + MAX(0, VERI_TABANI!D24*B24-VERI_TABANI!D24)*VERI_TABANI!$B$8) + (MIN(MAX(0, VERI_TABANI!D24-VERI_TABANI!D24*B24), VERI_TABANI!D24*C24)*VERI_TABANI!$B$7 + MAX(0, VERI_TABANI!D24*C24-MAX(0, VERI_TABANI!D24-VERI_TABANI!D24*B24))*VERI_TABANI!$B$8) + IF(ABS(IF(ISNUMBER(SEARCH("Var", D24)), 1, IF(ISNUMBER(SEARCH("Gri", D24)), -1, 0)))=1, VERI_TABANI!E24*(1-0.928)*VERI_TABANI!$B$9, 0) + (VERI_TABANI!D24*B24*(VERI_TABANI!$B$13-VERI_TABANI!$B$14)*VERI_TABANI!G24) + (VERI_TABANI!D24*C24*(VERI_TABANI!$B$13-VERI_TABANI!$B$15)*VERI_TABANI!G24) + IF(ABS(IF(ISNUMBER(SEARCH("Var", D24)), 1, IF(ISNUMBER(SEARCH("Gri", D24)), -1, 0)))=1, VERI_TABANI!E24*(1-0.928)*0.00206091519919798*VERI_TABANI!G24, 0)) + ((MIN(VERI_TABANI!D25, VERI_TABANI!D25*B24)*VERI_TABANI!$B$7 + MAX(0, VERI_TABANI!D25*B24-VERI_TABANI!D25)*VERI_TABANI!$B$8) + (MIN(MAX(0, VERI_TABANI!D25-VERI_TABANI!D25*B24), VERI_TABANI!D25*C24)*VERI_TABANI!$B$7 + MAX(0, VERI_TABANI!D25*C24-MAX(0, VERI_TABANI!D25-VERI_TABANI!D25*B24))*VERI_TABANI!$B$8) + IF(ABS(IF(ISNUMBER(SEARCH("Var", D24)), 1, IF(ISNUMBER(SEARCH("Gri", D24)), -1, 0)))=1, VERI_TABANI!E25*(1-0.928)*VERI_TABANI!$B$9, 0) + (VERI_TABANI!D25*B24*(VERI_TABANI!$B$13-VERI_TABANI!$B$14)*VERI_TABANI!G25) + (VERI_TABANI!D25*C24*(VERI_TABANI!$B$13-VERI_TABANI!$B$15)*VERI_TABANI!G25) + IF(ABS(IF(ISNUMBER(SEARCH("Var", D24)), 1, IF(ISNUMBER(SEARCH("Gri", D24)), -1, 0)))=1, VERI_TABANI!E25*(1-0.928)*0.00206091519919798*VERI_TABANI!G25, 0)) + ((MIN(VERI_TABANI!D26, VERI_TABANI!D26*B24)*VERI_TABANI!$B$7 + MAX(0, VERI_TABANI!D26*B24-VERI_TABANI!D26)*VERI_TABANI!$B$8) + (MIN(MAX(0, VERI_TABANI!D26-VERI_TABANI!D26*B24), VERI_TABANI!D26*C24)*VERI_TABANI!$B$7 + MAX(0, VERI_TABANI!D26*C24-MAX(0, VERI_TABANI!D26-VERI_TABANI!D26*B24))*VERI_TABANI!$B$8) + IF(ABS(IF(ISNUMBER(SEARCH("Var", D24)), 1, IF(ISNUMBER(SEARCH("Gri", D24)), -1, 0)))=1, VERI_TABANI!E26*(1-0.928)*VERI_TABANI!$B$9, 0) + (VERI_TABANI!D26*B24*(VERI_TABANI!$B$13-VERI_TABANI!$B$14)*VERI_TABANI!G26) + (VERI_TABANI!D26*C24*(VERI_TABANI!$B$13-VERI_TABANI!$B$15)*VERI_TABANI!G26) + IF(ABS(IF(ISNUMBER(SEARCH("Var", D24)), 1, IF(ISNUMBER(SEARCH("Gri", D24)), -1, 0)))=1, VERI_TABANI!E26*(1-0.928)*0.00206091519919798*VERI_TABANI!G26, 0)) + ((MIN(VERI_TABANI!D27, VERI_TABANI!D27*B24)*VERI_TABANI!$B$7 + MAX(0, VERI_TABANI!D27*B24-VERI_TABANI!D27)*VERI_TABANI!$B$8) + (MIN(MAX(0, VERI_TABANI!D27-VERI_TABANI!D27*B24), VERI_TABANI!D27*C24)*VERI_TABANI!$B$7 + MAX(0, VERI_TABANI!D27*C24-MAX(0, VERI_TABANI!D27-VERI_TABANI!D27*B24))*VERI_TABANI!$B$8) + IF(ABS(IF(ISNUMBER(SEARCH("Var", D24)), 1, IF(ISNUMBER(SEARCH("Gri", D24)), -1, 0)))=1, VERI_TABANI!E27*(1-0.928)*VERI_TABANI!$B$9, 0) + (VERI_TABANI!D27*B24*(VERI_TABANI!$B$13-VERI_TABANI!$B$14)*VERI_TABANI!G27) + (VERI_TABANI!D27*C24*(VERI_TABANI!$B$13-VERI_TABANI!$B$15)*VERI_TABANI!G27) + IF(ABS(IF(ISNUMBER(SEARCH("Var", D24)), 1, IF(ISNUMBER(SEARCH("Gri", D24)), -1, 0)))=1, VERI_TABANI!E27*(1-0.928)*0.00206091519919798*VERI_TABANI!G27, 0)) + ((MIN(VERI_TABANI!D28, VERI_TABANI!D28*B24)*VERI_TABANI!$B$7 + MAX(0, VERI_TABANI!D28*B24-VERI_TABANI!D28)*VERI_TABANI!$B$8) + (MIN(MAX(0, VERI_TABANI!D28-VERI_TABANI!D28*B24), VERI_TABANI!D28*C24)*VERI_TABANI!$B$7 + MAX(0, VERI_TABANI!D28*C24-MAX(0, VERI_TABANI!D28-VERI_TABANI!D28*B24))*VERI_TABANI!$B$8) + IF(ABS(IF(ISNUMBER(SEARCH("Var", D24)), 1, IF(ISNUMBER(SEARCH("Gri", D24)), -1, 0)))=1, VERI_TABANI!E28*(1-0.928)*VERI_TABANI!$B$9, 0) + (VERI_TABANI!D28*B24*(VERI_TABANI!$B$13-VERI_TABANI!$B$14)*VERI_TABANI!G28) + (VERI_TABANI!D28*C24*(VERI_TABANI!$B$13-VERI_TABANI!$B$15)*VERI_TABANI!G28) + IF(ABS(IF(ISNUMBER(SEARCH("Var", D24)), 1, IF(ISNUMBER(SEARCH("Gri", D24)), -1, 0)))=1, VERI_TABANI!E28*(1-0.928)*0.00206091519919798*VERI_TABANI!G28, 0))) | H24: =(((VERI_TABANI!D23*B24*(VERI_TABANI!$B$13-VERI_TABANI!$B$14)) + (VERI_TABANI!D23*C24*(VERI_TABANI!$B$13-VERI_TABANI!$B$15)) + IF(ISNUMBER(SEARCH("Var", D24)), VERI_TABANI!F23*(0.00202-VERI_TABANI!$B$16), IF(ISNUMBER(SEARCH("Gri", D24)), VERI_TABANI!F23*(0.00202-VERI_TABANI!$B$17), 0))) + ((VERI_TABANI!D24*B24*(VERI_TABANI!$B$13-VERI_TABANI!$B$14)) + (VERI_TABANI!D24*C24*(VERI_TABANI!$B$13-VERI_TABANI!$B$15)) + IF(ISNUMBER(SEARCH("Var", D24)), VERI_TABANI!F24*(0.00202-VERI_TABANI!$B$16), IF(ISNUMBER(SEARCH("Gri", D24)), VERI_TABANI!F24*(0.00202-VERI_TABANI!$B$17), 0))) + ((VERI_TABANI!D25*B24*(VERI_TABANI!$B$13-VERI_TABANI!$B$14)) + (VERI_TABANI!D25*C24*(VERI_TABANI!$B$13-VERI_TABANI!$B$15)) + IF(ISNUMBER(SEARCH("Var", D24)), VERI_TABANI!F25*(0.00202-VERI_TABANI!$B$16), IF(ISNUMBER(SEARCH("Gri", D24)), VERI_TABANI!F25*(0.00202-VERI_TABANI!$B$17), 0))) + ((VERI_TABANI!D26*B24*(VERI_TABANI!$B$13-VERI_TABANI!$B$14)) + (VERI_TABANI!D26*C24*(VERI_TABANI!$B$13-VERI_TABANI!$B$15)) + IF(ISNUMBER(SEARCH("Var", D24)), VERI_TABANI!F26*(0.00202-VERI_TABANI!$B$16), IF(ISNUMBER(SEARCH("Gri", D24)), VERI_TABANI!F26*(0.00202-VERI_TABANI!$B$17), 0))) + ((VERI_TABANI!D27*B24*(VERI_TABANI!$B$13-VERI_TABANI!$B$14)) + (VERI_TABANI!D27*C24*(VERI_TABANI!$B$13-VERI_TABANI!$B$15)) + IF(ISNUMBER(SEARCH("Var", D24)), VERI_TABANI!F27*(0.00202-VERI_TABANI!$B$16), IF(ISNUMBER(SEARCH("Gri", D24)), VERI_TABANI!F27*(0.00202-VERI_TABANI!$B$17), 0))) + ((VERI_TABANI!D28*B24*(VERI_TABANI!$B$13-VERI_TABANI!$B$14)) + (VERI_TABANI!D28*C24*(VERI_TABANI!$B$13-VERI_TABANI!$B$15)) + IF(ISNUMBER(SEARCH("Var", D24)), VERI_TABANI!F28*(0.00202-VERI_TABANI!$B$16), IF(ISNUMBER(SEARCH("Gri", D24)), VERI_TABANI!F28*(0.00202-VERI_TABANI!$B$17), 0)))) | I24: =IFERROR(((VERI_TABANI!$D$29*B24*VERI_TABANI!$B$14 + VERI_TABANI!$D$29*C24*VERI_TABANI!$B$15 + IF(ISNUMBER(SEARCH("Var", D24)), VERI_TABANI!$F$29*VERI_TABANI!$B$16, 0))) / (((VERI_TABANI!$D$29*B24 + VERI_TABANI!$D$29*C24)*VERI_TABANI!$B$13 + IF(ISNUMBER(SEARCH("Var", D24)), VERI_TABANI!$E$29*(1-0.928)*VERI_TABANI!$B$18, 0))), 0) | J24: =IFERROR(F24/(G24/29), 0) | K24: =IF(F24>0, H24/F24, 0) | L24: =IF(F24>0, I24, 1000000000) | M24: =ABS((B24+C24)-1) | N24: =IF(F24>0, (G24/29)/F24, 0) | O24: =IF(AND((B24+C24)>=1, ISNUMBER(SEARCH("Var", D24))), F24, 1000000000) | P24: =IF(F24>0, SQRT((F24/MAX(F$5:F$886))^2 + (1 - H24/MAX(H$5:H$886))^2 + (J24/MAX(J$5:J$886))^2), 1000000000) | Q24: =IF(AND(ABS(B24-0.5)<0.01, ABS(C24-0.5)<0.01, ISNUMBER(SEARCH("Var", D24))), 1, 0) | R24: =IF(F24>0, J24, 1000000000) | S24: =IF(AND(F24<=DASHBOARD!$B$11, H24>=DASHBOARD!$B$13), G24, -1000000000000) | T24: =IF(AND(F24<=DASHBOARD!$B$11, H24>=DASHBOARD!$B$13), R24, 1000000000000) | U24: =IF(AND(F24<=DASHBOARD!$B$11, H24>=DASHBOARD!$B$13), N24, -1000000000000) | V24: =IF(AND(F24<=DASHBOARD!$B$11, H24>=DASHBOARD!$B$13), H24, -1000000000000) | W24: =IF(AND(F24<=DASHBOARD!$B$11, H24>=DASHBOARD!$B$13), K24, -1000000000000) | X24: =IF(AND(F24<=DASHBOARD!$B$11, H24>=DASHBOARD!$B$13), M24, 1000000000000) | Y24: =IF(AND(F24<=DASHBOARD!$B$10, H24>=DASHBOARD!$B$11), L24, 1000000000000) | Z24: =IF(AND(F24<=DASHBOARD!$B$10, H24>=DASHBOARD!$B$11), O24, 1000000000000) | AA24: =IF(AND(F24<=DASHBOARD!$B$10, H24>=DASHBOARD!$B$11), P24, 1000000000000) | AB24: =IF(AND(F24<=DASHBOARD!$B$10, H24>=DASHBOARD!$B$11), Q24, -1000000000000)
A25: 21 | B25: 0 | C25: 1 | D25: Yok (%0) | E25: =IF((B25+C25)<=1, "Tam Mahsuplaşma (≤%100)", "Kısmi Satış (>%100)") | F25: =((VERI_TABANI!$D$29*B25/VERI_TABANI!$B$29)/VERI_TABANI!$B$3)*VERI_TABANI!$B$5 + ((VERI_TABANI!$D$29*C25/VERI_TABANI!$B$29)/VERI_TABANI!$B$4)*VERI_TABANI!$B$6 + IF(ISNUMBER(SEARCH("Var", D25)), (VERI_TABANI!$F$29/VERI_TABANI!$B$29)*(VERI_TABANI!$B$10+VERI_TABANI!$B$12), 0) | G25: =(((MIN(VERI_TABANI!D23, VERI_TABANI!D23*B25)*VERI_TABANI!$B$7 + MAX(0, VERI_TABANI!D23*B25-VERI_TABANI!D23)*VERI_TABANI!$B$8) + (MIN(MAX(0, VERI_TABANI!D23-VERI_TABANI!D23*B25), VERI_TABANI!D23*C25)*VERI_TABANI!$B$7 + MAX(0, VERI_TABANI!D23*C25-MAX(0, VERI_TABANI!D23-VERI_TABANI!D23*B25))*VERI_TABANI!$B$8) + IF(ABS(IF(ISNUMBER(SEARCH("Var", D25)), 1, IF(ISNUMBER(SEARCH("Gri", D25)), -1, 0)))=1, VERI_TABANI!E23*(1-0.928)*VERI_TABANI!$B$9, 0) + (VERI_TABANI!D23*B25*(VERI_TABANI!$B$13-VERI_TABANI!$B$14)*VERI_TABANI!G23) + (VERI_TABANI!D23*C25*(VERI_TABANI!$B$13-VERI_TABANI!$B$15)*VERI_TABANI!G23) + IF(ABS(IF(ISNUMBER(SEARCH("Var", D25)), 1, IF(ISNUMBER(SEARCH("Gri", D25)), -1, 0)))=1, VERI_TABANI!E23*(1-0.928)*0.00206091519919798*VERI_TABANI!G23, 0)) + ((MIN(VERI_TABANI!D24, VERI_TABANI!D24*B25)*VERI_TABANI!$B$7 + MAX(0, VERI_TABANI!D24*B25-VERI_TABANI!D24)*VERI_TABANI!$B$8) + (MIN(MAX(0, VERI_TABANI!D24-VERI_TABANI!D24*B25), VERI_TABANI!D24*C25)*VERI_TABANI!$B$7 + MAX(0, VERI_TABANI!D24*C25-MAX(0, VERI_TABANI!D24-VERI_TABANI!D24*B25))*VERI_TABANI!$B$8) + IF(ABS(IF(ISNUMBER(SEARCH("Var", D25)), 1, IF(ISNUMBER(SEARCH("Gri", D25)), -1, 0)))=1, VERI_TABANI!E24*(1-0.928)*VERI_TABANI!$B$9, 0) + (VERI_TABANI!D24*B25*(VERI_TABANI!$B$13-VERI_TABANI!$B$14)*VERI_TABANI!G24) + (VERI_TABANI!D24*C25*(VERI_TABANI!$B$13-VERI_TABANI!$B$15)*VERI_TABANI!G24) + IF(ABS(IF(ISNUMBER(SEARCH("Var", D25)), 1, IF(ISNUMBER(SEARCH("Gri", D25)), -1, 0)))=1, VERI_TABANI!E24*(1-0.928)*0.00206091519919798*VERI_TABANI!G24, 0)) + ((MIN(VERI_TABANI!D25, VERI_TABANI!D25*B25)*VERI_TABANI!$B$7 + MAX(0, VERI_TABANI!D25*B25-VERI_TABANI!D25)*VERI_TABANI!$B$8) + (MIN(MAX(0, VERI_TABANI!D25-VERI_TABANI!D25*B25), VERI_TABANI!D25*C25)*VERI_TABANI!$B$7 + MAX(0, VERI_TABANI!D25*C25-MAX(0, VERI_TABANI!D25-VERI_TABANI!D25*B25))*VERI_TABANI!$B$8) + IF(ABS(IF(ISNUMBER(SEARCH("Var", D25)), 1, IF(ISNUMBER(SEARCH("Gri", D25)), -1, 0)))=1, VERI_TABANI!E25*(1-0.928)*VERI_TABANI!$B$9, 0) + (VERI_TABANI!D25*B25*(VERI_TABANI!$B$13-VERI_TABANI!$B$14)*VERI_TABANI!G25) + (VERI_TABANI!D25*C25*(VERI_TABANI!$B$13-VERI_TABANI!$B$15)*VERI_TABANI!G25) + IF(ABS(IF(ISNUMBER(SEARCH("Var", D25)), 1, IF(ISNUMBER(SEARCH("Gri", D25)), -1, 0)))=1, VERI_TABANI!E25*(1-0.928)*0.00206091519919798*VERI_TABANI!G25, 0)) + ((MIN(VERI_TABANI!D26, VERI_TABANI!D26*B25)*VERI_TABANI!$B$7 + MAX(0, VERI_TABANI!D26*B25-VERI_TABANI!D26)*VERI_TABANI!$B$8) + (MIN(MAX(0, VERI_TABANI!D26-VERI_TABANI!D26*B25), VERI_TABANI!D26*C25)*VERI_TABANI!$B$7 + MAX(0, VERI_TABANI!D26*C25-MAX(0, VERI_TABANI!D26-VERI_TABANI!D26*B25))*VERI_TABANI!$B$8) + IF(ABS(IF(ISNUMBER(SEARCH("Var", D25)), 1, IF(ISNUMBER(SEARCH("Gri", D25)), -1, 0)))=1, VERI_TABANI!E26*(1-0.928)*VERI_TABANI!$B$9, 0) + (VERI_TABANI!D26*B25*(VERI_TABANI!$B$13-VERI_TABANI!$B$14)*VERI_TABANI!G26) + (VERI_TABANI!D26*C25*(VERI_TABANI!$B$13-VERI_TABANI!$B$15)*VERI_TABANI!G26) + IF(ABS(IF(ISNUMBER(SEARCH("Var", D25)), 1, IF(ISNUMBER(SEARCH("Gri", D25)), -1, 0)))=1, VERI_TABANI!E26*(1-0.928)*0.00206091519919798*VERI_TABANI!G26, 0)) + ((MIN(VERI_TABANI!D27, VERI_TABANI!D27*B25)*VERI_TABANI!$B$7 + MAX(0, VERI_TABANI!D27*B25-VERI_TABANI!D27)*VERI_TABANI!$B$8) + (MIN(MAX(0, VERI_TABANI!D27-VERI_TABANI!D27*B25), VERI_TABANI!D27*C25)*VERI_TABANI!$B$7 + MAX(0, VERI_TABANI!D27*C25-MAX(0, VERI_TABANI!D27-VERI_TABANI!D27*B25))*VERI_TABANI!$B$8) + IF(ABS(IF(ISNUMBER(SEARCH("Var", D25)), 1, IF(ISNUMBER(SEARCH("Gri", D25)), -1, 0)))=1, VERI_TABANI!E27*(1-0.928)*VERI_TABANI!$B$9, 0) + (VERI_TABANI!D27*B25*(VERI_TABANI!$B$13-VERI_TABANI!$B$14)*VERI_TABANI!G27) + (VERI_TABANI!D27*C25*(VERI_TABANI!$B$13-VERI_TABANI!$B$15)*VERI_TABANI!G27) + IF(ABS(IF(ISNUMBER(SEARCH("Var", D25)), 1, IF(ISNUMBER(SEARCH("Gri", D25)), -1, 0)))=1, VERI_TABANI!E27*(1-0.928)*0.00206091519919798*VERI_TABANI!G27, 0)) + ((MIN(VERI_TABANI!D28, VERI_TABANI!D28*B25)*VERI_TABANI!$B$7 + MAX(0, VERI_TABANI!D28*B25-VERI_TABANI!D28)*VERI_TABANI!$B$8) + (MIN(MAX(0, VERI_TABANI!D28-VERI_TABANI!D28*B25), VERI_TABANI!D28*C25)*VERI_TABANI!$B$7 + MAX(0, VERI_TABANI!D28*C25-MAX(0, VERI_TABANI!D28-VERI_TABANI!D28*B25))*VERI_TABANI!$B$8) + IF(ABS(IF(ISNUMBER(SEARCH("Var", D25)), 1, IF(ISNUMBER(SEARCH("Gri", D25)), -1, 0)))=1, VERI_TABANI!E28*(1-0.928)*VERI_TABANI!$B$9, 0) + (VERI_TABANI!D28*B25*(VERI_TABANI!$B$13-VERI_TABANI!$B$14)*VERI_TABANI!G28) + (VERI_TABANI!D28*C25*(VERI_TABANI!$B$13-VERI_TABANI!$B$15)*VERI_TABANI!G28) + IF(ABS(IF(ISNUMBER(SEARCH("Var", D25)), 1, IF(ISNUMBER(SEARCH("Gri", D25)), -1, 0)))=1, VERI_TABANI!E28*(1-0.928)*0.00206091519919798*VERI_TABANI!G28, 0))) | H25: =(((VERI_TABANI!D23*B25*(VERI_TABANI!$B$13-VERI_TABANI!$B$14)) + (VERI_TABANI!D23*C25*(VERI_TABANI!$B$13-VERI_TABANI!$B$15)) + IF(ISNUMBER(SEARCH("Var", D25)), VERI_TABANI!F23*(0.00202-VERI_TABANI!$B$16), IF(ISNUMBER(SEARCH("Gri", D25)), VERI_TABANI!F23*(0.00202-VERI_TABANI!$B$17), 0))) + ((VERI_TABANI!D24*B25*(VERI_TABANI!$B$13-VERI_TABANI!$B$14)) + (VERI_TABANI!D24*C25*(VERI_TABANI!$B$13-VERI_TABANI!$B$15)) + IF(ISNUMBER(SEARCH("Var", D25)), VERI_TABANI!F24*(0.00202-VERI_TABANI!$B$16), IF(ISNUMBER(SEARCH("Gri", D25)), VERI_TABANI!F24*(0.00202-VERI_TABANI!$B$17), 0))) + ((VERI_TABANI!D25*B25*(VERI_TABANI!$B$13-VERI_TABANI!$B$14)) + (VERI_TABANI!D25*C25*(VERI_TABANI!$B$13-VERI_TABANI!$B$15)) + IF(ISNUMBER(SEARCH("Var", D25)), VERI_TABANI!F25*(0.00202-VERI_TABANI!$B$16), IF(ISNUMBER(SEARCH("Gri", D25)), VERI_TABANI!F25*(0.00202-VERI_TABANI!$B$17), 0))) + ((VERI_TABANI!D26*B25*(VERI_TABANI!$B$13-VERI_TABANI!$B$14)) + (VERI_TABANI!D26*C25*(VERI_TABANI!$B$13-VERI_TABANI!$B$15)) + IF(ISNUMBER(SEARCH("Var", D25)), VERI_TABANI!F26*(0.00202-VERI_TABANI!$B$16), IF(ISNUMBER(SEARCH("Gri", D25)), VERI_TABANI!F26*(0.00202-VERI_TABANI!$B$17), 0))) + ((VERI_TABANI!D27*B25*(VERI_TABANI!$B$13-VERI_TABANI!$B$14)) + (VERI_TABANI!D27*C25*(VERI_TABANI!$B$13-VERI_TABANI!$B$15)) + IF(ISNUMBER(SEARCH("Var", D25)), VERI_TABANI!F27*(0.00202-VERI_TABANI!$B$16), IF(ISNUMBER(SEARCH("Gri", D25)), VERI_TABANI!F27*(0.00202-VERI_TABANI!$B$17), 0))) + ((VERI_TABANI!D28*B25*(VERI_TABANI!$B$13-VERI_TABANI!$B$14)) + (VERI_TABANI!D28*C25*(VERI_TABANI!$B$13-VERI_TABANI!$B$15)) + IF(ISNUMBER(SEARCH("Var", D25)), VERI_TABANI!F28*(0.00202-VERI_TABANI!$B$16), IF(ISNUMBER(SEARCH("Gri", D25)), VERI_TABANI!F28*(0.00202-VERI_TABANI!$B$17), 0)))) | I25: =IFERROR(((VERI_TABANI!$D$29*B25*VERI_TABANI!$B$14 + VERI_TABANI!$D$29*C25*VERI_TABANI!$B$15 + IF(ISNUMBER(SEARCH("Var", D25)), VERI_TABANI!$F$29*VERI_TABANI!$B$16, 0))) / (((VERI_TABANI!$D$29*B25 + VERI_TABANI!$D$29*C25)*VERI_TABANI!$B$13 + IF(ISNUMBER(SEARCH("Var", D25)), VERI_TABANI!$E$29*(1-0.928)*VERI_TABANI!$B$18, 0))), 0) | J25: =IFERROR(F25/(G25/29), 0) | K25: =IF(F25>0, H25/F25, 0) | L25: =IF(F25>0, I25, 1000000000) | M25: =ABS((B25+C25)-1) | N25: =IF(F25>0, (G25/29)/F25, 0) | O25: =IF(AND((B25+C25)>=1, ISNUMBER(SEARCH("Var", D25))), F25, 1000000000) | P25: =IF(F25>0, SQRT((F25/MAX(F$5:F$886))^2 + (1 - H25/MAX(H$5:H$886))^2 + (J25/MAX(J$5:J$886))^2), 1000000000) | Q25: =IF(AND(ABS(B25-0.5)<0.01, ABS(C25-0.5)<0.01, ISNUMBER(SEARCH("Var", D25))), 1, 0) | R25: =IF(F25>0, J25, 1000000000) | S25: =IF(AND(F25<=DASHBOARD!$B$11, H25>=DASHBOARD!$B$13), G25, -1000000000000) | T25: =IF(AND(F25<=DASHBOARD!$B$11, H25>=DASHBOARD!$B$13), R25, 1000000000000) | U25: =IF(AND(F25<=DASHBOARD!$B$11, H25>=DASHBOARD!$B$13), N25, -1000000000000) | V25: =IF(AND(F25<=DASHBOARD!$B$11, H25>=DASHBOARD!$B$13), H25, -1000000000000) | W25: =IF(AND(F25<=DASHBOARD!$B$11, H25>=DASHBOARD!$B$13), K25, -1000000000000) | X25: =IF(AND(F25<=DASHBOARD!$B$11, H25>=DASHBOARD!$B$13), M25, 1000000000000) | Y25: =IF(AND(F25<=DASHBOARD!$B$10, H25>=DASHBOARD!$B$11), L25, 1000000000000) | Z25: =IF(AND(F25<=DASHBOARD!$B$10, H25>=DASHBOARD!$B$11), O25, 1000000000000) | AA25: =IF(AND(F25<=DASHBOARD!$B$10, H25>=DASHBOARD!$B$11), P25, 1000000000000) | AB25: =IF(AND(F25<=DASHBOARD!$B$10, H25>=DASHBOARD!$B$11), Q25, -1000000000000)
